Workbook

Sheet Notes
A1: FirstEnergy distribution and customer costs compared with Northeast and Midwest peers, 2000–2025
A2: Prepared 2026-10-24.
A3: Measures
A4: Total costs = distribution O&M (accounts 580–598) + customer costs (accounts 901–910) + distribution depreciation and amortization (p. 336). Capital additions to distribution plant (p. 204) are reported separately and are not added to total costs, because depreciation already reflects past capital. Sales expenses (911–916), A&G, taxes and return on rate base are not included. Electric utility only. Nominal dollars unless the constant-dollar columns are filled.
A5: Per-customer values divide dollars by customers used (see data treatment 3). Group values divide group totals by group customers; Peer Medians gives the median of utility-level values.
A6: Sheets
A7: Group Results – FirstEnergy consolidated, Northeast peers and Midwest peers by year: dollars, per-customer values, constant-dollar columns, growth rates.
A8: Utility Results – each utility by year, with ranks among the 36 utilities. Includes a FirstEnergy Pennsylvania combined series (four Pennsylvania companies through 2023, FirstEnergy Pennsylvania Electric from 2024).
A9: Peer Medians – medians of utility-level per-customer values for each peer group, with FirstEnergy consolidated.
A10: Reconciliation – line items vs reported subtotals for every utility-year. Peer Groups – utilities, IDs and years. Category Map – accounts behind each measure. Assumptions – adjustable inputs. Data – inputs from PUDL.
A11: Source and version
A12: Catalyst Cooperative, Public Utility Data Liberation (PUDL), data release v2026.10.0 (datapackage created 2026-10-14T17:10:33Z; git SHA 90561c620a8292583c59b063fe7fd69f59035c24; DOI https://doi.org/10.5281/zenodo.22172378). Documentation: https://docs.catalyst.coop/pudl/en/v2026.10.0/data_sources/ferc1.html. License: CC-BY-4.0 (PUDL); underlying FERC and EIA data are U.S. Government works.
... A37: Blue text: input values from PUDL or typed labels. Black text: formulas referring only to the same sheet. Green text: formulas referring to another sheet. Yellow fill: adjustable inputs.

Sheet Group Results
A1: Distribution and customer costs per customer: FirstEnergy (consolidated) and peer groups, 2000–2025
A2: Group totals divided by group customers (dollar-weighted). Nominal dollars; constant-dollar columns fill when the GDP price index is entered on the Assumptions sheet. Total costs = distribution O&M + customer costs + distribution depreciation. Capital additions are shown separately.
A4: Year | B4: FirstEnergy: utilities | C4: FirstEnergy: customers | D4: FirstEnergy: Distribution O&M ($mm) | E4: FirstEnergy: Customer costs ($mm) | F4: FirstEnergy: Depreciation ($mm) | G4: FirstEnergy: Total costs ($mm) | H4: FirstEnergy: Capital additions ($mm) | I4: FirstEnergy: Distribution O&M per customer ($) | J4: FirstEnergy: Customer costs per customer ($) | K4: FirstEnergy: Depreciation per customer ($) | L4: FirstEnergy: Total costs per customer ($) | M4: FirstEnergy: Capital additions per customer ($) | N4: FirstEnergy: total costs per customer, constant $ | O4: FirstEnergy: capital additions per customer, constant $ | P4: Northeast peers: utilities | Q4: Northeast peers: customers | R4: Northeast peers: Distribution O&M ($mm) | S4: Northeast peers: Customer costs ($mm) | T4: Northeast peers: Depreciation ($mm) | U4: Northeast peers: Total costs ($mm) | V4: Northeast peers: Capital additions ($mm) | W4: Northeast peers: Distribution O&M per customer ($) | X4: Northeast peers: Customer costs per customer ($) | Y4: Northeast peers: Depreciation per customer ($) | Z4: Northeast peers: Total costs per customer ($) | AA4: Northeast peers: Capital additions per customer ($) | AB4: Northeast peers: total costs per customer, constant $ | AC4: Northeast peers: capital additions per customer, constant $ | AD4: Midwest peers: utilities | AE4: Midwest peers: customers | AF4: Midwest peers: Distribution O&M ($mm) | AG4: Midwest peers: Customer costs ($mm) | AH4: Midwest peers: Depreciation ($mm) | AI4: Midwest peers: Total costs ($mm) | AJ4: Midwest peers: Capital additions ($mm) | AK4: Midwest peers: Distribution O&M per customer ($) | AL4: Midwest peers: Customer costs per customer ($) | AM4: Midwest peers: Depreciation per customer ($) | AN4: Midwest peers: Total costs per customer ($) | AO4: Midwest peers: Capital additions per customer ($) | AP4: Midwest peers: total costs per customer, constant $ | AQ4: Midwest peers: capital additions per customer, constant $
A5: 2000 | B5: =COUNTIFS(Data!$A$2:$A$1006,$A5,Data!$C$2:$C$1006,"FirstEnergy") -> 10 | C5: =SUMIFS(Data!$L$2:$L$1006,Data!$A$2:$A$1006,$A5,Data!$C$2:$C$1006,"FirstEnergy") -> 5717603 | D5: =SUMIFS(Data!$E$2:$E$1006,Data!$A$2:$A$1006,$A5,Data!$C$2:$C$1006,"FirstEnergy") -> 452.5503 | E5: =SUMIFS(Data!$F$2:$F$1006,Data!$A$2:$A$1006,$A5,Data!$C$2:$C$1006,"FirstEnergy") -> 417.40168 | F5: =SUMIFS(Data!$G$2:$G$1006,Data!$A$2:$A$1006,$A5,Data!$C$2:$C$1006,"FirstEnergy") -> 313.46906 | G5: =SUMIFS(Data!$N$2:$N$1006,Data!$A$2:$A$1006,$A5,Data!$C$2:$C$1006,"FirstEnergy") -> 1183.421 | H5: =SUMIFS(Data!$H$2:$H$1006,Data!$A$2:$A$1006,$A5,Data!$C$2:$C$1006,"FirstEnergy") -> 452.52607 | I5: =IFERROR(D5*1000000/C5,"") -> 79.150355 | J5: =IFERROR(E5*1000000/C5,"") -> 73.002914 | K5: =IFERROR(F5*1000000/C5,"") -> 54.825257 | L5: =IFERROR(G5*1000000/C5,"") -> 206.97853 | M5: =IFERROR(H5*1000000/C5,"") -> 79.146116 | N5: =IFERROR(IF(OR(IFERROR(INDEX(Assumptions!$B$8:$B$33,MATCH(Assumptions!$B$5,Assumptions!$A$8:$A$33,0)),"")="",INDEX(Assumptions!$B$8:$B$33,MATCH($A5,Assumptions!$A$8:$A$33,0))=""),"",L5*IFERROR(INDEX(Assumptions!$B$8:$B$33,MATCH(Assumptions!$B$5,Assumptions!$A$8:$A$33,0)),"")/INDEX(Assumptions!$B$8:$B$33,MATCH($A5,Assumptions!$A$8:$A$33,0))),"") | O5: =IFERROR(IF(OR(IFERROR(INDEX(Assumptions!$B$8:$B$33,MATCH(Assumptions!$B$5,Assumptions!$A$8:$A$33,0)),"")="",INDEX(Assumptions!$B$8:$B$33,MATCH($A5,Assumptions!$A$8:$A$33,0))=""),"",M5*IFERROR(INDEX(Assumptions!$B$8:$B$33,MATCH(Assumptions!$B$5,Assumptions!$A$8:$A$33,0)),"")/INDEX(Assumptions!$B$8:$B$33,MATCH($A5,Assumptions!$A$8:$A$33,0))),"") | P5: =COUNTIFS(Data!$A$2:$A$1006,$A5,Data!$C$2:$C$1006,"Northeast peers") -> 12 | Q5: =SUMIFS(Data!$L$2:$L$1006,Data!$A$2:$A$1006,$A5,Data!$C$2:$C$1006,"Northeast peers") -> 11311217 | R5: =SUMIFS(Data!$E$2:$E$1006,Data!$A$2:$A$1006,$A5,Data!$C$2:$C$1006,"Northeast peers") -> 848.18644 | S5: =SUMIFS(Data!$F$2:$F$1006,Data!$A$2:$A$1006,$A5,Data!$C$2:$C$1006,"Northeast peers") -> 847.05251 | T5: =SUMIFS(Data!$G$2:$G$1006,Data!$A$2:$A$1006,$A5,Data!$C$2:$C$1006,"Northeast peers") -> 644.19853 | U5: =SUMIFS(Data!$N$2:$N$1006,Data!$A$2:$A$1006,$A5,Data!$C$2:$C$1006,"Northeast peers") -> 2339.4375 | V5: =SUMIFS(Data!$H$2:$H$1006,Data!$A$2:$A$1006,$A5,Data!$C$2:$C$1006,"Northeast peers") -> 1052.0881 | W5: =IFERROR(R5*1000000/Q5,"") -> 74.986311 | X5: =IFERROR(S5*1000000/Q5,"") -> 74.886063 | Y5: =IFERROR(T5*1000000/Q5,"") -> 56.952185 | Z5: =IFERROR(U5*1000000/Q5,"") -> 206.82456 | AA5: =IFERROR(V5*1000000/Q5,"") -> 93.012812 | AB5: =IFERROR(IF(OR(IFERROR(INDEX(Assumptions!$B$8:$B$33,MATCH(Assumptions!$B$5,Assumptions!$A$8:$A$33,0)),"")="",INDEX(Assumptions!$B$8:$B$33,MATCH($A5,Assumptions!$A$8:$A$33,0))=""),"",Z5*IFERROR(INDEX(Assumptions!$B$8:$B$33,MATCH(Assumptions!$B$5,Assumptions!$A$8:$A$33,0)),"")/INDEX(Assumptions!$B$8:$B$33,MATCH($A5,Assumptions!$A$8:$A$33,0))),"") | AC5: =IFERROR(IF(OR(IFERROR(INDEX(Assumptions!$B$8:$B$33,MATCH(Assumptions!$B$5,Assumptions!$A$8:$A$33,0)),"")="",INDEX(Assumptions!$B$8:$B$33,MATCH($A5,Assumptions!$A$8:$A$33,0))=""),"",AA5*IFERROR(INDEX(Assumptions!$B$8:$B$33,MATCH(Assumptions!$B$5,Assumptions!$A$8:$A$33,0)),"")/INDEX(Assumptions!$B$8:$B$33,MATCH($A5,Assumptions!$A$8:$A$33,0))),"") | AD5: =COUNTIFS(Data!$A$2:$A$1006,$A5,Data!$C$2:$C$1006,"Midwest peers") -> 17 | AE5: =SUMIFS(Data!$L$2:$L$1006,Data!$A$2:$A$1006,$A5,Data!$C$2:$C$1006,"Midwest peers") -> 10911721 | AF5: =SUMIFS(Data!$E$2:$E$1006,Data!$A$2:$A$1006,$A5,Data!$C$2:$C$1006,"Midwest peers") -> 784.85799 | AG5: =SUMIFS(Data!$F$2:$F$1006,Data!$A$2:$A$1006,$A5,Data!$C$2:$C$1006,"Midwest peers") -> 641.81182 | AH5: =SUMIFS(Data!$G$2:$G$1006,Data!$A$2:$A$1006,$A5,Data!$C$2:$C$1006,"Midwest peers") -> 732.8381 | AI5: =SUMIFS(Data!$N$2:$N$1006,Data!$A$2:$A$1006,$A5,Data!$C$2:$C$1006,"Midwest peers") -> 2159.5079 | AJ5: =SUMIFS(Data!$H$2:$H$1006,Data!$A$2:$A$1006,$A5,Data!$C$2:$C$1006,"Midwest peers") -> 1250.1348 | AK5: =IFERROR(AF5*1000000/AE5,"") -> 71.927975 | AL5: =IFERROR(AG5*1000000/AE5,"") -> 58.81857 | AM5: =IFERROR(AH5*1000000/AE5,"") -> 67.160634 | AN5: =IFERROR(AI5*1000000/AE5,"") -> 197.90718 | AO5: =IFERROR(AJ5*1000000/AE5,"") -> 114.56807 | AP5: =IFERROR(IF(OR(IFERROR(INDEX(Assumptions!$B$8:$B$33,MATCH(Assumptions!$B$5,Assumptions!$A$8:$A$33,0)),"")="",INDEX(Assumptions!$B$8:$B$33,MATCH($A5,Assumptions!$A$8:$A$33,0))=""),"",AN5*IFERROR(INDEX(Assumptions!$B$8:$B$33,MATCH(Assumptions!$B$5,Assumptions!$A$8:$A$33,0)),"")/INDEX(Assumptions!$B$8:$B$33,MATCH($A5,Assumptions!$A$8:$A$33,0))),"") | AQ5: =IFERROR(IF(OR(IFERROR(INDEX(Assumptions!$B$8:$B$33,MATCH(Assumptions!$B$5,Assumptions!$A$8:$A$33,0)),"")="",INDEX(Assumptions!$B$8:$B$33,MATCH($A5,Assumptions!$A$8:$A$33,0))=""),"",AO5*IFERROR(INDEX(Assumptions!$B$8:$B$33,MATCH(Assumptions!$B$5,Assumptions!$A$8:$A$33,0)),"")/INDEX(Assumptions!$B$8:$B$33,MATCH($A5,Assumptions!$A$8:$A$33,0))),"")
A6: 2001 | B6: =COUNTIFS(Data!$A$2:$A$1006,$A6,Data!$C$2:$C$1006,"FirstEnergy") -> 10 | C6: =SUMIFS(Data!$L$2:$L$1006,Data!$A$2:$A$1006,$A6,Data!$C$2:$C$1006,"FirstEnergy") -> 5786092 | D6: =SUMIFS(Data!$E$2:$E$1006,Data!$A$2:$A$1006,$A6,Data!$C$2:$C$1006,"FirstEnergy") -> 452.72893 | E6: =SUMIFS(Data!$F$2:$F$1006,Data!$A$2:$A$1006,$A6,Data!$C$2:$C$1006,"FirstEnergy") -> 296.75485 | F6: =SUMIFS(Data!$G$2:$G$1006,Data!$A$2:$A$1006,$A6,Data!$C$2:$C$1006,"FirstEnergy") -> 327.16523 | G6: =SUMIFS(Data!$N$2:$N$1006,Data!$A$2:$A$1006,$A6,Data!$C$2:$C$1006,"FirstEnergy") -> 1076.649 | H6: =SUMIFS(Data!$H$2:$H$1006,Data!$A$2:$A$1006,$A6,Data!$C$2:$C$1006,"FirstEnergy") -> 442.53223 | I6: =IFERROR(D6*1000000/C6,"") -> 78.244337 | J6: =IFERROR(E6*1000000/C6,"") -> 51.287613 | K6: =IFERROR(F6*1000000/C6,"") -> 56.543386 | L6: =IFERROR(G6*1000000/C6,"") -> 186.07534 | M6: =IFERROR(H6*1000000/C6,"") -> 76.48206 | N6: =IFERROR(IF(OR(IFERROR(INDEX(Assumptions!$B$8:$B$33,MATCH(Assumptions!$B$5,Assumptions!$A$8:$A$33,0)),"")="",INDEX(Assumptions!$B$8:$B$33,MATCH($A6,Assumptions!$A$8:$A$33,0))=""),"",L6*IFERROR(INDEX(Assumptions!$B$8:$B$33,MATCH(Assumptions!$B$5,Assumptions!$A$8:$A$33,0)),"")/INDEX(Assumptions!$B$8:$B$33,MATCH($A6,Assumptions!$A$8:$A$33,0))),"") | O6: =IFERROR(IF(OR(IFERROR(INDEX(Assumptions!$B$8:$B$33,MATCH(Assumptions!$B$5,Assumptions!$A$8:$A$33,0)),"")="",INDEX(Assumptions!$B$8:$B$33,MATCH($A6,Assumptions!$A$8:$A$33,0))=""),"",M6*IFERROR(INDEX(Assumptions!$B$8:$B$33,MATCH(Assumptions!$B$5,Assumptions!$A$8:$A$33,0)),"")/INDEX(Assumptions!$B$8:$B$33,MATCH($A6,Assumptions!$A$8:$A$33,0))),"") | P6: =COUNTIFS(Data!$A$2:$A$1006,$A6,Data!$C$2:$C$1006,"Northeast peers") -> 12 | Q6: =SUMIFS(Data!$L$2:$L$1006,Data!$A$2:$A$1006,$A6,Data!$C$2:$C$1006,"Northeast peers") -> 11714513 | R6: =SUMIFS(Data!$E$2:$E$1006,Data!$A$2:$A$1006,$A6,Data!$C$2:$C$1006,"Northeast peers") -> 969.73855 | S6: =SUMIFS(Data!$F$2:$F$1006,Data!$A$2:$A$1006,$A6,Data!$C$2:$C$1006,"Northeast peers") -> 836.00108 | T6: =SUMIFS(Data!$G$2:$G$1006,Data!$A$2:$A$1006,$A6,Data!$C$2:$C$1006,"Northeast peers") -> 660.32343 | U6: =SUMIFS(Data!$N$2:$N$1006,Data!$A$2:$A$1006,$A6,Data!$C$2:$C$1006,"Northeast peers") -> 2466.0631 | V6: =SUMIFS(Data!$H$2:$H$1006,Data!$A$2:$A$1006,$A6,Data!$C$2:$C$1006,"Northeast peers") -> 1187.3893 | W6: =IFERROR(R6*1000000/Q6,"") -> 82.780953 | X6: =IFERROR(S6*1000000/Q6,"") -> 71.364561 | Y6: =IFERROR(T6*1000000/Q6,"") -> 56.367979 | Z6: =IFERROR(U6*1000000/Q6,"") -> 210.51349 | AA6: =IFERROR(V6*1000000/Q6,"") -> 101.36054 | AB6: =IFERROR(IF(OR(IFERROR(INDEX(Assumptions!$B$8:$B$33,MATCH(Assumptions!$B$5,Assumptions!$A$8:$A$33,0)),"")="",INDEX(Assumptions!$B$8:$B$33,MATCH($A6,Assumptions!$A$8:$A$33,0))=""),"",Z6*IFERROR(INDEX(Assumptions!$B$8:$B$33,MATCH(Assumptions!$B$5,Assumptions!$A$8:$A$33,0)),"")/INDEX(Assumptions!$B$8:$B$33,MATCH($A6,Assumptions!$A$8:$A$33,0))),"") | AC6: =IFERROR(IF(OR(IFERROR(INDEX(Assumptions!$B$8:$B$33,MATCH(Assumptions!$B$5,Assumptions!$A$8:$A$33,0)),"")="",INDEX(Assumptions!$B$8:$B$33,MATCH($A6,Assumptions!$A$8:$A$33,0))=""),"",AA6*IFERROR(INDEX(Assumptions!$B$8:$B$33,MATCH(Assumptions!$B$5,Assumptions!$A$8:$A$33,0)),"")/INDEX(Assumptions!$B$8:$B$33,MATCH($A6,Assumptions!$A$8:$A$33,0))),"") | AD6: =COUNTIFS(Data!$A$2:$A$1006,$A6,Data!$C$2:$C$1006,"Midwest peers") -> 17 | AE6: =SUMIFS(Data!$L$2:$L$1006,Data!$A$2:$A$1006,$A6,Data!$C$2:$C$1006,"Midwest peers") -> 11041374 | AF6: =SUMIFS(Data!$E$2:$E$1006,Data!$A$2:$A$1006,$A6,Data!$C$2:$C$1006,"Midwest peers") -> 803.54397 | AG6: =SUMIFS(Data!$F$2:$F$1006,Data!$A$2:$A$1006,$A6,Data!$C$2:$C$1006,"Midwest peers") -> 678.32759 | AH6: =SUMIFS(Data!$G$2:$G$1006,Data!$A$2:$A$1006,$A6,Data!$C$2:$C$1006,"Midwest peers") -> 763.99208 | AI6: =SUMIFS(Data!$N$2:$N$1006,Data!$A$2:$A$1006,$A6,Data!$C$2:$C$1006,"Midwest peers") -> 2245.8636 | AJ6: =SUMIFS(Data!$H$2:$H$1006,Data!$A$2:$A$1006,$A6,Data!$C$2:$C$1006,"Midwest peers") -> 1238.9469 | AK6: =IFERROR(AF6*1000000/AE6,"") -> 72.775723 | AL6: =IFERROR(AG6*1000000/AE6,"") -> 61.435071 | AM6: =IFERROR(AH6*1000000/AE6,"") -> 69.19357 | AN6: =IFERROR(AI6*1000000/AE6,"") -> 203.40436 | AO6: =IFERROR(AJ6*1000000/AE6,"") -> 112.20949 | AP6: =IFERROR(IF(OR(IFERROR(INDEX(Assumptions!$B$8:$B$33,MATCH(Assumptions!$B$5,Assumptions!$A$8:$A$33,0)),"")="",INDEX(Assumptions!$B$8:$B$33,MATCH($A6,Assumptions!$A$8:$A$33,0))=""),"",AN6*IFERROR(INDEX(Assumptions!$B$8:$B$33,MATCH(Assumptions!$B$5,Assumptions!$A$8:$A$33,0)),"")/INDEX(Assumptions!$B$8:$B$33,MATCH($A6,Assumptions!$A$8:$A$33,0))),"") | AQ6: =IFERROR(IF(OR(IFERROR(INDEX(Assumptions!$B$8:$B$33,MATCH(Assumptions!$B$5,Assumptions!$A$8:$A$33,0)),"")="",INDEX(Assumptions!$B$8:$B$33,MATCH($A6,Assumptions!$A$8:$A$33,0))=""),"",AO6*IFERROR(INDEX(Assumptions!$B$8:$B$33,MATCH(Assumptions!$B$5,Assumptions!$A$8:$A$33,0)),"")/INDEX(Assumptions!$B$8:$B$33,MATCH($A6,Assumptions!$A$8:$A$33,0))),"")
A7: 2002 | B7: =COUNTIFS(Data!$A$2:$A$1006,$A7,Data!$C$2:$C$1006,"FirstEnergy") -> 10 | C7: =SUMIFS(Data!$L$2:$L$1006,Data!$A$2:$A$1006,$A7,Data!$C$2:$C$1006,"FirstEnergy") -> 5849398 | D7: =SUMIFS(Data!$E$2:$E$1006,Data!$A$2:$A$1006,$A7,Data!$C$2:$C$1006,"FirstEnergy") -> 445.09164 | E7: =SUMIFS(Data!$F$2:$F$1006,Data!$A$2:$A$1006,$A7,Data!$C$2:$C$1006,"FirstEnergy") -> 256.53968 | F7: =SUMIFS(Data!$G$2:$G$1006,Data!$A$2:$A$1006,$A7,Data!$C$2:$C$1006,"FirstEnergy") -> 325.16668 | G7: =SUMIFS(Data!$N$2:$N$1006,Data!$A$2:$A$1006,$A7,Data!$C$2:$C$1006,"FirstEnergy") -> 1026.798 | H7: =SUMIFS(Data!$H$2:$H$1006,Data!$A$2:$A$1006,$A7,Data!$C$2:$C$1006,"FirstEnergy") -> 410.86825 | I7: =IFERROR(D7*1000000/C7,"") -> 76.091871 | J7: =IFERROR(E7*1000000/C7,"") -> 43.85745 | K7: =IFERROR(F7*1000000/C7,"") -> 55.589768 | L7: =IFERROR(G7*1000000/C7,"") -> 175.53909 | M7: =IFERROR(H7*1000000/C7,"") -> 70.241116 | N7: =IFERROR(IF(OR(IFERROR(INDEX(Assumptions!$B$8:$B$33,MATCH(Assumptions!$B$5,Assumptions!$A$8:$A$33,0)),"")="",INDEX(Assumptions!$B$8:$B$33,MATCH($A7,Assumptions!$A$8:$A$33,0))=""),"",L7*IFERROR(INDEX(Assumptions!$B$8:$B$33,MATCH(Assumptions!$B$5,Assumptions!$A$8:$A$33,0)),"")/INDEX(Assumptions!$B$8:$B$33,MATCH($A7,Assumptions!$A$8:$A$33,0))),"") | O7: =IFERROR(IF(OR(IFERROR(INDEX(Assumptions!$B$8:$B$33,MATCH(Assumptions!$B$5,Assumptions!$A$8:$A$33,0)),"")="",INDEX(Assumptions!$B$8:$B$33,MATCH($A7,Assumptions!$A$8:$A$33,0))=""),"",M7*IFERROR(INDEX(Assumptions!$B$8:$B$33,MATCH(Assumptions!$B$5,Assumptions!$A$8:$A$33,0)),"")/INDEX(Assumptions!$B$8:$B$33,MATCH($A7,Assumptions!$A$8:$A$33,0))),"") | P7: =COUNTIFS(Data!$A$2:$A$1006,$A7,Data!$C$2:$C$1006,"Northeast peers") -> 12 | Q7: =SUMIFS(Data!$L$2:$L$1006,Data!$A$2:$A$1006,$A7,Data!$C$2:$C$1006,"Northeast peers") -> 11803407 | R7: =SUMIFS(Data!$E$2:$E$1006,Data!$A$2:$A$1006,$A7,Data!$C$2:$C$1006,"Northeast peers") -> 875.25374 | S7: =SUMIFS(Data!$F$2:$F$1006,Data!$A$2:$A$1006,$A7,Data!$C$2:$C$1006,"Northeast peers") -> 812.63265 | T7: =SUMIFS(Data!$G$2:$G$1006,Data!$A$2:$A$1006,$A7,Data!$C$2:$C$1006,"Northeast peers") -> 663.27585 | U7: =SUMIFS(Data!$N$2:$N$1006,Data!$A$2:$A$1006,$A7,Data!$C$2:$C$1006,"Northeast peers") -> 2351.1622 | V7: =SUMIFS(Data!$H$2:$H$1006,Data!$A$2:$A$1006,$A7,Data!$C$2:$C$1006,"Northeast peers") -> 1221.4337 | W7: =IFERROR(R7*1000000/Q7,"") -> 74.152635 | X7: =IFERROR(S7*1000000/Q7,"") -> 68.847295 | Y7: =IFERROR(T7*1000000/Q7,"") -> 56.193593 | Z7: =IFERROR(U7*1000000/Q7,"") -> 199.19352 | AA7: =IFERROR(V7*1000000/Q7,"") -> 103.48145 | AB7: =IFERROR(IF(OR(IFERROR(INDEX(Assumptions!$B$8:$B$33,MATCH(Assumptions!$B$5,Assumptions!$A$8:$A$33,0)),"")="",INDEX(Assumptions!$B$8:$B$33,MATCH($A7,Assumptions!$A$8:$A$33,0))=""),"",Z7*IFERROR(INDEX(Assumptions!$B$8:$B$33,MATCH(Assumptions!$B$5,Assumptions!$A$8:$A$33,0)),"")/INDEX(Assumptions!$B$8:$B$33,MATCH($A7,Assumptions!$A$8:$A$33,0))),"") | AC7: =IFERROR(IF(OR(IFERROR(INDEX(Assumptions!$B$8:$B$33,MATCH(Assumptions!$B$5,Assumptions!$A$8:$A$33,0)),"")="",INDEX(Assumptions!$B$8:$B$33,MATCH($A7,Assumptions!$A$8:$A$33,0))=""),"",AA7*IFERROR(INDEX(Assumptions!$B$8:$B$33,MATCH(Assumptions!$B$5,Assumptions!$A$8:$A$33,0)),"")/INDEX(Assumptions!$B$8:$B$33,MATCH($A7,Assumptions!$A$8:$A$33,0))),"") | AD7: =COUNTIFS(Data!$A$2:$A$1006,$A7,Data!$C$2:$C$1006,"Midwest peers") -> 16 | AE7: =SUMIFS(Data!$L$2:$L$1006,Data!$A$2:$A$1006,$A7,Data!$C$2:$C$1006,"Midwest peers") -> 9450554 | AF7: =SUMIFS(Data!$E$2:$E$1006,Data!$A$2:$A$1006,$A7,Data!$C$2:$C$1006,"Midwest peers") -> 696.7392 | AG7: =SUMIFS(Data!$F$2:$F$1006,Data!$A$2:$A$1006,$A7,Data!$C$2:$C$1006,"Midwest peers") -> 656.57887 | AH7: =SUMIFS(Data!$G$2:$G$1006,Data!$A$2:$A$1006,$A7,Data!$C$2:$C$1006,"Midwest peers") -> 687.41818 | AI7: =SUMIFS(Data!$N$2:$N$1006,Data!$A$2:$A$1006,$A7,Data!$C$2:$C$1006,"Midwest peers") -> 2040.7363 | AJ7: =SUMIFS(Data!$H$2:$H$1006,Data!$A$2:$A$1006,$A7,Data!$C$2:$C$1006,"Midwest peers") -> 1073.9155 | AK7: =IFERROR(AF7*1000000/AE7,"") -> 73.724694 | AL7: =IFERROR(AG7*1000000/AE7,"") -> 69.475173 | AM7: =IFERROR(AH7*1000000/AE7,"") -> 72.7384 | AN7: =IFERROR(AI7*1000000/AE7,"") -> 215.93827 | AO7: =IFERROR(AJ7*1000000/AE7,"") -> 113.63519 | AP7: =IFERROR(IF(OR(IFERROR(INDEX(Assumptions!$B$8:$B$33,MATCH(Assumptions!$B$5,Assumptions!$A$8:$A$33,0)),"")="",INDEX(Assumptions!$B$8:$B$33,MATCH($A7,Assumptions!$A$8:$A$33,0))=""),"",AN7*IFERROR(INDEX(Assumptions!$B$8:$B$33,MATCH(Assumptions!$B$5,Assumptions!$A$8:$A$33,0)),"")/INDEX(Assumptions!$B$8:$B$33,MATCH($A7,Assumptions!$A$8:$A$33,0))),"") | AQ7: =IFERROR(IF(OR(IFERROR(INDEX(Assumptions!$B$8:$B$33,MATCH(Assumptions!$B$5,Assumptions!$A$8:$A$33,0)),"")="",INDEX(Assumptions!$B$8:$B$33,MATCH($A7,Assumptions!$A$8:$A$33,0))=""),"",AO7*IFERROR(INDEX(Assumptions!$B$8:$B$33,MATCH(Assumptions!$B$5,Assumptions!$A$8:$A$33,0)),"")/INDEX(Assumptions!$B$8:$B$33,MATCH($A7,Assumptions!$A$8:$A$33,0))),"")
A8: 2003 | B8: =COUNTIFS(Data!$A$2:$A$1006,$A8,Data!$C$2:$C$1006,"FirstEnergy") -> 10 | C8: =SUMIFS(Data!$L$2:$L$1006,Data!$A$2:$A$1006,$A8,Data!$C$2:$C$1006,"FirstEnergy") -> 5895460 | D8: =SUMIFS(Data!$E$2:$E$1006,Data!$A$2:$A$1006,$A8,Data!$C$2:$C$1006,"FirstEnergy") -> 534.36972 | E8: =SUMIFS(Data!$F$2:$F$1006,Data!$A$2:$A$1006,$A8,Data!$C$2:$C$1006,"FirstEnergy") -> 312.91545 | F8: =SUMIFS(Data!$G$2:$G$1006,Data!$A$2:$A$1006,$A8,Data!$C$2:$C$1006,"FirstEnergy") -> 311.47871 | G8: =SUMIFS(Data!$N$2:$N$1006,Data!$A$2:$A$1006,$A8,Data!$C$2:$C$1006,"FirstEnergy") -> 1158.7639 | H8: =SUMIFS(Data!$H$2:$H$1006,Data!$A$2:$A$1006,$A8,Data!$C$2:$C$1006,"FirstEnergy") -> 448.41531 | I8: =IFERROR(D8*1000000/C8,"") -> 90.640887 | J8: =IFERROR(E8*1000000/C8,"") -> 53.07736 | K8: =IFERROR(F8*1000000/C8,"") -> 52.833656 | L8: =IFERROR(G8*1000000/C8,"") -> 196.5519 | M8: =IFERROR(H8*1000000/C8,"") -> 76.061123 | N8: =IFERROR(IF(OR(IFERROR(INDEX(Assumptions!$B$8:$B$33,MATCH(Assumptions!$B$5,Assumptions!$A$8:$A$33,0)),"")="",INDEX(Assumptions!$B$8:$B$33,MATCH($A8,Assumptions!$A$8:$A$33,0))=""),"",L8*IFERROR(INDEX(Assumptions!$B$8:$B$33,MATCH(Assumptions!$B$5,Assumptions!$A$8:$A$33,0)),"")/INDEX(Assumptions!$B$8:$B$33,MATCH($A8,Assumptions!$A$8:$A$33,0))),"") | O8: =IFERROR(IF(OR(IFERROR(INDEX(Assumptions!$B$8:$B$33,MATCH(Assumptions!$B$5,Assumptions!$A$8:$A$33,0)),"")="",INDEX(Assumptions!$B$8:$B$33,MATCH($A8,Assumptions!$A$8:$A$33,0))=""),"",M8*IFERROR(INDEX(Assumptions!$B$8:$B$33,MATCH(Assumptions!$B$5,Assumptions!$A$8:$A$33,0)),"")/INDEX(Assumptions!$B$8:$B$33,MATCH($A8,Assumptions!$A$8:$A$33,0))),"") | P8: =COUNTIFS(Data!$A$2:$A$1006,$A8,Data!$C$2:$C$1006,"Northeast peers") -> 12 | Q8: =SUMIFS(Data!$L$2:$L$1006,Data!$A$2:$A$1006,$A8,Data!$C$2:$C$1006,"Northeast peers") -> 11891572 | R8: =SUMIFS(Data!$E$2:$E$1006,Data!$A$2:$A$1006,$A8,Data!$C$2:$C$1006,"Northeast peers") -> 987.18704 | S8: =SUMIFS(Data!$F$2:$F$1006,Data!$A$2:$A$1006,$A8,Data!$C$2:$C$1006,"Northeast peers") -> 769.72625 | T8: =SUMIFS(Data!$G$2:$G$1006,Data!$A$2:$A$1006,$A8,Data!$C$2:$C$1006,"Northeast peers") -> 655.78689 | U8: =SUMIFS(Data!$N$2:$N$1006,Data!$A$2:$A$1006,$A8,Data!$C$2:$C$1006,"Northeast peers") -> 2412.7002 | V8: =SUMIFS(Data!$H$2:$H$1006,Data!$A$2:$A$1006,$A8,Data!$C$2:$C$1006,"Northeast peers") -> 1291.3414 | W8: =IFERROR(R8*1000000/Q8,"") -> 83.015689 | X8: =IFERROR(S8*1000000/Q8,"") -> 64.728721 | Y8: =IFERROR(T8*1000000/Q8,"") -> 55.147199 | Z8: =IFERROR(U8*1000000/Q8,"") -> 202.89161 | AA8: =IFERROR(V8*1000000/Q8,"") -> 108.59299 | AB8: =IFERROR(IF(OR(IFERROR(INDEX(Assumptions!$B$8:$B$33,MATCH(Assumptions!$B$5,Assumptions!$A$8:$A$33,0)),"")="",INDEX(Assumptions!$B$8:$B$33,MATCH($A8,Assumptions!$A$8:$A$33,0))=""),"",Z8*IFERROR(INDEX(Assumptions!$B$8:$B$33,MATCH(Assumptions!$B$5,Assumptions!$A$8:$A$33,0)),"")/INDEX(Assumptions!$B$8:$B$33,MATCH($A8,Assumptions!$A$8:$A$33,0))),"") | AC8: =IFERROR(IF(OR(IFERROR(INDEX(Assumptions!$B$8:$B$33,MATCH(Assumptions!$B$5,Assumptions!$A$8:$A$33,0)),"")="",INDEX(Assumptions!$B$8:$B$33,MATCH($A8,Assumptions!$A$8:$A$33,0))=""),"",AA8*IFERROR(INDEX(Assumptions!$B$8:$B$33,MATCH(Assumptions!$B$5,Assumptions!$A$8:$A$33,0)),"")/INDEX(Assumptions!$B$8:$B$33,MATCH($A8,Assumptions!$A$8:$A$33,0))),"") | AD8: =COUNTIFS(Data!$A$2:$A$1006,$A8,Data!$C$2:$C$1006,"Midwest peers") -> 16 | AE8: =SUMIFS(Data!$L$2:$L$1006,Data!$A$2:$A$1006,$A8,Data!$C$2:$C$1006,"Midwest peers") -> 9532900 | AF8: =SUMIFS(Data!$E$2:$E$1006,Data!$A$2:$A$1006,$A8,Data!$C$2:$C$1006,"Midwest peers") -> 741.83681 | AG8: =SUMIFS(Data!$F$2:$F$1006,Data!$A$2:$A$1006,$A8,Data!$C$2:$C$1006,"Midwest peers") -> 668.28068 | AH8: =SUMIFS(Data!$G$2:$G$1006,Data!$A$2:$A$1006,$A8,Data!$C$2:$C$1006,"Midwest peers") -> 717.66696 | AI8: =SUMIFS(Data!$N$2:$N$1006,Data!$A$2:$A$1006,$A8,Data!$C$2:$C$1006,"Midwest peers") -> 2127.7845 | AJ8: =SUMIFS(Data!$H$2:$H$1006,Data!$A$2:$A$1006,$A8,Data!$C$2:$C$1006,"Midwest peers") -> 1150.2861 | AK8: =IFERROR(AF8*1000000/AE8,"") -> 77.818587 | AL8: =IFERROR(AG8*1000000/AE8,"") -> 70.102559 | AM8: =IFERROR(AH8*1000000/AE8,"") -> 75.283173 | AN8: =IFERROR(AI8*1000000/AE8,"") -> 223.20432 | AO8: =IFERROR(AJ8*1000000/AE8,"") -> 120.66487 | AP8: =IFERROR(IF(OR(IFERROR(INDEX(Assumptions!$B$8:$B$33,MATCH(Assumptions!$B$5,Assumptions!$A$8:$A$33,0)),"")="",INDEX(Assumptions!$B$8:$B$33,MATCH($A8,Assumptions!$A$8:$A$33,0))=""),"",AN8*IFERROR(INDEX(Assumptions!$B$8:$B$33,MATCH(Assumptions!$B$5,Assumptions!$A$8:$A$33,0)),"")/INDEX(Assumptions!$B$8:$B$33,MATCH($A8,Assumptions!$A$8:$A$33,0))),"") | AQ8: =IFERROR(IF(OR(IFERROR(INDEX(Assumptions!$B$8:$B$33,MATCH(Assumptions!$B$5,Assumptions!$A$8:$A$33,0)),"")="",INDEX(Assumptions!$B$8:$B$33,MATCH($A8,Assumptions!$A$8:$A$33,0))=""),"",AO8*IFERROR(INDEX(Assumptions!$B$8:$B$33,MATCH(Assumptions!$B$5,Assumptions!$A$8:$A$33,0)),"")/INDEX(Assumptions!$B$8:$B$33,MATCH($A8,Assumptions!$A$8:$A$33,0))),"")
A9: 2004 | B9: =COUNTIFS(Data!$A$2:$A$1006,$A9,Data!$C$2:$C$1006,"FirstEnergy") -> 10 | C9: =SUMIFS(Data!$L$2:$L$1006,Data!$A$2:$A$1006,$A9,Data!$C$2:$C$1006,"FirstEnergy") -> 5941310 | D9: =SUMIFS(Data!$E$2:$E$1006,Data!$A$2:$A$1006,$A9,Data!$C$2:$C$1006,"FirstEnergy") -> 447.37982 | E9: =SUMIFS(Data!$F$2:$F$1006,Data!$A$2:$A$1006,$A9,Data!$C$2:$C$1006,"FirstEnergy") -> 304.58678 | F9: =SUMIFS(Data!$G$2:$G$1006,Data!$A$2:$A$1006,$A9,Data!$C$2:$C$1006,"FirstEnergy") -> 301.89728 | G9: =SUMIFS(Data!$N$2:$N$1006,Data!$A$2:$A$1006,$A9,Data!$C$2:$C$1006,"FirstEnergy") -> 1053.8639 | H9: =SUMIFS(Data!$H$2:$H$1006,Data!$A$2:$A$1006,$A9,Data!$C$2:$C$1006,"FirstEnergy") -> 517.7844 | I9: =IFERROR(D9*1000000/C9,"") -> 75.299862 | J9: =IFERROR(E9*1000000/C9,"") -> 51.265929 | K9: =IFERROR(F9*1000000/C9,"") -> 50.813252 | L9: =IFERROR(G9*1000000/C9,"") -> 177.37904 | M9: =IFERROR(H9*1000000/C9,"") -> 87.14987 | N9: =IFERROR(IF(OR(IFERROR(INDEX(Assumptions!$B$8:$B$33,MATCH(Assumptions!$B$5,Assumptions!$A$8:$A$33,0)),"")="",INDEX(Assumptions!$B$8:$B$33,MATCH($A9,Assumptions!$A$8:$A$33,0))=""),"",L9*IFERROR(INDEX(Assumptions!$B$8:$B$33,MATCH(Assumptions!$B$5,Assumptions!$A$8:$A$33,0)),"")/INDEX(Assumptions!$B$8:$B$33,MATCH($A9,Assumptions!$A$8:$A$33,0))),"") | O9: =IFERROR(IF(OR(IFERROR(INDEX(Assumptions!$B$8:$B$33,MATCH(Assumptions!$B$5,Assumptions!$A$8:$A$33,0)),"")="",INDEX(Assumptions!$B$8:$B$33,MATCH($A9,Assumptions!$A$8:$A$33,0))=""),"",M9*IFERROR(INDEX(Assumptions!$B$8:$B$33,MATCH(Assumptions!$B$5,Assumptions!$A$8:$A$33,0)),"")/INDEX(Assumptions!$B$8:$B$33,MATCH($A9,Assumptions!$A$8:$A$33,0))),"") | P9: =COUNTIFS(Data!$A$2:$A$1006,$A9,Data!$C$2:$C$1006,"Northeast peers") -> 12 | Q9: =SUMIFS(Data!$L$2:$L$1006,Data!$A$2:$A$1006,$A9,Data!$C$2:$C$1006,"Northeast peers") -> 12007423 | R9: =SUMIFS(Data!$E$2:$E$1006,Data!$A$2:$A$1006,$A9,Data!$C$2:$C$1006,"Northeast peers") -> 967.47299 | S9: =SUMIFS(Data!$F$2:$F$1006,Data!$A$2:$A$1006,$A9,Data!$C$2:$C$1006,"Northeast peers") -> 775.39309 | T9: =SUMIFS(Data!$G$2:$G$1006,Data!$A$2:$A$1006,$A9,Data!$C$2:$C$1006,"Northeast peers") -> 827.77558 | U9: =SUMIFS(Data!$N$2:$N$1006,Data!$A$2:$A$1006,$A9,Data!$C$2:$C$1006,"Northeast peers") -> 2570.6417 | V9: =SUMIFS(Data!$H$2:$H$1006,Data!$A$2:$A$1006,$A9,Data!$C$2:$C$1006,"Northeast peers") -> 1212.0515 | W9: =IFERROR(R9*1000000/Q9,"") -> 80.572908 | X9: =IFERROR(S9*1000000/Q9,"") -> 64.576145 | Y9: =IFERROR(T9*1000000/Q9,"") -> 68.938654 | Z9: =IFERROR(U9*1000000/Q9,"") -> 214.08771 | AA9: =IFERROR(V9*1000000/Q9,"") -> 100.94185 | AB9: =IFERROR(IF(OR(IFERROR(INDEX(Assumptions!$B$8:$B$33,MATCH(Assumptions!$B$5,Assumptions!$A$8:$A$33,0)),"")="",INDEX(Assumptions!$B$8:$B$33,MATCH($A9,Assumptions!$A$8:$A$33,0))=""),"",Z9*IFERROR(INDEX(Assumptions!$B$8:$B$33,MATCH(Assumptions!$B$5,Assumptions!$A$8:$A$33,0)),"")/INDEX(Assumptions!$B$8:$B$33,MATCH($A9,Assumptions!$A$8:$A$33,0))),"") | AC9: =IFERROR(IF(OR(IFERROR(INDEX(Assumptions!$B$8:$B$33,MATCH(Assumptions!$B$5,Assumptions!$A$8:$A$33,0)),"")="",INDEX(Assumptions!$B$8:$B$33,MATCH($A9,Assumptions!$A$8:$A$33,0))=""),"",AA9*IFERROR(INDEX(Assumptions!$B$8:$B$33,MATCH(Assumptions!$B$5,Assumptions!$A$8:$A$33,0)),"")/INDEX(Assumptions!$B$8:$B$33,MATCH($A9,Assumptions!$A$8:$A$33,0))),"") | AD9: =COUNTIFS(Data!$A$2:$A$1006,$A9,Data!$C$2:$C$1006,"Midwest peers") -> 16 | AE9: =SUMIFS(Data!$L$2:$L$1006,Data!$A$2:$A$1006,$A9,Data!$C$2:$C$1006,"Midwest peers") -> 9630221 | AF9: =SUMIFS(Data!$E$2:$E$1006,Data!$A$2:$A$1006,$A9,Data!$C$2:$C$1006,"Midwest peers") -> 732.37506 | AG9: =SUMIFS(Data!$F$2:$F$1006,Data!$A$2:$A$1006,$A9,Data!$C$2:$C$1006,"Midwest peers") -> 664.23152 | AH9: =SUMIFS(Data!$G$2:$G$1006,Data!$A$2:$A$1006,$A9,Data!$C$2:$C$1006,"Midwest peers") -> 756.00234 | AI9: =SUMIFS(Data!$N$2:$N$1006,Data!$A$2:$A$1006,$A9,Data!$C$2:$C$1006,"Midwest peers") -> 2152.6089 | AJ9: =SUMIFS(Data!$H$2:$H$1006,Data!$A$2:$A$1006,$A9,Data!$C$2:$C$1006,"Midwest peers") -> 1256.0857 | AK9: =IFERROR(AF9*1000000/AE9,"") -> 76.049663 | AL9: =IFERROR(AG9*1000000/AE9,"") -> 68.973653 | AM9: =IFERROR(AH9*1000000/AE9,"") -> 78.503114 | AN9: =IFERROR(AI9*1000000/AE9,"") -> 223.52643 | AO9: =IFERROR(AJ9*1000000/AE9,"") -> 130.43166 | AP9: =IFERROR(IF(OR(IFERROR(INDEX(Assumptions!$B$8:$B$33,MATCH(Assumptions!$B$5,Assumptions!$A$8:$A$33,0)),"")="",INDEX(Assumptions!$B$8:$B$33,MATCH($A9,Assumptions!$A$8:$A$33,0))=""),"",AN9*IFERROR(INDEX(Assumptions!$B$8:$B$33,MATCH(Assumptions!$B$5,Assumptions!$A$8:$A$33,0)),"")/INDEX(Assumptions!$B$8:$B$33,MATCH($A9,Assumptions!$A$8:$A$33,0))),"") | AQ9: =IFERROR(IF(OR(IFERROR(INDEX(Assumptions!$B$8:$B$33,MATCH(Assumptions!$B$5,Assumptions!$A$8:$A$33,0)),"")="",INDEX(Assumptions!$B$8:$B$33,MATCH($A9,Assumptions!$A$8:$A$33,0))=""),"",AO9*IFERROR(INDEX(Assumptions!$B$8:$B$33,MATCH(Assumptions!$B$5,Assumptions!$A$8:$A$33,0)),"")/INDEX(Assumptions!$B$8:$B$33,MATCH($A9,Assumptions!$A$8:$A$33,0))),"")
A10: 2005 | B10: =COUNTIFS(Data!$A$2:$A$1006,$A10,Data!$C$2:$C$1006,"FirstEnergy") -> 10 | C10: =SUMIFS(Data!$L$2:$L$1006,Data!$A$2:$A$1006,$A10,Data!$C$2:$C$1006,"FirstEnergy") -> 6008786 | D10: =SUMIFS(Data!$E$2:$E$1006,Data!$A$2:$A$1006,$A10,Data!$C$2:$C$1006,"FirstEnergy") -> 471.66532 | E10: =SUMIFS(Data!$F$2:$F$1006,Data!$A$2:$A$1006,$A10,Data!$C$2:$C$1006,"FirstEnergy") -> 346.40929 | F10: =SUMIFS(Data!$G$2:$G$1006,Data!$A$2:$A$1006,$A10,Data!$C$2:$C$1006,"FirstEnergy") -> 315.65434 | G10: =SUMIFS(Data!$N$2:$N$1006,Data!$A$2:$A$1006,$A10,Data!$C$2:$C$1006,"FirstEnergy") -> 1133.7289 | H10: =SUMIFS(Data!$H$2:$H$1006,Data!$A$2:$A$1006,$A10,Data!$C$2:$C$1006,"FirstEnergy") -> 680.83121 | I10: =IFERROR(D10*1000000/C10,"") -> 78.495942 | J10: =IFERROR(E10*1000000/C10,"") -> 57.650463 | K10: =IFERROR(F10*1000000/C10,"") -> 52.532131 | L10: =IFERROR(G10*1000000/C10,"") -> 188.67854 | M10: =IFERROR(H10*1000000/C10,"") -> 113.30595 | N10: =IFERROR(IF(OR(IFERROR(INDEX(Assumptions!$B$8:$B$33,MATCH(Assumptions!$B$5,Assumptions!$A$8:$A$33,0)),"")="",INDEX(Assumptions!$B$8:$B$33,MATCH($A10,Assumptions!$A$8:$A$33,0))=""),"",L10*IFERROR(INDEX(Assumptions!$B$8:$B$33,MATCH(Assumptions!$B$5,Assumptions!$A$8:$A$33,0)),"")/INDEX(Assumptions!$B$8:$B$33,MATCH($A10,Assumptions!$A$8:$A$33,0))),"") | O10: =IFERROR(IF(OR(IFERROR(INDEX(Assumptions!$B$8:$B$33,MATCH(Assumptions!$B$5,Assumptions!$A$8:$A$33,0)),"")="",INDEX(Assumptions!$B$8:$B$33,MATCH($A10,Assumptions!$A$8:$A$33,0))=""),"",M10*IFERROR(INDEX(Assumptions!$B$8:$B$33,MATCH(Assumptions!$B$5,Assumptions!$A$8:$A$33,0)),"")/INDEX(Assumptions!$B$8:$B$33,MATCH($A10,Assumptions!$A$8:$A$33,0))),"") | P10: =COUNTIFS(Data!$A$2:$A$1006,$A10,Data!$C$2:$C$1006,"Northeast peers") -> 12 | Q10: =SUMIFS(Data!$L$2:$L$1006,Data!$A$2:$A$1006,$A10,Data!$C$2:$C$1006,"Northeast peers") -> 12105214 | R10: =SUMIFS(Data!$E$2:$E$1006,Data!$A$2:$A$1006,$A10,Data!$C$2:$C$1006,"Northeast peers") -> 973.41842 | S10: =SUMIFS(Data!$F$2:$F$1006,Data!$A$2:$A$1006,$A10,Data!$C$2:$C$1006,"Northeast peers") -> 792.51232 | T10: =SUMIFS(Data!$G$2:$G$1006,Data!$A$2:$A$1006,$A10,Data!$C$2:$C$1006,"Northeast peers") -> 851.15631 | U10: =SUMIFS(Data!$N$2:$N$1006,Data!$A$2:$A$1006,$A10,Data!$C$2:$C$1006,"Northeast peers") -> 2617.087 | V10: =SUMIFS(Data!$H$2:$H$1006,Data!$A$2:$A$1006,$A10,Data!$C$2:$C$1006,"Northeast peers") -> 1428.0201 | W10: =IFERROR(R10*1000000/Q10,"") -> 80.413153 | X10: =IFERROR(S10*1000000/Q10,"") -> 65.468675 | Y10: =IFERROR(T10*1000000/Q10,"") -> 70.313198 | Z10: =IFERROR(U10*1000000/Q10,"") -> 216.19503 | AA10: =IFERROR(V10*1000000/Q10,"") -> 117.96736 | AB10: =IFERROR(IF(OR(IFERROR(INDEX(Assumptions!$B$8:$B$33,MATCH(Assumptions!$B$5,Assumptions!$A$8:$A$33,0)),"")="",INDEX(Assumptions!$B$8:$B$33,MATCH($A10,Assumptions!$A$8:$A$33,0))=""),"",Z10*IFERROR(INDEX(Assumptions!$B$8:$B$33,MATCH(Assumptions!$B$5,Assumptions!$A$8:$A$33,0)),"")/INDEX(Assumptions!$B$8:$B$33,MATCH($A10,Assumptions!$A$8:$A$33,0))),"") | AC10: =IFERROR(IF(OR(IFERROR(INDEX(Assumptions!$B$8:$B$33,MATCH(Assumptions!$B$5,Assumptions!$A$8:$A$33,0)),"")="",INDEX(Assumptions!$B$8:$B$33,MATCH($A10,Assumptions!$A$8:$A$33,0))=""),"",AA10*IFERROR(INDEX(Assumptions!$B$8:$B$33,MATCH(Assumptions!$B$5,Assumptions!$A$8:$A$33,0)),"")/INDEX(Assumptions!$B$8:$B$33,MATCH($A10,Assumptions!$A$8:$A$33,0))),"") | AD10: =COUNTIFS(Data!$A$2:$A$1006,$A10,Data!$C$2:$C$1006,"Midwest peers") -> 17 | AE10: =SUMIFS(Data!$L$2:$L$1006,Data!$A$2:$A$1006,$A10,Data!$C$2:$C$1006,"Midwest peers") -> 11556354 | AF10: =SUMIFS(Data!$E$2:$E$1006,Data!$A$2:$A$1006,$A10,Data!$C$2:$C$1006,"Midwest peers") -> 927.84981 | AG10: =SUMIFS(Data!$F$2:$F$1006,Data!$A$2:$A$1006,$A10,Data!$C$2:$C$1006,"Midwest peers") -> 758.04043 | AH10: =SUMIFS(Data!$G$2:$G$1006,Data!$A$2:$A$1006,$A10,Data!$C$2:$C$1006,"Midwest peers") -> 890.19774 | AI10: =SUMIFS(Data!$N$2:$N$1006,Data!$A$2:$A$1006,$A10,Data!$C$2:$C$1006,"Midwest peers") -> 2576.088 | AJ10: =SUMIFS(Data!$H$2:$H$1006,Data!$A$2:$A$1006,$A10,Data!$C$2:$C$1006,"Midwest peers") -> 1215.3361 | AK10: =IFERROR(AF10*1000000/AE10,"") -> 80.289148 | AL10: =IFERROR(AG10*1000000/AE10,"") -> 65.59512 | AM10: =IFERROR(AH10*1000000/AE10,"") -> 77.03102 | AN10: =IFERROR(AI10*1000000/AE10,"") -> 222.91529 | AO10: =IFERROR(AJ10*1000000/AE10,"") -> 105.16605 | AP10: =IFERROR(IF(OR(IFERROR(INDEX(Assumptions!$B$8:$B$33,MATCH(Assumptions!$B$5,Assumptions!$A$8:$A$33,0)),"")="",INDEX(Assumptions!$B$8:$B$33,MATCH($A10,Assumptions!$A$8:$A$33,0))=""),"",AN10*IFERROR(INDEX(Assumptions!$B$8:$B$33,MATCH(Assumptions!$B$5,Assumptions!$A$8:$A$33,0)),"")/INDEX(Assumptions!$B$8:$B$33,MATCH($A10,Assumptions!$A$8:$A$33,0))),"") | AQ10: =IFERROR(IF(OR(IFERROR(INDEX(Assumptions!$B$8:$B$33,MATCH(Assumptions!$B$5,Assumptions!$A$8:$A$33,0)),"")="",INDEX(Assumptions!$B$8:$B$33,MATCH($A10,Assumptions!$A$8:$A$33,0))=""),"",AO10*IFERROR(INDEX(Assumptions!$B$8:$B$33,MATCH(Assumptions!$B$5,Assumptions!$A$8:$A$33,0)),"")/INDEX(Assumptions!$B$8:$B$33,MATCH($A10,Assumptions!$A$8:$A$33,0))),"")
A11: 2006 | B11: =COUNTIFS(Data!$A$2:$A$1006,$A11,Data!$C$2:$C$1006,"FirstEnergy") -> 10 | C11: =SUMIFS(Data!$L$2:$L$1006,Data!$A$2:$A$1006,$A11,Data!$C$2:$C$1006,"FirstEnergy") -> 6027692 | D11: =SUMIFS(Data!$E$2:$E$1006,Data!$A$2:$A$1006,$A11,Data!$C$2:$C$1006,"FirstEnergy") -> 467.88616 | E11: =SUMIFS(Data!$F$2:$F$1006,Data!$A$2:$A$1006,$A11,Data!$C$2:$C$1006,"FirstEnergy") -> 351.45234 | F11: =SUMIFS(Data!$G$2:$G$1006,Data!$A$2:$A$1006,$A11,Data!$C$2:$C$1006,"FirstEnergy") -> 338.70169 | G11: =SUMIFS(Data!$N$2:$N$1006,Data!$A$2:$A$1006,$A11,Data!$C$2:$C$1006,"FirstEnergy") -> 1158.0402 | H11: =SUMIFS(Data!$H$2:$H$1006,Data!$A$2:$A$1006,$A11,Data!$C$2:$C$1006,"FirstEnergy") -> 678.01388 | I11: =IFERROR(D11*1000000/C11,"") -> 77.622771 | J11: =IFERROR(E11*1000000/C11,"") -> 58.306287 | K11: =IFERROR(F11*1000000/C11,"") -> 56.190942 | L11: =IFERROR(G11*1000000/C11,"") -> 192.12 | M11: =IFERROR(H11*1000000/C11,"") -> 112.48317 | N11: =IFERROR(IF(OR(IFERROR(INDEX(Assumptions!$B$8:$B$33,MATCH(Assumptions!$B$5,Assumptions!$A$8:$A$33,0)),"")="",INDEX(Assumptions!$B$8:$B$33,MATCH($A11,Assumptions!$A$8:$A$33,0))=""),"",L11*IFERROR(INDEX(Assumptions!$B$8:$B$33,MATCH(Assumptions!$B$5,Assumptions!$A$8:$A$33,0)),"")/INDEX(Assumptions!$B$8:$B$33,MATCH($A11,Assumptions!$A$8:$A$33,0))),"") | O11: =IFERROR(IF(OR(IFERROR(INDEX(Assumptions!$B$8:$B$33,MATCH(Assumptions!$B$5,Assumptions!$A$8:$A$33,0)),"")="",INDEX(Assumptions!$B$8:$B$33,MATCH($A11,Assumptions!$A$8:$A$33,0))=""),"",M11*IFERROR(INDEX(Assumptions!$B$8:$B$33,MATCH(Assumptions!$B$5,Assumptions!$A$8:$A$33,0)),"")/INDEX(Assumptions!$B$8:$B$33,MATCH($A11,Assumptions!$A$8:$A$33,0))),"") | P11: =COUNTIFS(Data!$A$2:$A$1006,$A11,Data!$C$2:$C$1006,"Northeast peers") -> 12 | Q11: =SUMIFS(Data!$L$2:$L$1006,Data!$A$2:$A$1006,$A11,Data!$C$2:$C$1006,"Northeast peers") -> 12195157 | R11: =SUMIFS(Data!$E$2:$E$1006,Data!$A$2:$A$1006,$A11,Data!$C$2:$C$1006,"Northeast peers") -> 1051.2267 | S11: =SUMIFS(Data!$F$2:$F$1006,Data!$A$2:$A$1006,$A11,Data!$C$2:$C$1006,"Northeast peers") -> 840.74935 | T11: =SUMIFS(Data!$G$2:$G$1006,Data!$A$2:$A$1006,$A11,Data!$C$2:$C$1006,"Northeast peers") -> 884.8069 | U11: =SUMIFS(Data!$N$2:$N$1006,Data!$A$2:$A$1006,$A11,Data!$C$2:$C$1006,"Northeast peers") -> 2776.783 | V11: =SUMIFS(Data!$H$2:$H$1006,Data!$A$2:$A$1006,$A11,Data!$C$2:$C$1006,"Northeast peers") -> 1721.5166 | W11: =IFERROR(R11*1000000/Q11,"") -> 86.200343 | X11: =IFERROR(S11*1000000/Q11,"") -> 68.941248 | Y11: =IFERROR(T11*1000000/Q11,"") -> 72.553958 | Z11: =IFERROR(U11*1000000/Q11,"") -> 227.69555 | AA11: =IFERROR(V11*1000000/Q11,"") -> 141.16395 | AB11: =IFERROR(IF(OR(IFERROR(INDEX(Assumptions!$B$8:$B$33,MATCH(Assumptions!$B$5,Assumptions!$A$8:$A$33,0)),"")="",INDEX(Assumptions!$B$8:$B$33,MATCH($A11,Assumptions!$A$8:$A$33,0))=""),"",Z11*IFERROR(INDEX(Assumptions!$B$8:$B$33,MATCH(Assumptions!$B$5,Assumptions!$A$8:$A$33,0)),"")/INDEX(Assumptions!$B$8:$B$33,MATCH($A11,Assumptions!$A$8:$A$33,0))),"") | AC11: =IFERROR(IF(OR(IFERROR(INDEX(Assumptions!$B$8:$B$33,MATCH(Assumptions!$B$5,Assumptions!$A$8:$A$33,0)),"")="",INDEX(Assumptions!$B$8:$B$33,MATCH($A11,Assumptions!$A$8:$A$33,0))=""),"",AA11*IFERROR(INDEX(Assumptions!$B$8:$B$33,MATCH(Assumptions!$B$5,Assumptions!$A$8:$A$33,0)),"")/INDEX(Assumptions!$B$8:$B$33,MATCH($A11,Assumptions!$A$8:$A$33,0))),"") | AD11: =COUNTIFS(Data!$A$2:$A$1006,$A11,Data!$C$2:$C$1006,"Midwest peers") -> 17 | AE11: =SUMIFS(Data!$L$2:$L$1006,Data!$A$2:$A$1006,$A11,Data!$C$2:$C$1006,"Midwest peers") -> 11551752 | AF11: =SUMIFS(Data!$E$2:$E$1006,Data!$A$2:$A$1006,$A11,Data!$C$2:$C$1006,"Midwest peers") -> 974.54212 | AG11: =SUMIFS(Data!$F$2:$F$1006,Data!$A$2:$A$1006,$A11,Data!$C$2:$C$1006,"Midwest peers") -> 830.81704 | AH11: =SUMIFS(Data!$G$2:$G$1006,Data!$A$2:$A$1006,$A11,Data!$C$2:$C$1006,"Midwest peers") -> 927.84153 | AI11: =SUMIFS(Data!$N$2:$N$1006,Data!$A$2:$A$1006,$A11,Data!$C$2:$C$1006,"Midwest peers") -> 2733.2007 | AJ11: =SUMIFS(Data!$H$2:$H$1006,Data!$A$2:$A$1006,$A11,Data!$C$2:$C$1006,"Midwest peers") -> 1423.3923 | AK11: =IFERROR(AF11*1000000/AE11,"") -> 84.363144 | AL11: =IFERROR(AG11*1000000/AE11,"") -> 71.921301 | AM11: =IFERROR(AH11*1000000/AE11,"") -> 80.320417 | AN11: =IFERROR(AI11*1000000/AE11,"") -> 236.60486 | AO11: =IFERROR(AJ11*1000000/AE11,"") -> 123.21874 | AP11: =IFERROR(IF(OR(IFERROR(INDEX(Assumptions!$B$8:$B$33,MATCH(Assumptions!$B$5,Assumptions!$A$8:$A$33,0)),"")="",INDEX(Assumptions!$B$8:$B$33,MATCH($A11,Assumptions!$A$8:$A$33,0))=""),"",AN11*IFERROR(INDEX(Assumptions!$B$8:$B$33,MATCH(Assumptions!$B$5,Assumptions!$A$8:$A$33,0)),"")/INDEX(Assumptions!$B$8:$B$33,MATCH($A11,Assumptions!$A$8:$A$33,0))),"") | AQ11: =IFERROR(IF(OR(IFERROR(INDEX(Assumptions!$B$8:$B$33,MATCH(Assumptions!$B$5,Assumptions!$A$8:$A$33,0)),"")="",INDEX(Assumptions!$B$8:$B$33,MATCH($A11,Assumptions!$A$8:$A$33,0))=""),"",AO11*IFERROR(INDEX(Assumptions!$B$8:$B$33,MATCH(Assumptions!$B$5,Assumptions!$A$8:$A$33,0)),"")/INDEX(Assumptions!$B$8:$B$33,MATCH($A11,Assumptions!$A$8:$A$33,0))),"")
A12: 2007 | B12: =COUNTIFS(Data!$A$2:$A$1006,$A12,Data!$C$2:$C$1006,"FirstEnergy") -> 10 | C12: =SUMIFS(Data!$L$2:$L$1006,Data!$A$2:$A$1006,$A12,Data!$C$2:$C$1006,"FirstEnergy") -> 6053941 | D12: =SUMIFS(Data!$E$2:$E$1006,Data!$A$2:$A$1006,$A12,Data!$C$2:$C$1006,"FirstEnergy") -> 506.78771 | E12: =SUMIFS(Data!$F$2:$F$1006,Data!$A$2:$A$1006,$A12,Data!$C$2:$C$1006,"FirstEnergy") -> 379.46568 | F12: =SUMIFS(Data!$G$2:$G$1006,Data!$A$2:$A$1006,$A12,Data!$C$2:$C$1006,"FirstEnergy") -> 351.10258 | G12: =SUMIFS(Data!$N$2:$N$1006,Data!$A$2:$A$1006,$A12,Data!$C$2:$C$1006,"FirstEnergy") -> 1237.356 | H12: =SUMIFS(Data!$H$2:$H$1006,Data!$A$2:$A$1006,$A12,Data!$C$2:$C$1006,"FirstEnergy") -> 684.49441 | I12: =IFERROR(D12*1000000/C12,"") -> 83.712033 | J12: =IFERROR(E12*1000000/C12,"") -> 62.680769 | K12: =IFERROR(F12*1000000/C12,"") -> 57.995706 | L12: =IFERROR(G12*1000000/C12,"") -> 204.38851 | M12: =IFERROR(H12*1000000/C12,"") -> 113.06592 | N12: =IFERROR(IF(OR(IFERROR(INDEX(Assumptions!$B$8:$B$33,MATCH(Assumptions!$B$5,Assumptions!$A$8:$A$33,0)),"")="",INDEX(Assumptions!$B$8:$B$33,MATCH($A12,Assumptions!$A$8:$A$33,0))=""),"",L12*IFERROR(INDEX(Assumptions!$B$8:$B$33,MATCH(Assumptions!$B$5,Assumptions!$A$8:$A$33,0)),"")/INDEX(Assumptions!$B$8:$B$33,MATCH($A12,Assumptions!$A$8:$A$33,0))),"") | O12: =IFERROR(IF(OR(IFERROR(INDEX(Assumptions!$B$8:$B$33,MATCH(Assumptions!$B$5,Assumptions!$A$8:$A$33,0)),"")="",INDEX(Assumptions!$B$8:$B$33,MATCH($A12,Assumptions!$A$8:$A$33,0))=""),"",M12*IFERROR(INDEX(Assumptions!$B$8:$B$33,MATCH(Assumptions!$B$5,Assumptions!$A$8:$A$33,0)),"")/INDEX(Assumptions!$B$8:$B$33,MATCH($A12,Assumptions!$A$8:$A$33,0))),"") | P12: =COUNTIFS(Data!$A$2:$A$1006,$A12,Data!$C$2:$C$1006,"Northeast peers") -> 12 | Q12: =SUMIFS(Data!$L$2:$L$1006,Data!$A$2:$A$1006,$A12,Data!$C$2:$C$1006,"Northeast peers") -> 12271387 | R12: =SUMIFS(Data!$E$2:$E$1006,Data!$A$2:$A$1006,$A12,Data!$C$2:$C$1006,"Northeast peers") -> 1091.6722 | S12: =SUMIFS(Data!$F$2:$F$1006,Data!$A$2:$A$1006,$A12,Data!$C$2:$C$1006,"Northeast peers") -> 1031.7015 | T12: =SUMIFS(Data!$G$2:$G$1006,Data!$A$2:$A$1006,$A12,Data!$C$2:$C$1006,"Northeast peers") -> 903.5284 | U12: =SUMIFS(Data!$N$2:$N$1006,Data!$A$2:$A$1006,$A12,Data!$C$2:$C$1006,"Northeast peers") -> 3026.9021 | V12: =SUMIFS(Data!$H$2:$H$1006,Data!$A$2:$A$1006,$A12,Data!$C$2:$C$1006,"Northeast peers") -> 1642.4438 | W12: =IFERROR(R12*1000000/Q12,"") -> 88.960785 | X12: =IFERROR(S12*1000000/Q12,"") -> 84.073747 | Y12: =IFERROR(T12*1000000/Q12,"") -> 73.628873 | Z12: =IFERROR(U12*1000000/Q12,"") -> 246.66341 | AA12: =IFERROR(V12*1000000/Q12,"") -> 133.84337 | AB12: =IFERROR(IF(OR(IFERROR(INDEX(Assumptions!$B$8:$B$33,MATCH(Assumptions!$B$5,Assumptions!$A$8:$A$33,0)),"")="",INDEX(Assumptions!$B$8:$B$33,MATCH($A12,Assumptions!$A$8:$A$33,0))=""),"",Z12*IFERROR(INDEX(Assumptions!$B$8:$B$33,MATCH(Assumptions!$B$5,Assumptions!$A$8:$A$33,0)),"")/INDEX(Assumptions!$B$8:$B$33,MATCH($A12,Assumptions!$A$8:$A$33,0))),"") | AC12: =IFERROR(IF(OR(IFERROR(INDEX(Assumptions!$B$8:$B$33,MATCH(Assumptions!$B$5,Assumptions!$A$8:$A$33,0)),"")="",INDEX(Assumptions!$B$8:$B$33,MATCH($A12,Assumptions!$A$8:$A$33,0))=""),"",AA12*IFERROR(INDEX(Assumptions!$B$8:$B$33,MATCH(Assumptions!$B$5,Assumptions!$A$8:$A$33,0)),"")/INDEX(Assumptions!$B$8:$B$33,MATCH($A12,Assumptions!$A$8:$A$33,0))),"") | AD12: =COUNTIFS(Data!$A$2:$A$1006,$A12,Data!$C$2:$C$1006,"Midwest peers") -> 17 | AE12: =SUMIFS(Data!$L$2:$L$1006,Data!$A$2:$A$1006,$A12,Data!$C$2:$C$1006,"Midwest peers") -> 11607120 | AF12: =SUMIFS(Data!$E$2:$E$1006,Data!$A$2:$A$1006,$A12,Data!$C$2:$C$1006,"Midwest peers") -> 1044.1054 | AG12: =SUMIFS(Data!$F$2:$F$1006,Data!$A$2:$A$1006,$A12,Data!$C$2:$C$1006,"Midwest peers") -> 875.56601 | AH12: =SUMIFS(Data!$G$2:$G$1006,Data!$A$2:$A$1006,$A12,Data!$C$2:$C$1006,"Midwest peers") -> 953.26703 | AI12: =SUMIFS(Data!$N$2:$N$1006,Data!$A$2:$A$1006,$A12,Data!$C$2:$C$1006,"Midwest peers") -> 2872.9384 | AJ12: =SUMIFS(Data!$H$2:$H$1006,Data!$A$2:$A$1006,$A12,Data!$C$2:$C$1006,"Midwest peers") -> 1494.5061 | AK12: =IFERROR(AF12*1000000/AE12,"") -> 89.953873 | AL12: =IFERROR(AG12*1000000/AE12,"") -> 75.433528 | AM12: =IFERROR(AH12*1000000/AE12,"") -> 82.127783 | AN12: =IFERROR(AI12*1000000/AE12,"") -> 247.51518 | AO12: =IFERROR(AJ12*1000000/AE12,"") -> 128.75771 | AP12: =IFERROR(IF(OR(IFERROR(INDEX(Assumptions!$B$8:$B$33,MATCH(Assumptions!$B$5,Assumptions!$A$8:$A$33,0)),"")="",INDEX(Assumptions!$B$8:$B$33,MATCH($A12,Assumptions!$A$8:$A$33,0))=""),"",AN12*IFERROR(INDEX(Assumptions!$B$8:$B$33,MATCH(Assumptions!$B$5,Assumptions!$A$8:$A$33,0)),"")/INDEX(Assumptions!$B$8:$B$33,MATCH($A12,Assumptions!$A$8:$A$33,0))),"") | AQ12: =IFERROR(IF(OR(IFERROR(INDEX(Assumptions!$B$8:$B$33,MATCH(Assumptions!$B$5,Assumptions!$A$8:$A$33,0)),"")="",INDEX(Assumptions!$B$8:$B$33,MATCH($A12,Assumptions!$A$8:$A$33,0))=""),"",AO12*IFERROR(INDEX(Assumptions!$B$8:$B$33,MATCH(Assumptions!$B$5,Assumptions!$A$8:$A$33,0)),"")/INDEX(Assumptions!$B$8:$B$33,MATCH($A12,Assumptions!$A$8:$A$33,0))),"")
A13: 2008 | B13: =COUNTIFS(Data!$A$2:$A$1006,$A13,Data!$C$2:$C$1006,"FirstEnergy") -> 10 | C13: =SUMIFS(Data!$L$2:$L$1006,Data!$A$2:$A$1006,$A13,Data!$C$2:$C$1006,"FirstEnergy") -> 6069675 | D13: =SUMIFS(Data!$E$2:$E$1006,Data!$A$2:$A$1006,$A13,Data!$C$2:$C$1006,"FirstEnergy") -> 521.29043 | E13: =SUMIFS(Data!$F$2:$F$1006,Data!$A$2:$A$1006,$A13,Data!$C$2:$C$1006,"FirstEnergy") -> 400.12271 | F13: =SUMIFS(Data!$G$2:$G$1006,Data!$A$2:$A$1006,$A13,Data!$C$2:$C$1006,"FirstEnergy") -> 372.24394 | G13: =SUMIFS(Data!$N$2:$N$1006,Data!$A$2:$A$1006,$A13,Data!$C$2:$C$1006,"FirstEnergy") -> 1293.6571 | H13: =SUMIFS(Data!$H$2:$H$1006,Data!$A$2:$A$1006,$A13,Data!$C$2:$C$1006,"FirstEnergy") -> 804.06991 | I13: =IFERROR(D13*1000000/C13,"") -> 85.884406 | J13: =IFERROR(E13*1000000/C13,"") -> 65.921603 | K13: =IFERROR(F13*1000000/C13,"") -> 61.32848 | L13: =IFERROR(G13*1000000/C13,"") -> 213.13449 | M13: =IFERROR(H13*1000000/C13,"") -> 132.47331 | N13: =IFERROR(IF(OR(IFERROR(INDEX(Assumptions!$B$8:$B$33,MATCH(Assumptions!$B$5,Assumptions!$A$8:$A$33,0)),"")="",INDEX(Assumptions!$B$8:$B$33,MATCH($A13,Assumptions!$A$8:$A$33,0))=""),"",L13*IFERROR(INDEX(Assumptions!$B$8:$B$33,MATCH(Assumptions!$B$5,Assumptions!$A$8:$A$33,0)),"")/INDEX(Assumptions!$B$8:$B$33,MATCH($A13,Assumptions!$A$8:$A$33,0))),"") | O13: =IFERROR(IF(OR(IFERROR(INDEX(Assumptions!$B$8:$B$33,MATCH(Assumptions!$B$5,Assumptions!$A$8:$A$33,0)),"")="",INDEX(Assumptions!$B$8:$B$33,MATCH($A13,Assumptions!$A$8:$A$33,0))=""),"",M13*IFERROR(INDEX(Assumptions!$B$8:$B$33,MATCH(Assumptions!$B$5,Assumptions!$A$8:$A$33,0)),"")/INDEX(Assumptions!$B$8:$B$33,MATCH($A13,Assumptions!$A$8:$A$33,0))),"") | P13: =COUNTIFS(Data!$A$2:$A$1006,$A13,Data!$C$2:$C$1006,"Northeast peers") -> 12 | Q13: =SUMIFS(Data!$L$2:$L$1006,Data!$A$2:$A$1006,$A13,Data!$C$2:$C$1006,"Northeast peers") -> 12308890 | R13: =SUMIFS(Data!$E$2:$E$1006,Data!$A$2:$A$1006,$A13,Data!$C$2:$C$1006,"Northeast peers") -> 1144.0037 | S13: =SUMIFS(Data!$F$2:$F$1006,Data!$A$2:$A$1006,$A13,Data!$C$2:$C$1006,"Northeast peers") -> 1218.2577 | T13: =SUMIFS(Data!$G$2:$G$1006,Data!$A$2:$A$1006,$A13,Data!$C$2:$C$1006,"Northeast peers") -> 896.96806 | U13: =SUMIFS(Data!$N$2:$N$1006,Data!$A$2:$A$1006,$A13,Data!$C$2:$C$1006,"Northeast peers") -> 3259.2295 | V13: =SUMIFS(Data!$H$2:$H$1006,Data!$A$2:$A$1006,$A13,Data!$C$2:$C$1006,"Northeast peers") -> 1907.8548 | W13: =IFERROR(R13*1000000/Q13,"") -> 92.94126 | X13: =IFERROR(S13*1000000/Q13,"") -> 98.973803 | Y13: =IFERROR(T13*1000000/Q13,"") -> 72.871564 | Z13: =IFERROR(U13*1000000/Q13,"") -> 264.78663 | AA13: =IFERROR(V13*1000000/Q13,"") -> 154.99812 | AB13: =IFERROR(IF(OR(IFERROR(INDEX(Assumptions!$B$8:$B$33,MATCH(Assumptions!$B$5,Assumptions!$A$8:$A$33,0)),"")="",INDEX(Assumptions!$B$8:$B$33,MATCH($A13,Assumptions!$A$8:$A$33,0))=""),"",Z13*IFERROR(INDEX(Assumptions!$B$8:$B$33,MATCH(Assumptions!$B$5,Assumptions!$A$8:$A$33,0)),"")/INDEX(Assumptions!$B$8:$B$33,MATCH($A13,Assumptions!$A$8:$A$33,0))),"") | AC13: =IFERROR(IF(OR(IFERROR(INDEX(Assumptions!$B$8:$B$33,MATCH(Assumptions!$B$5,Assumptions!$A$8:$A$33,0)),"")="",INDEX(Assumptions!$B$8:$B$33,MATCH($A13,Assumptions!$A$8:$A$33,0))=""),"",AA13*IFERROR(INDEX(Assumptions!$B$8:$B$33,MATCH(Assumptions!$B$5,Assumptions!$A$8:$A$33,0)),"")/INDEX(Assumptions!$B$8:$B$33,MATCH($A13,Assumptions!$A$8:$A$33,0))),"") | AD13: =COUNTIFS(Data!$A$2:$A$1006,$A13,Data!$C$2:$C$1006,"Midwest peers") -> 17 | AE13: =SUMIFS(Data!$L$2:$L$1006,Data!$A$2:$A$1006,$A13,Data!$C$2:$C$1006,"Midwest peers") -> 11646245 | AF13: =SUMIFS(Data!$E$2:$E$1006,Data!$A$2:$A$1006,$A13,Data!$C$2:$C$1006,"Midwest peers") -> 1118.3942 | AG13: =SUMIFS(Data!$F$2:$F$1006,Data!$A$2:$A$1006,$A13,Data!$C$2:$C$1006,"Midwest peers") -> 981.83744 | AH13: =SUMIFS(Data!$G$2:$G$1006,Data!$A$2:$A$1006,$A13,Data!$C$2:$C$1006,"Midwest peers") -> 986.11572 | AI13: =SUMIFS(Data!$N$2:$N$1006,Data!$A$2:$A$1006,$A13,Data!$C$2:$C$1006,"Midwest peers") -> 3086.3474 | AJ13: =SUMIFS(Data!$H$2:$H$1006,Data!$A$2:$A$1006,$A13,Data!$C$2:$C$1006,"Midwest peers") -> 1805.4703 | AK13: =IFERROR(AF13*1000000/AE13,"") -> 96.030454 | AL13: =IFERROR(AG13*1000000/AE13,"") -> 84.305064 | AM13: =IFERROR(AH13*1000000/AE13,"") -> 84.672417 | AN13: =IFERROR(AI13*1000000/AE13,"") -> 265.00794 | AO13: =IFERROR(AJ13*1000000/AE13,"") -> 155.02596 | AP13: =IFERROR(IF(OR(IFERROR(INDEX(Assumptions!$B$8:$B$33,MATCH(Assumptions!$B$5,Assumptions!$A$8:$A$33,0)),"")="",INDEX(Assumptions!$B$8:$B$33,MATCH($A13,Assumptions!$A$8:$A$33,0))=""),"",AN13*IFERROR(INDEX(Assumptions!$B$8:$B$33,MATCH(Assumptions!$B$5,Assumptions!$A$8:$A$33,0)),"")/INDEX(Assumptions!$B$8:$B$33,MATCH($A13,Assumptions!$A$8:$A$33,0))),"") | AQ13: =IFERROR(IF(OR(IFERROR(INDEX(Assumptions!$B$8:$B$33,MATCH(Assumptions!$B$5,Assumptions!$A$8:$A$33,0)),"")="",INDEX(Assumptions!$B$8:$B$33,MATCH($A13,Assumptions!$A$8:$A$33,0))=""),"",AO13*IFERROR(INDEX(Assumptions!$B$8:$B$33,MATCH(Assumptions!$B$5,Assumptions!$A$8:$A$33,0)),"")/INDEX(Assumptions!$B$8:$B$33,MATCH($A13,Assumptions!$A$8:$A$33,0))),"")
A14: 2009 | B14: =COUNTIFS(Data!$A$2:$A$1006,$A14,Data!$C$2:$C$1006,"FirstEnergy") -> 10 | C14: =SUMIFS(Data!$L$2:$L$1006,Data!$A$2:$A$1006,$A14,Data!$C$2:$C$1006,"FirstEnergy") -> 6077048 | D14: =SUMIFS(Data!$E$2:$E$1006,Data!$A$2:$A$1006,$A14,Data!$C$2:$C$1006,"FirstEnergy") -> 401.30227 | E14: =SUMIFS(Data!$F$2:$F$1006,Data!$A$2:$A$1006,$A14,Data!$C$2:$C$1006,"FirstEnergy") -> 410.58589 | F14: =SUMIFS(Data!$G$2:$G$1006,Data!$A$2:$A$1006,$A14,Data!$C$2:$C$1006,"FirstEnergy") -> 386.98517 | G14: =SUMIFS(Data!$N$2:$N$1006,Data!$A$2:$A$1006,$A14,Data!$C$2:$C$1006,"FirstEnergy") -> 1198.8733 | H14: =SUMIFS(Data!$H$2:$H$1006,Data!$A$2:$A$1006,$A14,Data!$C$2:$C$1006,"FirstEnergy") -> 781.66791 | I14: =IFERROR(D14*1000000/C14,"") -> 66.035725 | J14: =IFERROR(E14*1000000/C14,"") -> 67.563379 | K14: =IFERROR(F14*1000000/C14,"") -> 63.679795 | L14: =IFERROR(G14*1000000/C14,"") -> 197.2789 | M14: =IFERROR(H14*1000000/C14,"") -> 128.62625 | N14: =IFERROR(IF(OR(IFERROR(INDEX(Assumptions!$B$8:$B$33,MATCH(Assumptions!$B$5,Assumptions!$A$8:$A$33,0)),"")="",INDEX(Assumptions!$B$8:$B$33,MATCH($A14,Assumptions!$A$8:$A$33,0))=""),"",L14*IFERROR(INDEX(Assumptions!$B$8:$B$33,MATCH(Assumptions!$B$5,Assumptions!$A$8:$A$33,0)),"")/INDEX(Assumptions!$B$8:$B$33,MATCH($A14,Assumptions!$A$8:$A$33,0))),"") | O14: =IFERROR(IF(OR(IFERROR(INDEX(Assumptions!$B$8:$B$33,MATCH(Assumptions!$B$5,Assumptions!$A$8:$A$33,0)),"")="",INDEX(Assumptions!$B$8:$B$33,MATCH($A14,Assumptions!$A$8:$A$33,0))=""),"",M14*IFERROR(INDEX(Assumptions!$B$8:$B$33,MATCH(Assumptions!$B$5,Assumptions!$A$8:$A$33,0)),"")/INDEX(Assumptions!$B$8:$B$33,MATCH($A14,Assumptions!$A$8:$A$33,0))),"") | P14: =COUNTIFS(Data!$A$2:$A$1006,$A14,Data!$C$2:$C$1006,"Northeast peers") -> 12 | Q14: =SUMIFS(Data!$L$2:$L$1006,Data!$A$2:$A$1006,$A14,Data!$C$2:$C$1006,"Northeast peers") -> 12347413 | R14: =SUMIFS(Data!$E$2:$E$1006,Data!$A$2:$A$1006,$A14,Data!$C$2:$C$1006,"Northeast peers") -> 1199.8235 | S14: =SUMIFS(Data!$F$2:$F$1006,Data!$A$2:$A$1006,$A14,Data!$C$2:$C$1006,"Northeast peers") -> 1199.5655 | T14: =SUMIFS(Data!$G$2:$G$1006,Data!$A$2:$A$1006,$A14,Data!$C$2:$C$1006,"Northeast peers") -> 925.53827 | U14: =SUMIFS(Data!$N$2:$N$1006,Data!$A$2:$A$1006,$A14,Data!$C$2:$C$1006,"Northeast peers") -> 3324.9273 | V14: =SUMIFS(Data!$H$2:$H$1006,Data!$A$2:$A$1006,$A14,Data!$C$2:$C$1006,"Northeast peers") -> 1904.5997 | W14: =IFERROR(R14*1000000/Q14,"") -> 97.172052 | X14: =IFERROR(S14*1000000/Q14,"") -> 97.151163 | Y14: =IFERROR(T14*1000000/Q14,"") -> 74.958072 | Z14: =IFERROR(U14*1000000/Q14,"") -> 269.28129 | AA14: =IFERROR(V14*1000000/Q14,"") -> 154.25091 | AB14: =IFERROR(IF(OR(IFERROR(INDEX(Assumptions!$B$8:$B$33,MATCH(Assumptions!$B$5,Assumptions!$A$8:$A$33,0)),"")="",INDEX(Assumptions!$B$8:$B$33,MATCH($A14,Assumptions!$A$8:$A$33,0))=""),"",Z14*IFERROR(INDEX(Assumptions!$B$8:$B$33,MATCH(Assumptions!$B$5,Assumptions!$A$8:$A$33,0)),"")/INDEX(Assumptions!$B$8:$B$33,MATCH($A14,Assumptions!$A$8:$A$33,0))),"") | AC14: =IFERROR(IF(OR(IFERROR(INDEX(Assumptions!$B$8:$B$33,MATCH(Assumptions!$B$5,Assumptions!$A$8:$A$33,0)),"")="",INDEX(Assumptions!$B$8:$B$33,MATCH($A14,Assumptions!$A$8:$A$33,0))=""),"",AA14*IFERROR(INDEX(Assumptions!$B$8:$B$33,MATCH(Assumptions!$B$5,Assumptions!$A$8:$A$33,0)),"")/INDEX(Assumptions!$B$8:$B$33,MATCH($A14,Assumptions!$A$8:$A$33,0))),"") | AD14: =COUNTIFS(Data!$A$2:$A$1006,$A14,Data!$C$2:$C$1006,"Midwest peers") -> 17 | AE14: =SUMIFS(Data!$L$2:$L$1006,Data!$A$2:$A$1006,$A14,Data!$C$2:$C$1006,"Midwest peers") -> 11645338 | AF14: =SUMIFS(Data!$E$2:$E$1006,Data!$A$2:$A$1006,$A14,Data!$C$2:$C$1006,"Midwest peers") -> 1029.1813 | AG14: =SUMIFS(Data!$F$2:$F$1006,Data!$A$2:$A$1006,$A14,Data!$C$2:$C$1006,"Midwest peers") -> 964.65181 | AH14: =SUMIFS(Data!$G$2:$G$1006,Data!$A$2:$A$1006,$A14,Data!$C$2:$C$1006,"Midwest peers") -> 1025.5352 | AI14: =SUMIFS(Data!$N$2:$N$1006,Data!$A$2:$A$1006,$A14,Data!$C$2:$C$1006,"Midwest peers") -> 3019.3684 | AJ14: =SUMIFS(Data!$H$2:$H$1006,Data!$A$2:$A$1006,$A14,Data!$C$2:$C$1006,"Midwest peers") -> 1658.7769 | AK14: =IFERROR(AF14*1000000/AE14,"") -> 88.377112 | AL14: =IFERROR(AG14*1000000/AE14,"") -> 82.835879 | AM14: =IFERROR(AH14*1000000/AE14,"") -> 88.064017 | AN14: =IFERROR(AI14*1000000/AE14,"") -> 259.27701 | AO14: =IFERROR(AJ14*1000000/AE14,"") -> 142.44128 | AP14: =IFERROR(IF(OR(IFERROR(INDEX(Assumptions!$B$8:$B$33,MATCH(Assumptions!$B$5,Assumptions!$A$8:$A$33,0)),"")="",INDEX(Assumptions!$B$8:$B$33,MATCH($A14,Assumptions!$A$8:$A$33,0))=""),"",AN14*IFERROR(INDEX(Assumptions!$B$8:$B$33,MATCH(Assumptions!$B$5,Assumptions!$A$8:$A$33,0)),"")/INDEX(Assumptions!$B$8:$B$33,MATCH($A14,Assumptions!$A$8:$A$33,0))),"") | AQ14: =IFERROR(IF(OR(IFERROR(INDEX(Assumptions!$B$8:$B$33,MATCH(Assumptions!$B$5,Assumptions!$A$8:$A$33,0)),"")="",INDEX(Assumptions!$B$8:$B$33,MATCH($A14,Assumptions!$A$8:$A$33,0))=""),"",AO14*IFERROR(INDEX(Assumptions!$B$8:$B$33,MATCH(Assumptions!$B$5,Assumptions!$A$8:$A$33,0)),"")/INDEX(Assumptions!$B$8:$B$33,MATCH($A14,Assumptions!$A$8:$A$33,0))),"")
A15: 2010 | B15: =COUNTIFS(Data!$A$2:$A$1006,$A15,Data!$C$2:$C$1006,"FirstEnergy") -> 10 | C15: =SUMIFS(Data!$L$2:$L$1006,Data!$A$2:$A$1006,$A15,Data!$C$2:$C$1006,"FirstEnergy") -> 6081211 | D15: =SUMIFS(Data!$E$2:$E$1006,Data!$A$2:$A$1006,$A15,Data!$C$2:$C$1006,"FirstEnergy") -> 398.10287 | E15: =SUMIFS(Data!$F$2:$F$1006,Data!$A$2:$A$1006,$A15,Data!$C$2:$C$1006,"FirstEnergy") -> 420.83519 | F15: =SUMIFS(Data!$G$2:$G$1006,Data!$A$2:$A$1006,$A15,Data!$C$2:$C$1006,"FirstEnergy") -> 397.05029 | G15: =SUMIFS(Data!$N$2:$N$1006,Data!$A$2:$A$1006,$A15,Data!$C$2:$C$1006,"FirstEnergy") -> 1215.9884 | H15: =SUMIFS(Data!$H$2:$H$1006,Data!$A$2:$A$1006,$A15,Data!$C$2:$C$1006,"FirstEnergy") -> 752.64907 | I15: =IFERROR(D15*1000000/C15,"") -> 65.464408 | J15: =IFERROR(E15*1000000/C15,"") -> 69.202531 | K15: =IFERROR(F15*1000000/C15,"") -> 65.29132 | L15: =IFERROR(G15*1000000/C15,"") -> 199.95826 | M15: =IFERROR(H15*1000000/C15,"") -> 123.76631 | N15: =IFERROR(IF(OR(IFERROR(INDEX(Assumptions!$B$8:$B$33,MATCH(Assumptions!$B$5,Assumptions!$A$8:$A$33,0)),"")="",INDEX(Assumptions!$B$8:$B$33,MATCH($A15,Assumptions!$A$8:$A$33,0))=""),"",L15*IFERROR(INDEX(Assumptions!$B$8:$B$33,MATCH(Assumptions!$B$5,Assumptions!$A$8:$A$33,0)),"")/INDEX(Assumptions!$B$8:$B$33,MATCH($A15,Assumptions!$A$8:$A$33,0))),"") | O15: =IFERROR(IF(OR(IFERROR(INDEX(Assumptions!$B$8:$B$33,MATCH(Assumptions!$B$5,Assumptions!$A$8:$A$33,0)),"")="",INDEX(Assumptions!$B$8:$B$33,MATCH($A15,Assumptions!$A$8:$A$33,0))=""),"",M15*IFERROR(INDEX(Assumptions!$B$8:$B$33,MATCH(Assumptions!$B$5,Assumptions!$A$8:$A$33,0)),"")/INDEX(Assumptions!$B$8:$B$33,MATCH($A15,Assumptions!$A$8:$A$33,0))),"") | P15: =COUNTIFS(Data!$A$2:$A$1006,$A15,Data!$C$2:$C$1006,"Northeast peers") -> 12 | Q15: =SUMIFS(Data!$L$2:$L$1006,Data!$A$2:$A$1006,$A15,Data!$C$2:$C$1006,"Northeast peers") -> 12396097 | R15: =SUMIFS(Data!$E$2:$E$1006,Data!$A$2:$A$1006,$A15,Data!$C$2:$C$1006,"Northeast peers") -> 1316.9264 | S15: =SUMIFS(Data!$F$2:$F$1006,Data!$A$2:$A$1006,$A15,Data!$C$2:$C$1006,"Northeast peers") -> 1468.2604 | T15: =SUMIFS(Data!$G$2:$G$1006,Data!$A$2:$A$1006,$A15,Data!$C$2:$C$1006,"Northeast peers") -> 972.72631 | U15: =SUMIFS(Data!$N$2:$N$1006,Data!$A$2:$A$1006,$A15,Data!$C$2:$C$1006,"Northeast peers") -> 3757.9131 | V15: =SUMIFS(Data!$H$2:$H$1006,Data!$A$2:$A$1006,$A15,Data!$C$2:$C$1006,"Northeast peers") -> 2068.0841 | W15: =IFERROR(R15*1000000/Q15,"") -> 106.23718 | X15: =IFERROR(S15*1000000/Q15,"") -> 118.44538 | Y15: =IFERROR(T15*1000000/Q15,"") -> 78.470369 | Z15: =IFERROR(U15*1000000/Q15,"") -> 303.15293 | AA15: =IFERROR(V15*1000000/Q15,"") -> 166.83349 | AB15: =IFERROR(IF(OR(IFERROR(INDEX(Assumptions!$B$8:$B$33,MATCH(Assumptions!$B$5,Assumptions!$A$8:$A$33,0)),"")="",INDEX(Assumptions!$B$8:$B$33,MATCH($A15,Assumptions!$A$8:$A$33,0))=""),"",Z15*IFERROR(INDEX(Assumptions!$B$8:$B$33,MATCH(Assumptions!$B$5,Assumptions!$A$8:$A$33,0)),"")/INDEX(Assumptions!$B$8:$B$33,MATCH($A15,Assumptions!$A$8:$A$33,0))),"") | AC15: =IFERROR(IF(OR(IFERROR(INDEX(Assumptions!$B$8:$B$33,MATCH(Assumptions!$B$5,Assumptions!$A$8:$A$33,0)),"")="",INDEX(Assumptions!$B$8:$B$33,MATCH($A15,Assumptions!$A$8:$A$33,0))=""),"",AA15*IFERROR(INDEX(Assumptions!$B$8:$B$33,MATCH(Assumptions!$B$5,Assumptions!$A$8:$A$33,0)),"")/INDEX(Assumptions!$B$8:$B$33,MATCH($A15,Assumptions!$A$8:$A$33,0))),"") | AD15: =COUNTIFS(Data!$A$2:$A$1006,$A15,Data!$C$2:$C$1006,"Midwest peers") -> 17 | AE15: =SUMIFS(Data!$L$2:$L$1006,Data!$A$2:$A$1006,$A15,Data!$C$2:$C$1006,"Midwest peers") -> 11649576 | AF15: =SUMIFS(Data!$E$2:$E$1006,Data!$A$2:$A$1006,$A15,Data!$C$2:$C$1006,"Midwest peers") -> 1083.768 | AG15: =SUMIFS(Data!$F$2:$F$1006,Data!$A$2:$A$1006,$A15,Data!$C$2:$C$1006,"Midwest peers") -> 1067.6422 | AH15: =SUMIFS(Data!$G$2:$G$1006,Data!$A$2:$A$1006,$A15,Data!$C$2:$C$1006,"Midwest peers") -> 1048.5392 | AI15: =SUMIFS(Data!$N$2:$N$1006,Data!$A$2:$A$1006,$A15,Data!$C$2:$C$1006,"Midwest peers") -> 3199.9493 | AJ15: =SUMIFS(Data!$H$2:$H$1006,Data!$A$2:$A$1006,$A15,Data!$C$2:$C$1006,"Midwest peers") -> 1605.9715 | AK15: =IFERROR(AF15*1000000/AE15,"") -> 93.030682 | AL15: =IFERROR(AG15*1000000/AE15,"") -> 91.646441 | AM15: =IFERROR(AH15*1000000/AE15,"") -> 90.006637 | AN15: =IFERROR(AI15*1000000/AE15,"") -> 274.68376 | AO15: =IFERROR(AJ15*1000000/AE15,"") -> 137.85664 | AP15: =IFERROR(IF(OR(IFERROR(INDEX(Assumptions!$B$8:$B$33,MATCH(Assumptions!$B$5,Assumptions!$A$8:$A$33,0)),"")="",INDEX(Assumptions!$B$8:$B$33,MATCH($A15,Assumptions!$A$8:$A$33,0))=""),"",AN15*IFERROR(INDEX(Assumptions!$B$8:$B$33,MATCH(Assumptions!$B$5,Assumptions!$A$8:$A$33,0)),"")/INDEX(Assumptions!$B$8:$B$33,MATCH($A15,Assumptions!$A$8:$A$33,0))),"") | AQ15: =IFERROR(IF(OR(IFERROR(INDEX(Assumptions!$B$8:$B$33,MATCH(Assumptions!$B$5,Assumptions!$A$8:$A$33,0)),"")="",INDEX(Assumptions!$B$8:$B$33,MATCH($A15,Assumptions!$A$8:$A$33,0))=""),"",AO15*IFERROR(INDEX(Assumptions!$B$8:$B$33,MATCH(Assumptions!$B$5,Assumptions!$A$8:$A$33,0)),"")/INDEX(Assumptions!$B$8:$B$33,MATCH($A15,Assumptions!$A$8:$A$33,0))),"")
A16: 2011 | B16: =COUNTIFS(Data!$A$2:$A$1006,$A16,Data!$C$2:$C$1006,"FirstEnergy") -> 10 | C16: =SUMIFS(Data!$L$2:$L$1006,Data!$A$2:$A$1006,$A16,Data!$C$2:$C$1006,"FirstEnergy") -> 5987117 | D16: =SUMIFS(Data!$E$2:$E$1006,Data!$A$2:$A$1006,$A16,Data!$C$2:$C$1006,"FirstEnergy") -> 443.02297 | E16: =SUMIFS(Data!$F$2:$F$1006,Data!$A$2:$A$1006,$A16,Data!$C$2:$C$1006,"FirstEnergy") -> 509.24502 | F16: =SUMIFS(Data!$G$2:$G$1006,Data!$A$2:$A$1006,$A16,Data!$C$2:$C$1006,"FirstEnergy") -> 463.59202 | G16: =SUMIFS(Data!$N$2:$N$1006,Data!$A$2:$A$1006,$A16,Data!$C$2:$C$1006,"FirstEnergy") -> 1415.86 | H16: =SUMIFS(Data!$H$2:$H$1006,Data!$A$2:$A$1006,$A16,Data!$C$2:$C$1006,"FirstEnergy") -> 700.50118 | I16: =IFERROR(D16*1000000/C16,"") -> 73.996044 | J16: =IFERROR(E16*1000000/C16,"") -> 85.0568 | K16: =IFERROR(F16*1000000/C16,"") -> 77.431595 | L16: =IFERROR(G16*1000000/C16,"") -> 236.48444 | M16: =IFERROR(H16*1000000/C16,"") -> 117.00142 | N16: =IFERROR(IF(OR(IFERROR(INDEX(Assumptions!$B$8:$B$33,MATCH(Assumptions!$B$5,Assumptions!$A$8:$A$33,0)),"")="",INDEX(Assumptions!$B$8:$B$33,MATCH($A16,Assumptions!$A$8:$A$33,0))=""),"",L16*IFERROR(INDEX(Assumptions!$B$8:$B$33,MATCH(Assumptions!$B$5,Assumptions!$A$8:$A$33,0)),"")/INDEX(Assumptions!$B$8:$B$33,MATCH($A16,Assumptions!$A$8:$A$33,0))),"") | O16: =IFERROR(IF(OR(IFERROR(INDEX(Assumptions!$B$8:$B$33,MATCH(Assumptions!$B$5,Assumptions!$A$8:$A$33,0)),"")="",INDEX(Assumptions!$B$8:$B$33,MATCH($A16,Assumptions!$A$8:$A$33,0))=""),"",M16*IFERROR(INDEX(Assumptions!$B$8:$B$33,MATCH(Assumptions!$B$5,Assumptions!$A$8:$A$33,0)),"")/INDEX(Assumptions!$B$8:$B$33,MATCH($A16,Assumptions!$A$8:$A$33,0))),"") | P16: =COUNTIFS(Data!$A$2:$A$1006,$A16,Data!$C$2:$C$1006,"Northeast peers") -> 12 | Q16: =SUMIFS(Data!$L$2:$L$1006,Data!$A$2:$A$1006,$A16,Data!$C$2:$C$1006,"Northeast peers") -> 12419140 | R16: =SUMIFS(Data!$E$2:$E$1006,Data!$A$2:$A$1006,$A16,Data!$C$2:$C$1006,"Northeast peers") -> 1368.9144 | S16: =SUMIFS(Data!$F$2:$F$1006,Data!$A$2:$A$1006,$A16,Data!$C$2:$C$1006,"Northeast peers") -> 1568.834 | T16: =SUMIFS(Data!$G$2:$G$1006,Data!$A$2:$A$1006,$A16,Data!$C$2:$C$1006,"Northeast peers") -> 1034.6011 | U16: =SUMIFS(Data!$N$2:$N$1006,Data!$A$2:$A$1006,$A16,Data!$C$2:$C$1006,"Northeast peers") -> 3972.3495 | V16: =SUMIFS(Data!$H$2:$H$1006,Data!$A$2:$A$1006,$A16,Data!$C$2:$C$1006,"Northeast peers") -> 2108.0545 | W16: =IFERROR(R16*1000000/Q16,"") -> 110.22619 | X16: =IFERROR(S16*1000000/Q16,"") -> 126.32388 | Y16: =IFERROR(T16*1000000/Q16,"") -> 83.306985 | Z16: =IFERROR(U16*1000000/Q16,"") -> 319.85705 | AA16: =IFERROR(V16*1000000/Q16,"") -> 169.74239 | AB16: =IFERROR(IF(OR(IFERROR(INDEX(Assumptions!$B$8:$B$33,MATCH(Assumptions!$B$5,Assumptions!$A$8:$A$33,0)),"")="",INDEX(Assumptions!$B$8:$B$33,MATCH($A16,Assumptions!$A$8:$A$33,0))=""),"",Z16*IFERROR(INDEX(Assumptions!$B$8:$B$33,MATCH(Assumptions!$B$5,Assumptions!$A$8:$A$33,0)),"")/INDEX(Assumptions!$B$8:$B$33,MATCH($A16,Assumptions!$A$8:$A$33,0))),"") | AC16: =IFERROR(IF(OR(IFERROR(INDEX(Assumptions!$B$8:$B$33,MATCH(Assumptions!$B$5,Assumptions!$A$8:$A$33,0)),"")="",INDEX(Assumptions!$B$8:$B$33,MATCH($A16,Assumptions!$A$8:$A$33,0))=""),"",AA16*IFERROR(INDEX(Assumptions!$B$8:$B$33,MATCH(Assumptions!$B$5,Assumptions!$A$8:$A$33,0)),"")/INDEX(Assumptions!$B$8:$B$33,MATCH($A16,Assumptions!$A$8:$A$33,0))),"") | AD16: =COUNTIFS(Data!$A$2:$A$1006,$A16,Data!$C$2:$C$1006,"Midwest peers") -> 17 | AE16: =SUMIFS(Data!$L$2:$L$1006,Data!$A$2:$A$1006,$A16,Data!$C$2:$C$1006,"Midwest peers") -> 11685397 | AF16: =SUMIFS(Data!$E$2:$E$1006,Data!$A$2:$A$1006,$A16,Data!$C$2:$C$1006,"Midwest peers") -> 1198.5889 | AG16: =SUMIFS(Data!$F$2:$F$1006,Data!$A$2:$A$1006,$A16,Data!$C$2:$C$1006,"Midwest peers") -> 1139.2401 | AH16: =SUMIFS(Data!$G$2:$G$1006,Data!$A$2:$A$1006,$A16,Data!$C$2:$C$1006,"Midwest peers") -> 1054.4958 | AI16: =SUMIFS(Data!$N$2:$N$1006,Data!$A$2:$A$1006,$A16,Data!$C$2:$C$1006,"Midwest peers") -> 3392.3248 | AJ16: =SUMIFS(Data!$H$2:$H$1006,Data!$A$2:$A$1006,$A16,Data!$C$2:$C$1006,"Midwest peers") -> 1662.4261 | AK16: =IFERROR(AF16*1000000/AE16,"") -> 102.57152 | AL16: =IFERROR(AG16*1000000/AE16,"") -> 97.492635 | AM16: =IFERROR(AH16*1000000/AE16,"") -> 90.240475 | AN16: =IFERROR(AI16*1000000/AE16,"") -> 290.30463 | AO16: =IFERROR(AJ16*1000000/AE16,"") -> 142.26526 | AP16: =IFERROR(IF(OR(IFERROR(INDEX(Assumptions!$B$8:$B$33,MATCH(Assumptions!$B$5,Assumptions!$A$8:$A$33,0)),"")="",INDEX(Assumptions!$B$8:$B$33,MATCH($A16,Assumptions!$A$8:$A$33,0))=""),"",AN16*IFERROR(INDEX(Assumptions!$B$8:$B$33,MATCH(Assumptions!$B$5,Assumptions!$A$8:$A$33,0)),"")/INDEX(Assumptions!$B$8:$B$33,MATCH($A16,Assumptions!$A$8:$A$33,0))),"") | AQ16: =IFERROR(IF(OR(IFERROR(INDEX(Assumptions!$B$8:$B$33,MATCH(Assumptions!$B$5,Assumptions!$A$8:$A$33,0)),"")="",INDEX(Assumptions!$B$8:$B$33,MATCH($A16,Assumptions!$A$8:$A$33,0))=""),"",AO16*IFERROR(INDEX(Assumptions!$B$8:$B$33,MATCH(Assumptions!$B$5,Assumptions!$A$8:$A$33,0)),"")/INDEX(Assumptions!$B$8:$B$33,MATCH($A16,Assumptions!$A$8:$A$33,0))),"")
... A30: 2025 | B30: =COUNTIFS(Data!$A$2:$A$1006,$A30,Data!$C$2:$C$1006,"FirstEnergy") -> 7 | C30: =SUMIFS(Data!$L$2:$L$1006,Data!$A$2:$A$1006,$A30,Data!$C$2:$C$1006,"FirstEnergy") -> 6284377 | D30: =SUMIFS(Data!$E$2:$E$1006,Data!$A$2:$A$1006,$A30,Data!$C$2:$C$1006,"FirstEnergy") -> 1021.8234 | E30: =SUMIFS(Data!$F$2:$F$1006,Data!$A$2:$A$1006,$A30,Data!$C$2:$C$1006,"FirstEnergy") -> 701.86078 | F30: =SUMIFS(Data!$G$2:$G$1006,Data!$A$2:$A$1006,$A30,Data!$C$2:$C$1006,"FirstEnergy") -> 904.12903 | G30: =SUMIFS(Data!$N$2:$N$1006,Data!$A$2:$A$1006,$A30,Data!$C$2:$C$1006,"FirstEnergy") -> 2627.8132 | H30: =SUMIFS(Data!$H$2:$H$1006,Data!$A$2:$A$1006,$A30,Data!$C$2:$C$1006,"FirstEnergy") -> 1952.1274 | I30: =IFERROR(D30*1000000/C30,"") -> 162.5974 | J30: =IFERROR(E30*1000000/C30,"") -> 111.68343 | K30: =IFERROR(F30*1000000/C30,"") -> 143.86932 | L30: =IFERROR(G30*1000000/C30,"") -> 418.15015 | M30: =IFERROR(H30*1000000/C30,"") -> 310.63182 | N30: =IFERROR(IF(OR(IFERROR(INDEX(Assumptions!$B$8:$B$33,MATCH(Assumptions!$B$5,Assumptions!$A$8:$A$33,0)),"")="",INDEX(Assumptions!$B$8:$B$33,MATCH($A30,Assumptions!$A$8:$A$33,0))=""),"",L30*IFERROR(INDEX(Assumptions!$B$8:$B$33,MATCH(Assumptions!$B$5,Assumptions!$A$8:$A$33,0)),"")/INDEX(Assumptions!$B$8:$B$33,MATCH($A30,Assumptions!$A$8:$A$33,0))),"") | O30: =IFERROR(IF(OR(IFERROR(INDEX(Assumptions!$B$8:$B$33,MATCH(Assumptions!$B$5,Assumptions!$A$8:$A$33,0)),"")="",INDEX(Assumptions!$B$8:$B$33,MATCH($A30,Assumptions!$A$8:$A$33,0))=""),"",M30*IFERROR(INDEX(Assumptions!$B$8:$B$33,MATCH(Assumptions!$B$5,Assumptions!$A$8:$A$33,0)),"")/INDEX(Assumptions!$B$8:$B$33,MATCH($A30,Assumptions!$A$8:$A$33,0))),"") | P30: =COUNTIFS(Data!$A$2:$A$1006,$A30,Data!$C$2:$C$1006,"Northeast peers") -> 12 | Q30: =SUMIFS(Data!$L$2:$L$1006,Data!$A$2:$A$1006,$A30,Data!$C$2:$C$1006,"Northeast peers") -> 13490862 | R30: =SUMIFS(Data!$E$2:$E$1006,Data!$A$2:$A$1006,$A30,Data!$C$2:$C$1006,"Northeast peers") -> 2224.6729 | S30: =SUMIFS(Data!$F$2:$F$1006,Data!$A$2:$A$1006,$A30,Data!$C$2:$C$1006,"Northeast peers") -> 2171.4369 | T30: =SUMIFS(Data!$G$2:$G$1006,Data!$A$2:$A$1006,$A30,Data!$C$2:$C$1006,"Northeast peers") -> 2249.2007 | U30: =SUMIFS(Data!$N$2:$N$1006,Data!$A$2:$A$1006,$A30,Data!$C$2:$C$1006,"Northeast peers") -> 6645.3106 | V30: =SUMIFS(Data!$H$2:$H$1006,Data!$A$2:$A$1006,$A30,Data!$C$2:$C$1006,"Northeast peers") -> 6138.4716 | W30: =IFERROR(R30*1000000/Q30,"") -> 164.9022 | X30: =IFERROR(S30*1000000/Q30,"") -> 160.95613 | Y30: =IFERROR(T30*1000000/Q30,"") -> 166.72031 | Z30: =IFERROR(U30*1000000/Q30,"") -> 492.57865 | AA30: =IFERROR(V30*1000000/Q30,"") -> 455.00959 | AB30: =IFERROR(IF(OR(IFERROR(INDEX(Assumptions!$B$8:$B$33,MATCH(Assumptions!$B$5,Assumptions!$A$8:$A$33,0)),"")="",INDEX(Assumptions!$B$8:$B$33,MATCH($A30,Assumptions!$A$8:$A$33,0))=""),"",Z30*IFERROR(INDEX(Assumptions!$B$8:$B$33,MATCH(Assumptions!$B$5,Assumptions!$A$8:$A$33,0)),"")/INDEX(Assumptions!$B$8:$B$33,MATCH($A30,Assumptions!$A$8:$A$33,0))),"") | AC30: =IFERROR(IF(OR(IFERROR(INDEX(Assumptions!$B$8:$B$33,MATCH(Assumptions!$B$5,Assumptions!$A$8:$A$33,0)),"")="",INDEX(Assumptions!$B$8:$B$33,MATCH($A30,Assumptions!$A$8:$A$33,0))=""),"",AA30*IFERROR(INDEX(Assumptions!$B$8:$B$33,MATCH(Assumptions!$B$5,Assumptions!$A$8:$A$33,0)),"")/INDEX(Assumptions!$B$8:$B$33,MATCH($A30,Assumptions!$A$8:$A$33,0))),"") | AD30: =COUNTIFS(Data!$A$2:$A$1006,$A30,Data!$C$2:$C$1006,"Midwest peers") -> 17 | AE30: =SUMIFS(Data!$L$2:$L$1006,Data!$A$2:$A$1006,$A30,Data!$C$2:$C$1006,"Midwest peers") -> 12733714 | AF30: =SUMIFS(Data!$E$2:$E$1006,Data!$A$2:$A$1006,$A30,Data!$C$2:$C$1006,"Midwest peers") -> 1748.9151 | AG30: =SUMIFS(Data!$F$2:$F$1006,Data!$A$2:$A$1006,$A30,Data!$C$2:$C$1006,"Midwest peers") -> 1557.1298 | AH30: =SUMIFS(Data!$G$2:$G$1006,Data!$A$2:$A$1006,$A30,Data!$C$2:$C$1006,"Midwest peers") -> 2412.2027 | AI30: =SUMIFS(Data!$N$2:$N$1006,Data!$A$2:$A$1006,$A30,Data!$C$2:$C$1006,"Midwest peers") -> 5718.2475 | AJ30: =SUMIFS(Data!$H$2:$H$1006,Data!$A$2:$A$1006,$A30,Data!$C$2:$C$1006,"Midwest peers") -> 7402.4673 | AK30: =IFERROR(AF30*1000000/AE30,"") -> 137.34525 | AL30: =IFERROR(AG30*1000000/AE30,"") -> 122.28402 | AM30: =IFERROR(AH30*1000000/AE30,"") -> 189.43434 | AN30: =IFERROR(AI30*1000000/AE30,"") -> 449.06361 | AO30: =IFERROR(AJ30*1000000/AE30,"") -> 581.32822 | AP30: =IFERROR(IF(OR(IFERROR(INDEX(Assumptions!$B$8:$B$33,MATCH(Assumptions!$B$5,Assumptions!$A$8:$A$33,0)),"")="",INDEX(Assumptions!$B$8:$B$33,MATCH($A30,Assumptions!$A$8:$A$33,0))=""),"",AN30*IFERROR(INDEX(Assumptions!$B$8:$B$33,MATCH(Assumptions!$B$5,Assumptions!$A$8:$A$33,0)),"")/INDEX(Assumptions!$B$8:$B$33,MATCH($A30,Assumptions!$A$8:$A$33,0))),"") | AQ30: =IFERROR(IF(OR(IFERROR(INDEX(Assumptions!$B$8:$B$33,MATCH(Assumptions!$B$5,Assumptions!$A$8:$A$33,0)),"")="",INDEX(Assumptions!$B$8:$B$33,MATCH($A30,Assumptions!$A$8:$A$33,0))=""),"",AO30*IFERROR(INDEX(Assumptions!$B$8:$B$33,MATCH(Assumptions!$B$5,Assumptions!$A$8:$A$33,0)),"")/INDEX(Assumptions!$B$8:$B$33,MATCH($A30,Assumptions!$A$8:$A$33,0))),"")
A32: Growth 2000–2025, compound annual rate (nominal): | I32: =IFERROR((I30/I5)^(1/25)-1,"") -> 0.029215764 | J32: =IFERROR((J30/J5)^(1/25)-1,"") -> 0.017152198 | K32: =IFERROR((K30/K5)^(1/25)-1,"") -> 0.039344447 | L32: =IFERROR((L30/L5)^(1/25)-1,"") -> 0.028528378 | M32: =IFERROR((M30/M5)^(1/25)-1,"") -> 0.056215784 | W32: =IFERROR((W30/W5)^(1/25)-1,"") -> 0.032023957 | X32: =IFERROR((X30/X5)^(1/25)-1,"") -> 0.031079758 | Y32: =IFERROR((Y30/Y5)^(1/25)-1,"") -> 0.043900546 | Z32: =IFERROR((Z30/Z5)^(1/25)-1,"") -> 0.035320799 | AA32: =IFERROR((AA30/AA5)^(1/25)-1,"") -> 0.065562949 | AK32: =IFERROR((AK30/AK5)^(1/25)-1,"") -> 0.02621092 | AL32: =IFERROR((AL30/AL5)^(1/25)-1,"") -> 0.029708293 | AM32: =IFERROR((AM30/AM5)^(1/25)-1,"") -> 0.042350446 | AN32: =IFERROR((AN30/AN5)^(1/25)-1,"") -> 0.033317662 | AO32: =IFERROR((AO30/AO5)^(1/25)-1,"") -> 0.067122587
A33: Capital additions 2000–2025 per average customer ($): | M33: =SUM(H5:H30)*1000000/AVERAGE(C5:C30) -> 4031.9115 | AA33: =SUM(V5:V30)*1000000/AVERAGE(Q5:Q30) -> 5524.6145 | AO33: =SUM(AJ5:AJ30)*1000000/AVERAGE(AE5:AE30) -> 6011.765

Sheet Utility Results
A1: Per-customer results by utility and year (nominal $). Ranks are among all 36 utilities reporting in the year (1 = highest); the FirstEnergy Pennsylvania combined series is not ranked.
A3: Year | B3: Utility | C3: Group | D3: State | E3: Customers used | F3: Distribution O&M ($mm) | G3: Customer costs ($mm) | H3: Depreciation ($mm) | I3: Total costs ($mm) | J3: Capital additions ($mm) | K3: Distribution O&M per customer ($) | L3: Customer costs per customer ($) | M3: Depreciation per customer ($) | N3: Total costs per customer ($) | O3: Capital additions per customer ($) | P3: Rank: total costs per customer | Q3: Rank: capital additions per customer
A4: 2000 | B4: Cleveland Electric Illuminating | C4: FirstEnergy | D4: OH | E4: =SUMIFS(Data!$L$2:$L$1006,Data!$A$2:$A$1006,$A4,Data!$B$2:$B$1006,$B4) -> 743158 | F4: =SUMIFS(Data!$E$2:$E$1006,Data!$A$2:$A$1006,$A4,Data!$B$2:$B$1006,$B4) -> 58.333212 | G4: =SUMIFS(Data!$F$2:$F$1006,Data!$A$2:$A$1006,$A4,Data!$B$2:$B$1006,$B4) -> 52.097101 | H4: =SUMIFS(Data!$G$2:$G$1006,Data!$A$2:$A$1006,$A4,Data!$B$2:$B$1006,$B4) -> 39.712796 | I4: =SUMIFS(Data!$N$2:$N$1006,Data!$A$2:$A$1006,$A4,Data!$B$2:$B$1006,$B4) -> 150.14311 | J4: =SUMIFS(Data!$H$2:$H$1006,Data!$A$2:$A$1006,$A4,Data!$B$2:$B$1006,$B4) -> 29.98762 | K4: =IFERROR(F4*1000000/$E4,"") -> 78.493688 | L4: =IFERROR(G4*1000000/$E4,"") -> 70.102321 | M4: =IFERROR(H4*1000000/$E4,"") -> 53.437891 | N4: =IFERROR(I4*1000000/$E4,"") -> 202.0339 | O4: =IFERROR(J4*1000000/$E4,"") -> 40.351608 | P4: =COUNTIFS($A$4:$A$1008,$A4,$N$4:$N$1008,">"&N4)+1 -> 21 | Q4: =COUNTIFS($A$4:$A$1008,$A4,$O$4:$O$1008,">"&O4)+1 -> 38
A5: 2000 | B5: Jersey Central Power & Light | C5: FirstEnergy | D5: NJ | E5: =SUMIFS(Data!$L$2:$L$1006,Data!$A$2:$A$1006,$A5,Data!$B$2:$B$1006,$B5) -> 1002120 | F5: =SUMIFS(Data!$E$2:$E$1006,Data!$A$2:$A$1006,$A5,Data!$B$2:$B$1006,$B5) -> 102.35468 | G5: =SUMIFS(Data!$F$2:$F$1006,Data!$A$2:$A$1006,$A5,Data!$B$2:$B$1006,$B5) -> 97.350554 | H5: =SUMIFS(Data!$G$2:$G$1006,Data!$A$2:$A$1006,$A5,Data!$B$2:$B$1006,$B5) -> 78.199154 | I5: =SUMIFS(Data!$N$2:$N$1006,Data!$A$2:$A$1006,$A5,Data!$B$2:$B$1006,$B5) -> 277.90439 | J5: =SUMIFS(Data!$H$2:$H$1006,Data!$A$2:$A$1006,$A5,Data!$B$2:$B$1006,$B5) -> 107.60812 | K5: =IFERROR(F5*1000000/$E5,"") -> 102.13815 | L5: =IFERROR(G5*1000000/$E5,"") -> 97.144607 | M5: =IFERROR(H5*1000000/$E5,"") -> 78.033723 | N5: =IFERROR(I5*1000000/$E5,"") -> 277.31648 | O5: =IFERROR(J5*1000000/$E5,"") -> 107.38047 | P5: =COUNTIFS($A$4:$A$1008,$A5,$N$4:$N$1008,">"&N5)+1 -> 5 | Q5: =COUNTIFS($A$4:$A$1008,$A5,$O$4:$O$1008,">"&O5)+1 -> 13
A6: 2000 | B6: Metropolitan Edison | C6: FirstEnergy | D6: PA | E6: =SUMIFS(Data!$L$2:$L$1006,Data!$A$2:$A$1006,$A6,Data!$B$2:$B$1006,$B6) -> 491905 | F6: =SUMIFS(Data!$E$2:$E$1006,Data!$A$2:$A$1006,$A6,Data!$B$2:$B$1006,$B6) -> 35.78359 | G6: =SUMIFS(Data!$F$2:$F$1006,Data!$A$2:$A$1006,$A6,Data!$B$2:$B$1006,$B6) -> 45.498449 | H6: =SUMIFS(Data!$G$2:$G$1006,Data!$A$2:$A$1006,$A6,Data!$B$2:$B$1006,$B6) -> 25.302159 | I6: =SUMIFS(Data!$N$2:$N$1006,Data!$A$2:$A$1006,$A6,Data!$B$2:$B$1006,$B6) -> 106.5842 | J6: =SUMIFS(Data!$H$2:$H$1006,Data!$A$2:$A$1006,$A6,Data!$B$2:$B$1006,$B6) -> 41.130203 | K6: =IFERROR(F6*1000000/$E6,"") -> 72.74492 | L6: =IFERROR(G6*1000000/$E6,"") -> 92.494382 | M6: =IFERROR(H6*1000000/$E6,"") -> 51.437084 | N6: =IFERROR(I6*1000000/$E6,"") -> 216.67639 | O6: =IFERROR(J6*1000000/$E6,"") -> 83.614119 | P6: =COUNTIFS($A$4:$A$1008,$A6,$N$4:$N$1008,">"&N6)+1 -> 14 | Q6: =COUNTIFS($A$4:$A$1008,$A6,$O$4:$O$1008,">"&O6)+1 -> 28
A7: 2000 | B7: Monongahela Power | C7: FirstEnergy | D7: WV | E7: =SUMIFS(Data!$L$2:$L$1006,Data!$A$2:$A$1006,$A7,Data!$B$2:$B$1006,$B7) -> 387020 | F7: =SUMIFS(Data!$E$2:$E$1006,Data!$A$2:$A$1006,$A7,Data!$B$2:$B$1006,$B7) -> 34.314597 | G7: =SUMIFS(Data!$F$2:$F$1006,Data!$A$2:$A$1006,$A7,Data!$B$2:$B$1006,$B7) -> 15.751245 | H7: =SUMIFS(Data!$G$2:$G$1006,Data!$A$2:$A$1006,$A7,Data!$B$2:$B$1006,$B7) -> 20.224646 | I7: =SUMIFS(Data!$N$2:$N$1006,Data!$A$2:$A$1006,$A7,Data!$B$2:$B$1006,$B7) -> 70.290488 | J7: =SUMIFS(Data!$H$2:$H$1006,Data!$A$2:$A$1006,$A7,Data!$B$2:$B$1006,$B7) -> 38.784727 | K7: =IFERROR(F7*1000000/$E7,"") -> 88.663627 | L7: =IFERROR(G7*1000000/$E7,"") -> 40.698788 | M7: =IFERROR(H7*1000000/$E7,"") -> 52.257367 | N7: =IFERROR(I7*1000000/$E7,"") -> 181.61978 | O7: =IFERROR(J7*1000000/$E7,"") -> 100.21375 | P7: =COUNTIFS($A$4:$A$1008,$A7,$N$4:$N$1008,">"&N7)+1 -> 29 | Q7: =COUNTIFS($A$4:$A$1008,$A7,$O$4:$O$1008,">"&O7)+1 -> 21
A8: 2000 | B8: Ohio Edison | C8: FirstEnergy | D8: OH | E8: =SUMIFS(Data!$L$2:$L$1006,Data!$A$2:$A$1006,$A8,Data!$B$2:$B$1006,$B8) -> 993655 | F8: =SUMIFS(Data!$E$2:$E$1006,Data!$A$2:$A$1006,$A8,Data!$B$2:$B$1006,$B8) -> 65.821602 | G8: =SUMIFS(Data!$F$2:$F$1006,Data!$A$2:$A$1006,$A8,Data!$B$2:$B$1006,$B8) -> 76.311504 | H8: =SUMIFS(Data!$G$2:$G$1006,Data!$A$2:$A$1006,$A8,Data!$B$2:$B$1006,$B8) -> 31.565034 | I8: =SUMIFS(Data!$N$2:$N$1006,Data!$A$2:$A$1006,$A8,Data!$B$2:$B$1006,$B8) -> 173.69814 | J8: =SUMIFS(Data!$H$2:$H$1006,Data!$A$2:$A$1006,$A8,Data!$B$2:$B$1006,$B8) -> 42.14557 | K8: =IFERROR(F8*1000000/$E8,"") -> 66.241907 | L8: =IFERROR(G8*1000000/$E8,"") -> 76.798792 | M8: =IFERROR(H8*1000000/$E8,"") -> 31.766593 | N8: =IFERROR(I8*1000000/$E8,"") -> 174.80729 | O8: =IFERROR(J8*1000000/$E8,"") -> 42.414691 | P8: =COUNTIFS($A$4:$A$1008,$A8,$N$4:$N$1008,">"&N8)+1 -> 32 | Q8: =COUNTIFS($A$4:$A$1008,$A8,$O$4:$O$1008,">"&O8)+1 -> 37
A9: 2000 | B9: Pennsylvania Electric | C9: FirstEnergy | D9: PA | E9: =SUMIFS(Data!$L$2:$L$1006,Data!$A$2:$A$1006,$A9,Data!$B$2:$B$1006,$B9) -> 579087 | F9: =SUMIFS(Data!$E$2:$E$1006,Data!$A$2:$A$1006,$A9,Data!$B$2:$B$1006,$B9) -> 49.803059 | G9: =SUMIFS(Data!$F$2:$F$1006,Data!$A$2:$A$1006,$A9,Data!$B$2:$B$1006,$B9) -> 53.697075 | H9: =SUMIFS(Data!$G$2:$G$1006,Data!$A$2:$A$1006,$A9,Data!$B$2:$B$1006,$B9) -> 37.934021 | I9: =SUMIFS(Data!$N$2:$N$1006,Data!$A$2:$A$1006,$A9,Data!$B$2:$B$1006,$B9) -> 141.43416 | J9: =SUMIFS(Data!$H$2:$H$1006,Data!$A$2:$A$1006,$A9,Data!$B$2:$B$1006,$B9) -> 61.998848 | K9: =IFERROR(F9*1000000/$E9,"") -> 86.002723 | L9: =IFERROR(G9*1000000/$E9,"") -> 92.727129 | M9: =IFERROR(H9*1000000/$E9,"") -> 65.506601 | N9: =IFERROR(I9*1000000/$E9,"") -> 244.23645 | O9: =IFERROR(J9*1000000/$E9,"") -> 107.0631 | P9: =COUNTIFS($A$4:$A$1008,$A9,$N$4:$N$1008,">"&N9)+1 -> 8 | Q9: =COUNTIFS($A$4:$A$1008,$A9,$O$4:$O$1008,">"&O9)+1 -> 15
A10: 2000 | B10: Pennsylvania Power | C10: FirstEnergy | D10: PA | E10: =SUMIFS(Data!$L$2:$L$1006,Data!$A$2:$A$1006,$A10,Data!$B$2:$B$1006,$B10) -> 134634 | F10: =SUMIFS(Data!$E$2:$E$1006,Data!$A$2:$A$1006,$A10,Data!$B$2:$B$1006,$B10) -> 10.959921 | G10: =SUMIFS(Data!$F$2:$F$1006,Data!$A$2:$A$1006,$A10,Data!$B$2:$B$1006,$B10) -> 8.22639 | H10: =SUMIFS(Data!$G$2:$G$1006,Data!$A$2:$A$1006,$A10,Data!$B$2:$B$1006,$B10) -> 6.374134 | I10: =SUMIFS(Data!$N$2:$N$1006,Data!$A$2:$A$1006,$A10,Data!$B$2:$B$1006,$B10) -> 25.560445 | J10: =SUMIFS(Data!$H$2:$H$1006,Data!$A$2:$A$1006,$A10,Data!$B$2:$B$1006,$B10) -> 9.280058 | K10: =IFERROR(F10*1000000/$E10,"") -> 81.405299 | L10: =IFERROR(G10*1000000/$E10,"") -> 61.101876 | M10: =IFERROR(H10*1000000/$E10,"") -> 47.344163 | N10: =IFERROR(I10*1000000/$E10,"") -> 189.85134 | O10: =IFERROR(J10*1000000/$E10,"") -> 68.928042 | P10: =COUNTIFS($A$4:$A$1008,$A10,$N$4:$N$1008,">"&N10)+1 -> 23 | Q10: =COUNTIFS($A$4:$A$1008,$A10,$O$4:$O$1008,">"&O10)+1 -> 32
A11: 2000 | B11: Potomac Edison | C11: FirstEnergy | D11: MD/WV | E11: =SUMIFS(Data!$L$2:$L$1006,Data!$A$2:$A$1006,$A11,Data!$B$2:$B$1006,$B11) -> 402621 | F11: =SUMIFS(Data!$E$2:$E$1006,Data!$A$2:$A$1006,$A11,Data!$B$2:$B$1006,$B11) -> 26.348026 | G11: =SUMIFS(Data!$F$2:$F$1006,Data!$A$2:$A$1006,$A11,Data!$B$2:$B$1006,$B11) -> 17.321462 | H11: =SUMIFS(Data!$G$2:$G$1006,Data!$A$2:$A$1006,$A11,Data!$B$2:$B$1006,$B11) -> 26.221384 | I11: =SUMIFS(Data!$N$2:$N$1006,Data!$A$2:$A$1006,$A11,Data!$B$2:$B$1006,$B11) -> 69.890872 | J11: =SUMIFS(Data!$H$2:$H$1006,Data!$A$2:$A$1006,$A11,Data!$B$2:$B$1006,$B11) -> 53.9817 | K11: =IFERROR(F11*1000000/$E11,"") -> 65.441261 | L11: =IFERROR(G11*1000000/$E11,"") -> 43.021755 | M11: =IFERROR(H11*1000000/$E11,"") -> 65.126717 | N11: =IFERROR(I11*1000000/$E11,"") -> 173.58973 | O11: =IFERROR(J11*1000000/$E11,"") -> 134.07572 | P11: =COUNTIFS($A$4:$A$1008,$A11,$N$4:$N$1008,">"&N11)+1 -> 33 | Q11: =COUNTIFS($A$4:$A$1008,$A11,$O$4:$O$1008,">"&O11)+1 -> 6
A12: 2000 | B12: Toledo Edison | C12: FirstEnergy | D12: OH | E12: =SUMIFS(Data!$L$2:$L$1006,Data!$A$2:$A$1006,$A12,Data!$B$2:$B$1006,$B12) -> 302480 | F12: =SUMIFS(Data!$E$2:$E$1006,Data!$A$2:$A$1006,$A12,Data!$B$2:$B$1006,$B12) -> 29.09178 | G12: =SUMIFS(Data!$F$2:$F$1006,Data!$A$2:$A$1006,$A12,Data!$B$2:$B$1006,$B12) -> 19.902142 | H12: =SUMIFS(Data!$G$2:$G$1006,Data!$A$2:$A$1006,$A12,Data!$B$2:$B$1006,$B12) -> 18.549546 | I12: =SUMIFS(Data!$N$2:$N$1006,Data!$A$2:$A$1006,$A12,Data!$B$2:$B$1006,$B12) -> 67.543468 | J12: =SUMIFS(Data!$H$2:$H$1006,Data!$A$2:$A$1006,$A12,Data!$B$2:$B$1006,$B12) -> 20.917035 | K12: =IFERROR(F12*1000000/$E12,"") -> 96.177532 | L12: =IFERROR(G12*1000000/$E12,"") -> 65.796555 | M12: =IFERROR(H12*1000000/$E12,"") -> 61.324868 | N12: =IFERROR(I12*1000000/$E12,"") -> 223.29896 | O12: =IFERROR(J12*1000000/$E12,"") -> 69.151795 | P12: =COUNTIFS($A$4:$A$1008,$A12,$N$4:$N$1008,">"&N12)+1 -> 11 | Q12: =COUNTIFS($A$4:$A$1008,$A12,$O$4:$O$1008,">"&O12)+1 -> 31
A13: 2000 | B13: West Penn Power | C13: FirstEnergy | D13: PA | E13: =SUMIFS(Data!$L$2:$L$1006,Data!$A$2:$A$1006,$A13,Data!$B$2:$B$1006,$B13) -> 680923 | F13: =SUMIFS(Data!$E$2:$E$1006,Data!$A$2:$A$1006,$A13,Data!$B$2:$B$1006,$B13) -> 39.739834 | G13: =SUMIFS(Data!$F$2:$F$1006,Data!$A$2:$A$1006,$A13,Data!$B$2:$B$1006,$B13) -> 31.245758 | H13: =SUMIFS(Data!$G$2:$G$1006,Data!$A$2:$A$1006,$A13,Data!$B$2:$B$1006,$B13) -> 29.386181 | I13: =SUMIFS(Data!$N$2:$N$1006,Data!$A$2:$A$1006,$A13,Data!$B$2:$B$1006,$B13) -> 100.37177 | J13: =SUMIFS(Data!$H$2:$H$1006,Data!$A$2:$A$1006,$A13,Data!$B$2:$B$1006,$B13) -> 46.692189 | K13: =IFERROR(F13*1000000/$E13,"") -> 58.361715 | L13: =IFERROR(G13*1000000/$E13,"") -> 45.887359 | M13: =IFERROR(H13*1000000/$E13,"") -> 43.156394 | N13: =IFERROR(I13*1000000/$E13,"") -> 147.40547 | O13: =IFERROR(J13*1000000/$E13,"") -> 68.571908 | P13: =COUNTIFS($A$4:$A$1008,$A13,$N$4:$N$1008,">"&N13)+1 -> 36 | Q13: =COUNTIFS($A$4:$A$1008,$A13,$O$4:$O$1008,">"&O13)+1 -> 34
A14: 2000 | B14: AEP Ohio (Ohio Power) | C14: Northeast peers | D14: OH | E14: =SUMIFS(Data!$L$2:$L$1006,Data!$A$2:$A$1006,$A14,Data!$B$2:$B$1006,$B14) -> 1354690 | F14: =SUMIFS(Data!$E$2:$E$1006,Data!$A$2:$A$1006,$A14,Data!$B$2:$B$1006,$B14) -> 98.937796 | G14: =SUMIFS(Data!$F$2:$F$1006,Data!$A$2:$A$1006,$A14,Data!$B$2:$B$1006,$B14) -> 76.065082 | H14: =SUMIFS(Data!$G$2:$G$1006,Data!$A$2:$A$1006,$A14,Data!$B$2:$B$1006,$B14) -> 78.984041 | I14: =SUMIFS(Data!$N$2:$N$1006,Data!$A$2:$A$1006,$A14,Data!$B$2:$B$1006,$B14) -> 253.98692 | J14: =SUMIFS(Data!$H$2:$H$1006,Data!$A$2:$A$1006,$A14,Data!$B$2:$B$1006,$B14) -> 145.20209 | K14: =IFERROR(F14*1000000/$E14,"") -> 73.033532 | L14: =IFERROR(G14*1000000/$E14,"") -> 56.149438 | M14: =IFERROR(H14*1000000/$E14,"") -> 58.304144 | N14: =IFERROR(I14*1000000/$E14,"") -> 187.48711 | O14: =IFERROR(J14*1000000/$E14,"") -> 107.18474 | P14: =COUNTIFS($A$4:$A$1008,$A14,$N$4:$N$1008,">"&N14)+1 -> 26 | Q14: =COUNTIFS($A$4:$A$1008,$A14,$O$4:$O$1008,">"&O14)+1 -> 14
A15: 2000 | B15: AES Ohio (Dayton Power & Light) | C15: Northeast peers | D15: OH | E15: =SUMIFS(Data!$L$2:$L$1006,Data!$A$2:$A$1006,$A15,Data!$B$2:$B$1006,$B15) -> 496623 | F15: =SUMIFS(Data!$E$2:$E$1006,Data!$A$2:$A$1006,$A15,Data!$B$2:$B$1006,$B15) -> 23.561136 | G15: =SUMIFS(Data!$F$2:$F$1006,Data!$A$2:$A$1006,$A15,Data!$B$2:$B$1006,$B15) -> 34.003834 | H15: =SUMIFS(Data!$G$2:$G$1006,Data!$A$2:$A$1006,$A15,Data!$B$2:$B$1006,$B15) -> 30.277266 | I15: =SUMIFS(Data!$N$2:$N$1006,Data!$A$2:$A$1006,$A15,Data!$B$2:$B$1006,$B15) -> 87.842236 | J15: =SUMIFS(Data!$H$2:$H$1006,Data!$A$2:$A$1006,$A15,Data!$B$2:$B$1006,$B15) -> 25.959165 | K15: =IFERROR(F15*1000000/$E15,"") -> 47.4427 | L15: =IFERROR(G15*1000000/$E15,"") -> 68.470115 | M15: =IFERROR(H15*1000000/$E15,"") -> 60.966298 | N15: =IFERROR(I15*1000000/$E15,"") -> 176.87911 | O15: =IFERROR(J15*1000000/$E15,"") -> 52.271371 | P15: =COUNTIFS($A$4:$A$1008,$A15,$N$4:$N$1008,">"&N15)+1 -> 31 | Q15: =COUNTIFS($A$4:$A$1008,$A15,$O$4:$O$1008,">"&O15)+1 -> 36
... A1008: 2025 | B1008: Wisconsin Public Service | C1008: Midwest peers | D1008: WI | E1008: =SUMIFS(Data!$L$2:$L$1006,Data!$A$2:$A$1006,$A1008,Data!$B$2:$B$1006,$B1008) -> 472199 | F1008: =SUMIFS(Data!$E$2:$E$1006,Data!$A$2:$A$1006,$A1008,Data!$B$2:$B$1006,$B1008) -> 45.865031 | G1008: =SUMIFS(Data!$F$2:$F$1006,Data!$A$2:$A$1006,$A1008,Data!$B$2:$B$1006,$B1008) -> 41.917457 | H1008: =SUMIFS(Data!$G$2:$G$1006,Data!$A$2:$A$1006,$A1008,Data!$B$2:$B$1006,$B1008) -> 66.353524 | I1008: =SUMIFS(Data!$N$2:$N$1006,Data!$A$2:$A$1006,$A1008,Data!$B$2:$B$1006,$B1008) -> 154.13601 | J1008: =SUMIFS(Data!$H$2:$H$1006,Data!$A$2:$A$1006,$A1008,Data!$B$2:$B$1006,$B1008) -> 211.63783 | K1008: =IFERROR(F1008*1000000/$E1008,"") -> 97.130725 | L1008: =IFERROR(G1008*1000000/$E1008,"") -> 88.770745 | M1008: =IFERROR(H1008*1000000/$E1008,"") -> 140.52026 | N1008: =IFERROR(I1008*1000000/$E1008,"") -> 326.42172 | O1008: =IFERROR(J1008*1000000/$E1008,"") -> 448.19627 | P1008: =COUNTIFS($A$4:$A$1008,$A1008,$N$4:$N$1008,">"&N1008)+1 -> 31 | Q1008: =COUNTIFS($A$4:$A$1008,$A1008,$O$4:$O$1008,">"&O1008)+1 -> 17
A1009: 2000 | B1009: FirstEnergy Pennsylvania (combined series) | C1009: FirstEnergy PA series | D1009: PA | E1009: =SUMIFS(Data!$L$2:$L$1006,Data!$A$2:$A$1006,$A1009,Data!$C$2:$C$1006,"FirstEnergy",Data!$D$2:$D$1006,"PA") -> 1886549 | F1009: =SUMIFS(Data!$E$2:$E$1006,Data!$A$2:$A$1006,$A1009,Data!$C$2:$C$1006,"FirstEnergy",Data!$D$2:$D$1006,"PA") -> 136.2864 | G1009: =SUMIFS(Data!$F$2:$F$1006,Data!$A$2:$A$1006,$A1009,Data!$C$2:$C$1006,"FirstEnergy",Data!$D$2:$D$1006,"PA") -> 138.66767 | H1009: =SUMIFS(Data!$G$2:$G$1006,Data!$A$2:$A$1006,$A1009,Data!$C$2:$C$1006,"FirstEnergy",Data!$D$2:$D$1006,"PA") -> 98.996495 | I1009: =SUMIFS(Data!$N$2:$N$1006,Data!$A$2:$A$1006,$A1009,Data!$C$2:$C$1006,"FirstEnergy",Data!$D$2:$D$1006,"PA") -> 373.95057 | J1009: =SUMIFS(Data!$H$2:$H$1006,Data!$A$2:$A$1006,$A1009,Data!$C$2:$C$1006,"FirstEnergy",Data!$D$2:$D$1006,"PA") -> 159.1013 | K1009: =IFERROR(F1009*1000000/$E1009,"") -> 72.241115 | L1009: =IFERROR(G1009*1000000/$E1009,"") -> 73.50335 | M1009: =IFERROR(H1009*1000000/$E1009,"") -> 52.474913 | N1009: =IFERROR(I1009*1000000/$E1009,"") -> 198.21938 | O1009: =IFERROR(J1009*1000000/$E1009,"") -> 84.33457
A1010: 2001 | B1010: FirstEnergy Pennsylvania (combined series) | C1010: FirstEnergy PA series | D1010: PA | E1010: =SUMIFS(Data!$L$2:$L$1006,Data!$A$2:$A$1006,$A1010,Data!$C$2:$C$1006,"FirstEnergy",Data!$D$2:$D$1006,"PA") -> 1915625 | F1010: =SUMIFS(Data!$E$2:$E$1006,Data!$A$2:$A$1006,$A1010,Data!$C$2:$C$1006,"FirstEnergy",Data!$D$2:$D$1006,"PA") -> 143.75481 | G1010: =SUMIFS(Data!$F$2:$F$1006,Data!$A$2:$A$1006,$A1010,Data!$C$2:$C$1006,"FirstEnergy",Data!$D$2:$D$1006,"PA") -> 128.66684 | H1010: =SUMIFS(Data!$G$2:$G$1006,Data!$A$2:$A$1006,$A1010,Data!$C$2:$C$1006,"FirstEnergy",Data!$D$2:$D$1006,"PA") -> 103.3471 | I1010: =SUMIFS(Data!$N$2:$N$1006,Data!$A$2:$A$1006,$A1010,Data!$C$2:$C$1006,"FirstEnergy",Data!$D$2:$D$1006,"PA") -> 375.76875 | J1010: =SUMIFS(Data!$H$2:$H$1006,Data!$A$2:$A$1006,$A1010,Data!$C$2:$C$1006,"FirstEnergy",Data!$D$2:$D$1006,"PA") -> 150.19125 | K1010: =IFERROR(F1010*1000000/$E1010,"") -> 75.043296 | L1010: =IFERROR(G1010*1000000/$E1010,"") -> 67.16703 | M1010: =IFERROR(H1010*1000000/$E1010,"") -> 53.949545 | N1010: =IFERROR(I1010*1000000/$E1010,"") -> 196.15987 | O1010: =IFERROR(J1010*1000000/$E1010,"") -> 78.403262
A1011: 2002 | B1011: FirstEnergy Pennsylvania (combined series) | C1011: FirstEnergy PA series | D1011: PA | E1011: =SUMIFS(Data!$L$2:$L$1006,Data!$A$2:$A$1006,$A1011,Data!$C$2:$C$1006,"FirstEnergy",Data!$D$2:$D$1006,"PA") -> 1933299 | F1011: =SUMIFS(Data!$E$2:$E$1006,Data!$A$2:$A$1006,$A1011,Data!$C$2:$C$1006,"FirstEnergy",Data!$D$2:$D$1006,"PA") -> 143.50141 | G1011: =SUMIFS(Data!$F$2:$F$1006,Data!$A$2:$A$1006,$A1011,Data!$C$2:$C$1006,"FirstEnergy",Data!$D$2:$D$1006,"PA") -> 98.258285 | H1011: =SUMIFS(Data!$G$2:$G$1006,Data!$A$2:$A$1006,$A1011,Data!$C$2:$C$1006,"FirstEnergy",Data!$D$2:$D$1006,"PA") -> 98.315198 | I1011: =SUMIFS(Data!$N$2:$N$1006,Data!$A$2:$A$1006,$A1011,Data!$C$2:$C$1006,"FirstEnergy",Data!$D$2:$D$1006,"PA") -> 340.07489 | J1011: =SUMIFS(Data!$H$2:$H$1006,Data!$A$2:$A$1006,$A1011,Data!$C$2:$C$1006,"FirstEnergy",Data!$D$2:$D$1006,"PA") -> 123.01361 | K1011: =IFERROR(F1011*1000000/$E1011,"") -> 74.226183 | L1011: =IFERROR(G1011*1000000/$E1011,"") -> 50.824153 | M1011: =IFERROR(H1011*1000000/$E1011,"") -> 50.853592 | N1011: =IFERROR(I1011*1000000/$E1011,"") -> 175.90393 | O1011: =IFERROR(J1011*1000000/$E1011,"") -> 63.628858
A1012: 2003 | B1012: FirstEnergy Pennsylvania (combined series) | C1012: FirstEnergy PA series | D1012: PA | E1012: =SUMIFS(Data!$L$2:$L$1006,Data!$A$2:$A$1006,$A1012,Data!$C$2:$C$1006,"FirstEnergy",Data!$D$2:$D$1006,"PA") -> 1947091 | F1012: =SUMIFS(Data!$E$2:$E$1006,Data!$A$2:$A$1006,$A1012,Data!$C$2:$C$1006,"FirstEnergy",Data!$D$2:$D$1006,"PA") -> 169.43161 | G1012: =SUMIFS(Data!$F$2:$F$1006,Data!$A$2:$A$1006,$A1012,Data!$C$2:$C$1006,"FirstEnergy",Data!$D$2:$D$1006,"PA") -> 115.04252 | H1012: =SUMIFS(Data!$G$2:$G$1006,Data!$A$2:$A$1006,$A1012,Data!$C$2:$C$1006,"FirstEnergy",Data!$D$2:$D$1006,"PA") -> 95.47889 | I1012: =SUMIFS(Data!$N$2:$N$1006,Data!$A$2:$A$1006,$A1012,Data!$C$2:$C$1006,"FirstEnergy",Data!$D$2:$D$1006,"PA") -> 379.95302 | J1012: =SUMIFS(Data!$H$2:$H$1006,Data!$A$2:$A$1006,$A1012,Data!$C$2:$C$1006,"FirstEnergy",Data!$D$2:$D$1006,"PA") -> 126.96355 | K1012: =IFERROR(F1012*1000000/$E1012,"") -> 87.017819 | L1012: =IFERROR(G1012*1000000/$E1012,"") -> 59.084306 | M1012: =IFERROR(H1012*1000000/$E1012,"") -> 49.036686 | N1012: =IFERROR(I1012*1000000/$E1012,"") -> 195.13881 | O1012: =IFERROR(J1012*1000000/$E1012,"") -> 65.206789
A1013: 2004 | B1013: FirstEnergy Pennsylvania (combined series) | C1013: FirstEnergy PA series | D1013: PA | E1013: =SUMIFS(Data!$L$2:$L$1006,Data!$A$2:$A$1006,$A1013,Data!$C$2:$C$1006,"FirstEnergy",Data!$D$2:$D$1006,"PA") -> 1960923 | F1013: =SUMIFS(Data!$E$2:$E$1006,Data!$A$2:$A$1006,$A1013,Data!$C$2:$C$1006,"FirstEnergy",Data!$D$2:$D$1006,"PA") -> 144.49907 | G1013: =SUMIFS(Data!$F$2:$F$1006,Data!$A$2:$A$1006,$A1013,Data!$C$2:$C$1006,"FirstEnergy",Data!$D$2:$D$1006,"PA") -> 93.946091 | H1013: =SUMIFS(Data!$G$2:$G$1006,Data!$A$2:$A$1006,$A1013,Data!$C$2:$C$1006,"FirstEnergy",Data!$D$2:$D$1006,"PA") -> 98.449498 | I1013: =SUMIFS(Data!$N$2:$N$1006,Data!$A$2:$A$1006,$A1013,Data!$C$2:$C$1006,"FirstEnergy",Data!$D$2:$D$1006,"PA") -> 336.89465 | J1013: =SUMIFS(Data!$H$2:$H$1006,Data!$A$2:$A$1006,$A1013,Data!$C$2:$C$1006,"FirstEnergy",Data!$D$2:$D$1006,"PA") -> 162.11186 | K1013: =IFERROR(F1013*1000000/$E1013,"") -> 73.689311 | L1013: =IFERROR(G1013*1000000/$E1013,"") -> 47.909118 | M1013: =IFERROR(H1013*1000000/$E1013,"") -> 50.205693 | N1013: =IFERROR(I1013*1000000/$E1013,"") -> 171.80412 | O1013: =IFERROR(J1013*1000000/$E1013,"") -> 82.671204
A1014: 2005 | B1014: FirstEnergy Pennsylvania (combined series) | C1014: FirstEnergy PA series | D1014: PA | E1014: =SUMIFS(Data!$L$2:$L$1006,Data!$A$2:$A$1006,$A1014,Data!$C$2:$C$1006,"FirstEnergy",Data!$D$2:$D$1006,"PA") -> 1977996 | F1014: =SUMIFS(Data!$E$2:$E$1006,Data!$A$2:$A$1006,$A1014,Data!$C$2:$C$1006,"FirstEnergy",Data!$D$2:$D$1006,"PA") -> 139.52587 | G1014: =SUMIFS(Data!$F$2:$F$1006,Data!$A$2:$A$1006,$A1014,Data!$C$2:$C$1006,"FirstEnergy",Data!$D$2:$D$1006,"PA") -> 108.66791 | H1014: =SUMIFS(Data!$G$2:$G$1006,Data!$A$2:$A$1006,$A1014,Data!$C$2:$C$1006,"FirstEnergy",Data!$D$2:$D$1006,"PA") -> 103.05107 | I1014: =SUMIFS(Data!$N$2:$N$1006,Data!$A$2:$A$1006,$A1014,Data!$C$2:$C$1006,"FirstEnergy",Data!$D$2:$D$1006,"PA") -> 351.24485 | J1014: =SUMIFS(Data!$H$2:$H$1006,Data!$A$2:$A$1006,$A1014,Data!$C$2:$C$1006,"FirstEnergy",Data!$D$2:$D$1006,"PA") -> 234.1801 | K1014: =IFERROR(F1014*1000000/$E1014,"") -> 70.539004 | L1014: =IFERROR(G1014*1000000/$E1014,"") -> 54.938386 | M1014: =IFERROR(H1014*1000000/$E1014,"") -> 52.098728 | N1014: =IFERROR(I1014*1000000/$E1014,"") -> 177.57612 | O1014: =IFERROR(J1014*1000000/$E1014,"") -> 118.39261
A1015: 2006 | B1015: FirstEnergy Pennsylvania (combined series) | C1015: FirstEnergy PA series | D1015: PA | E1015: =SUMIFS(Data!$L$2:$L$1006,Data!$A$2:$A$1006,$A1015,Data!$C$2:$C$1006,"FirstEnergy",Data!$D$2:$D$1006,"PA") -> 1992014 | F1015: =SUMIFS(Data!$E$2:$E$1006,Data!$A$2:$A$1006,$A1015,Data!$C$2:$C$1006,"FirstEnergy",Data!$D$2:$D$1006,"PA") -> 148.30803 | G1015: =SUMIFS(Data!$F$2:$F$1006,Data!$A$2:$A$1006,$A1015,Data!$C$2:$C$1006,"FirstEnergy",Data!$D$2:$D$1006,"PA") -> 104.36694 | H1015: =SUMIFS(Data!$G$2:$G$1006,Data!$A$2:$A$1006,$A1015,Data!$C$2:$C$1006,"FirstEnergy",Data!$D$2:$D$1006,"PA") -> 104.45248 | I1015: =SUMIFS(Data!$N$2:$N$1006,Data!$A$2:$A$1006,$A1015,Data!$C$2:$C$1006,"FirstEnergy",Data!$D$2:$D$1006,"PA") -> 357.12745 | J1015: =SUMIFS(Data!$H$2:$H$1006,Data!$A$2:$A$1006,$A1015,Data!$C$2:$C$1006,"FirstEnergy",Data!$D$2:$D$1006,"PA") -> 229.51111 | K1015: =IFERROR(F1015*1000000/$E1015,"") -> 74.4513 | L1015: =IFERROR(G1015*1000000/$E1015,"") -> 52.392672 | M1015: =IFERROR(H1015*1000000/$E1015,"") -> 52.435617 | N1015: =IFERROR(I1015*1000000/$E1015,"") -> 179.27959 | O1015: =IFERROR(J1015*1000000/$E1015,"") -> 115.21561
A1016: 2007 | B1016: FirstEnergy Pennsylvania (combined series) | C1016: FirstEnergy PA series | D1016: PA | E1016: =SUMIFS(Data!$L$2:$L$1006,Data!$A$2:$A$1006,$A1016,Data!$C$2:$C$1006,"FirstEnergy",Data!$D$2:$D$1006,"PA") -> 2002719 | F1016: =SUMIFS(Data!$E$2:$E$1006,Data!$A$2:$A$1006,$A1016,Data!$C$2:$C$1006,"FirstEnergy",Data!$D$2:$D$1006,"PA") -> 165.60686 | G1016: =SUMIFS(Data!$F$2:$F$1006,Data!$A$2:$A$1006,$A1016,Data!$C$2:$C$1006,"FirstEnergy",Data!$D$2:$D$1006,"PA") -> 123.97804 | H1016: =SUMIFS(Data!$G$2:$G$1006,Data!$A$2:$A$1006,$A1016,Data!$C$2:$C$1006,"FirstEnergy",Data!$D$2:$D$1006,"PA") -> 108.06225 | I1016: =SUMIFS(Data!$N$2:$N$1006,Data!$A$2:$A$1006,$A1016,Data!$C$2:$C$1006,"FirstEnergy",Data!$D$2:$D$1006,"PA") -> 397.64714 | J1016: =SUMIFS(Data!$H$2:$H$1006,Data!$A$2:$A$1006,$A1016,Data!$C$2:$C$1006,"FirstEnergy",Data!$D$2:$D$1006,"PA") -> 228.70889 | K1016: =IFERROR(F1016*1000000/$E1016,"") -> 82.69101 | L1016: =IFERROR(G1016*1000000/$E1016,"") -> 61.90486 | M1016: =IFERROR(H1016*1000000/$E1016,"") -> 53.957768 | N1016: =IFERROR(I1016*1000000/$E1016,"") -> 198.55364 | O1016: =IFERROR(J1016*1000000/$E1016,"") -> 114.19919
A1017: 2008 | B1017: FirstEnergy Pennsylvania (combined series) | C1017: FirstEnergy PA series | D1017: PA | E1017: =SUMIFS(Data!$L$2:$L$1006,Data!$A$2:$A$1006,$A1017,Data!$C$2:$C$1006,"FirstEnergy",Data!$D$2:$D$1006,"PA") -> 2009321 | F1017: =SUMIFS(Data!$E$2:$E$1006,Data!$A$2:$A$1006,$A1017,Data!$C$2:$C$1006,"FirstEnergy",Data!$D$2:$D$1006,"PA") -> 159.76156 | G1017: =SUMIFS(Data!$F$2:$F$1006,Data!$A$2:$A$1006,$A1017,Data!$C$2:$C$1006,"FirstEnergy",Data!$D$2:$D$1006,"PA") -> 142.91008 | H1017: =SUMIFS(Data!$G$2:$G$1006,Data!$A$2:$A$1006,$A1017,Data!$C$2:$C$1006,"FirstEnergy",Data!$D$2:$D$1006,"PA") -> 113.01642 | I1017: =SUMIFS(Data!$N$2:$N$1006,Data!$A$2:$A$1006,$A1017,Data!$C$2:$C$1006,"FirstEnergy",Data!$D$2:$D$1006,"PA") -> 415.68806 | J1017: =SUMIFS(Data!$H$2:$H$1006,Data!$A$2:$A$1006,$A1017,Data!$C$2:$C$1006,"FirstEnergy",Data!$D$2:$D$1006,"PA") -> 271.13405 | K1017: =IFERROR(F1017*1000000/$E1017,"") -> 79.510223 | L1017: =IFERROR(G1017*1000000/$E1017,"") -> 71.123569 | M1017: =IFERROR(H1017*1000000/$E1017,"") -> 56.246076 | N1017: =IFERROR(I1017*1000000/$E1017,"") -> 206.87987 | O1017: =IFERROR(J1017*1000000/$E1017,"") -> 134.93815
A1018: 2009 | B1018: FirstEnergy Pennsylvania (combined series) | C1018: FirstEnergy PA series | D1018: PA | E1018: =SUMIFS(Data!$L$2:$L$1006,Data!$A$2:$A$1006,$A1018,Data!$C$2:$C$1006,"FirstEnergy",Data!$D$2:$D$1006,"PA") -> 2013543 | F1018: =SUMIFS(Data!$E$2:$E$1006,Data!$A$2:$A$1006,$A1018,Data!$C$2:$C$1006,"FirstEnergy",Data!$D$2:$D$1006,"PA") -> 123.7894 | G1018: =SUMIFS(Data!$F$2:$F$1006,Data!$A$2:$A$1006,$A1018,Data!$C$2:$C$1006,"FirstEnergy",Data!$D$2:$D$1006,"PA") -> 151.34381 | H1018: =SUMIFS(Data!$G$2:$G$1006,Data!$A$2:$A$1006,$A1018,Data!$C$2:$C$1006,"FirstEnergy",Data!$D$2:$D$1006,"PA") -> 119.7864 | I1018: =SUMIFS(Data!$N$2:$N$1006,Data!$A$2:$A$1006,$A1018,Data!$C$2:$C$1006,"FirstEnergy",Data!$D$2:$D$1006,"PA") -> 394.91961 | J1018: =SUMIFS(Data!$H$2:$H$1006,Data!$A$2:$A$1006,$A1018,Data!$C$2:$C$1006,"FirstEnergy",Data!$D$2:$D$1006,"PA") -> 279.77699 | K1018: =IFERROR(F1018*1000000/$E1018,"") -> 61.478398 | L1018: =IFERROR(G1018*1000000/$E1018,"") -> 75.162941 | M1018: =IFERROR(H1018*1000000/$E1018,"") -> 59.490359 | N1018: =IFERROR(I1018*1000000/$E1018,"") -> 196.1317 | O1018: =IFERROR(J1018*1000000/$E1018,"") -> 138.94761
A1019: 2010 | B1019: FirstEnergy Pennsylvania (combined series) | C1019: FirstEnergy PA series | D1019: PA | E1019: =SUMIFS(Data!$L$2:$L$1006,Data!$A$2:$A$1006,$A1019,Data!$C$2:$C$1006,"FirstEnergy",Data!$D$2:$D$1006,"PA") -> 2017622 | F1019: =SUMIFS(Data!$E$2:$E$1006,Data!$A$2:$A$1006,$A1019,Data!$C$2:$C$1006,"FirstEnergy",Data!$D$2:$D$1006,"PA") -> 135.47511 | G1019: =SUMIFS(Data!$F$2:$F$1006,Data!$A$2:$A$1006,$A1019,Data!$C$2:$C$1006,"FirstEnergy",Data!$D$2:$D$1006,"PA") -> 173.50218 | H1019: =SUMIFS(Data!$G$2:$G$1006,Data!$A$2:$A$1006,$A1019,Data!$C$2:$C$1006,"FirstEnergy",Data!$D$2:$D$1006,"PA") -> 122.71934 | I1019: =SUMIFS(Data!$N$2:$N$1006,Data!$A$2:$A$1006,$A1019,Data!$C$2:$C$1006,"FirstEnergy",Data!$D$2:$D$1006,"PA") -> 431.69663 | J1019: =SUMIFS(Data!$H$2:$H$1006,Data!$A$2:$A$1006,$A1019,Data!$C$2:$C$1006,"FirstEnergy",Data!$D$2:$D$1006,"PA") -> 257.01308 | K1019: =IFERROR(F1019*1000000/$E1019,"") -> 67.145931 | L1019: =IFERROR(G1019*1000000/$E1019,"") -> 85.993402 | M1019: =IFERROR(H1019*1000000/$E1019,"") -> 60.823754 | N1019: =IFERROR(I1019*1000000/$E1019,"") -> 213.96309 | O1019: =IFERROR(J1019*1000000/$E1019,"") -> 127.38416
A1020: 2011 | B1020: FirstEnergy Pennsylvania (combined series) | C1020: FirstEnergy PA series | D1020: PA | E1020: =SUMIFS(Data!$L$2:$L$1006,Data!$A$2:$A$1006,$A1020,Data!$C$2:$C$1006,"FirstEnergy",Data!$D$2:$D$1006,"PA") -> 2019801 | F1020: =SUMIFS(Data!$E$2:$E$1006,Data!$A$2:$A$1006,$A1020,Data!$C$2:$C$1006,"FirstEnergy",Data!$D$2:$D$1006,"PA") -> 130.94065 | G1020: =SUMIFS(Data!$F$2:$F$1006,Data!$A$2:$A$1006,$A1020,Data!$C$2:$C$1006,"FirstEnergy",Data!$D$2:$D$1006,"PA") -> 223.65094 | H1020: =SUMIFS(Data!$G$2:$G$1006,Data!$A$2:$A$1006,$A1020,Data!$C$2:$C$1006,"FirstEnergy",Data!$D$2:$D$1006,"PA") -> 147.10865 | I1020: =SUMIFS(Data!$N$2:$N$1006,Data!$A$2:$A$1006,$A1020,Data!$C$2:$C$1006,"FirstEnergy",Data!$D$2:$D$1006,"PA") -> 501.70024 | J1020: =SUMIFS(Data!$H$2:$H$1006,Data!$A$2:$A$1006,$A1020,Data!$C$2:$C$1006,"FirstEnergy",Data!$D$2:$D$1006,"PA") -> 264.42784 | K1020: =IFERROR(F1020*1000000/$E1020,"") -> 64.82849 | L1020: =IFERROR(G1020*1000000/$E1020,"") -> 110.7292 | M1020: =IFERROR(H1020*1000000/$E1020,"") -> 72.833239 | N1020: =IFERROR(I1020*1000000/$E1020,"") -> 248.39092 | O1020: =IFERROR(J1020*1000000/$E1020,"") -> 130.91777
... A1034: 2025 | B1034: FirstEnergy Pennsylvania (combined series) | C1034: FirstEnergy PA series | D1034: PA | E1034: =SUMIFS(Data!$L$2:$L$1006,Data!$A$2:$A$1006,$A1034,Data!$C$2:$C$1006,"FirstEnergy",Data!$D$2:$D$1006,"PA") -> 2097100 | F1034: =SUMIFS(Data!$E$2:$E$1006,Data!$A$2:$A$1006,$A1034,Data!$C$2:$C$1006,"FirstEnergy",Data!$D$2:$D$1006,"PA") -> 414.53737 | G1034: =SUMIFS(Data!$F$2:$F$1006,Data!$A$2:$A$1006,$A1034,Data!$C$2:$C$1006,"FirstEnergy",Data!$D$2:$D$1006,"PA") -> 349.88289 | H1034: =SUMIFS(Data!$G$2:$G$1006,Data!$A$2:$A$1006,$A1034,Data!$C$2:$C$1006,"FirstEnergy",Data!$D$2:$D$1006,"PA") -> 291.09111 | I1034: =SUMIFS(Data!$N$2:$N$1006,Data!$A$2:$A$1006,$A1034,Data!$C$2:$C$1006,"FirstEnergy",Data!$D$2:$D$1006,"PA") -> 1055.5114 | J1034: =SUMIFS(Data!$H$2:$H$1006,Data!$A$2:$A$1006,$A1034,Data!$C$2:$C$1006,"FirstEnergy",Data!$D$2:$D$1006,"PA") -> 814.8243 | K1034: =IFERROR(F1034*1000000/$E1034,"") -> 197.67172 | L1034: =IFERROR(G1034*1000000/$E1034,"") -> 166.8413 | M1034: =IFERROR(H1034*1000000/$E1034,"") -> 138.8065 | N1034: =IFERROR(I1034*1000000/$E1034,"") -> 503.31952 | O1034: =IFERROR(J1034*1000000/$E1034,"") -> 388.54814

Sheet Peer Medians
A1: Median of utility-level per-customer values, by peer group and year (nominal $), with FirstEnergy consolidated for comparison
A3: Year | B3: FirstEnergy consolidated: total costs per customer | C3: Northeast peers: median total costs per customer | D3: Midwest peers: median total costs per customer | E3: FirstEnergy consolidated: capital additions per customer | F3: Northeast peers: median capital additions per customer | G3: Midwest peers: median capital additions per customer
A4: 2000 | B4: ='Group Results'!L5 -> 206.97853 | C4: {=MEDIAN(IF(('Utility Results'!$A$4:$A$1008=$A4)*('Utility Results'!$C$4:$C$1008="Northeast peers"),'Utility Results'!$N$4:$N$1008))} -> 202.3303 | D4: {=MEDIAN(IF(('Utility Results'!$A$4:$A$1008=$A4)*('Utility Results'!$C$4:$C$1008="Midwest peers"),'Utility Results'!$N$4:$N$1008))} -> 205.49699 | E4: ='Group Results'!M5 -> 79.146116 | F4: {=MEDIAN(IF(('Utility Results'!$A$4:$A$1008=$A4)*('Utility Results'!$C$4:$C$1008="Northeast peers"),'Utility Results'!$O$4:$O$1008))} -> 91.677748 | G4: {=MEDIAN(IF(('Utility Results'!$A$4:$A$1008=$A4)*('Utility Results'!$C$4:$C$1008="Midwest peers"),'Utility Results'!$O$4:$O$1008))} -> 103.82264
A5: 2001 | B5: ='Group Results'!L6 -> 186.07534 | C5: {=MEDIAN(IF(('Utility Results'!$A$4:$A$1008=$A5)*('Utility Results'!$C$4:$C$1008="Northeast peers"),'Utility Results'!$N$4:$N$1008))} -> 207.86836 | D5: {=MEDIAN(IF(('Utility Results'!$A$4:$A$1008=$A5)*('Utility Results'!$C$4:$C$1008="Midwest peers"),'Utility Results'!$N$4:$N$1008))} -> 209.50427 | E5: ='Group Results'!M6 -> 76.48206 | F5: {=MEDIAN(IF(('Utility Results'!$A$4:$A$1008=$A5)*('Utility Results'!$C$4:$C$1008="Northeast peers"),'Utility Results'!$O$4:$O$1008))} -> 90.693806 | G5: {=MEDIAN(IF(('Utility Results'!$A$4:$A$1008=$A5)*('Utility Results'!$C$4:$C$1008="Midwest peers"),'Utility Results'!$O$4:$O$1008))} -> 105.53069
A6: 2002 | B6: ='Group Results'!L7 -> 175.53909 | C6: {=MEDIAN(IF(('Utility Results'!$A$4:$A$1008=$A6)*('Utility Results'!$C$4:$C$1008="Northeast peers"),'Utility Results'!$N$4:$N$1008))} -> 194.35352 | D6: {=MEDIAN(IF(('Utility Results'!$A$4:$A$1008=$A6)*('Utility Results'!$C$4:$C$1008="Midwest peers"),'Utility Results'!$N$4:$N$1008))} -> 215.90446 | E6: ='Group Results'!M7 -> 70.241116 | F6: {=MEDIAN(IF(('Utility Results'!$A$4:$A$1008=$A6)*('Utility Results'!$C$4:$C$1008="Northeast peers"),'Utility Results'!$O$4:$O$1008))} -> 89.848902 | G6: {=MEDIAN(IF(('Utility Results'!$A$4:$A$1008=$A6)*('Utility Results'!$C$4:$C$1008="Midwest peers"),'Utility Results'!$O$4:$O$1008))} -> 110.59122
A7: 2003 | B7: ='Group Results'!L8 -> 196.5519 | C7: {=MEDIAN(IF(('Utility Results'!$A$4:$A$1008=$A7)*('Utility Results'!$C$4:$C$1008="Northeast peers"),'Utility Results'!$N$4:$N$1008))} -> 211.47695 | D7: {=MEDIAN(IF(('Utility Results'!$A$4:$A$1008=$A7)*('Utility Results'!$C$4:$C$1008="Midwest peers"),'Utility Results'!$N$4:$N$1008))} -> 220.02112 | E7: ='Group Results'!M8 -> 76.061123 | F7: {=MEDIAN(IF(('Utility Results'!$A$4:$A$1008=$A7)*('Utility Results'!$C$4:$C$1008="Northeast peers"),'Utility Results'!$O$4:$O$1008))} -> 90.64461 | G7: {=MEDIAN(IF(('Utility Results'!$A$4:$A$1008=$A7)*('Utility Results'!$C$4:$C$1008="Midwest peers"),'Utility Results'!$O$4:$O$1008))} -> 109.77799
A8: 2004 | B8: ='Group Results'!L9 -> 177.37904 | C8: {=MEDIAN(IF(('Utility Results'!$A$4:$A$1008=$A8)*('Utility Results'!$C$4:$C$1008="Northeast peers"),'Utility Results'!$N$4:$N$1008))} -> 210.40467 | D8: {=MEDIAN(IF(('Utility Results'!$A$4:$A$1008=$A8)*('Utility Results'!$C$4:$C$1008="Midwest peers"),'Utility Results'!$N$4:$N$1008))} -> 217.58834 | E8: ='Group Results'!M9 -> 87.14987 | F8: {=MEDIAN(IF(('Utility Results'!$A$4:$A$1008=$A8)*('Utility Results'!$C$4:$C$1008="Northeast peers"),'Utility Results'!$O$4:$O$1008))} -> 100.04265 | G8: {=MEDIAN(IF(('Utility Results'!$A$4:$A$1008=$A8)*('Utility Results'!$C$4:$C$1008="Midwest peers"),'Utility Results'!$O$4:$O$1008))} -> 123.21306
A9: 2005 | B9: ='Group Results'!L10 -> 188.67854 | C9: {=MEDIAN(IF(('Utility Results'!$A$4:$A$1008=$A9)*('Utility Results'!$C$4:$C$1008="Northeast peers"),'Utility Results'!$N$4:$N$1008))} -> 213.51051 | D9: {=MEDIAN(IF(('Utility Results'!$A$4:$A$1008=$A9)*('Utility Results'!$C$4:$C$1008="Midwest peers"),'Utility Results'!$N$4:$N$1008))} -> 222.29609 | E9: ='Group Results'!M10 -> 113.30595 | F9: {=MEDIAN(IF(('Utility Results'!$A$4:$A$1008=$A9)*('Utility Results'!$C$4:$C$1008="Northeast peers"),'Utility Results'!$O$4:$O$1008))} -> 101.81018 | G9: {=MEDIAN(IF(('Utility Results'!$A$4:$A$1008=$A9)*('Utility Results'!$C$4:$C$1008="Midwest peers"),'Utility Results'!$O$4:$O$1008))} -> 113.8656
A10: 2006 | B10: ='Group Results'!L11 -> 192.12 | C10: {=MEDIAN(IF(('Utility Results'!$A$4:$A$1008=$A10)*('Utility Results'!$C$4:$C$1008="Northeast peers"),'Utility Results'!$N$4:$N$1008))} -> 213.96823 | D10: {=MEDIAN(IF(('Utility Results'!$A$4:$A$1008=$A10)*('Utility Results'!$C$4:$C$1008="Midwest peers"),'Utility Results'!$N$4:$N$1008))} -> 226.48412 | E10: ='Group Results'!M11 -> 112.48317 | F10: {=MEDIAN(IF(('Utility Results'!$A$4:$A$1008=$A10)*('Utility Results'!$C$4:$C$1008="Northeast peers"),'Utility Results'!$O$4:$O$1008))} -> 140.74769 | G10: {=MEDIAN(IF(('Utility Results'!$A$4:$A$1008=$A10)*('Utility Results'!$C$4:$C$1008="Midwest peers"),'Utility Results'!$O$4:$O$1008))} -> 123.87501
A11: 2007 | B11: ='Group Results'!L12 -> 204.38851 | C11: {=MEDIAN(IF(('Utility Results'!$A$4:$A$1008=$A11)*('Utility Results'!$C$4:$C$1008="Northeast peers"),'Utility Results'!$N$4:$N$1008))} -> 236.68627 | D11: {=MEDIAN(IF(('Utility Results'!$A$4:$A$1008=$A11)*('Utility Results'!$C$4:$C$1008="Midwest peers"),'Utility Results'!$N$4:$N$1008))} -> 233.86936 | E11: ='Group Results'!M12 -> 113.06592 | F11: {=MEDIAN(IF(('Utility Results'!$A$4:$A$1008=$A11)*('Utility Results'!$C$4:$C$1008="Northeast peers"),'Utility Results'!$O$4:$O$1008))} -> 139.61635 | G11: {=MEDIAN(IF(('Utility Results'!$A$4:$A$1008=$A11)*('Utility Results'!$C$4:$C$1008="Midwest peers"),'Utility Results'!$O$4:$O$1008))} -> 146.55383
A12: 2008 | B12: ='Group Results'!L13 -> 213.13449 | C12: {=MEDIAN(IF(('Utility Results'!$A$4:$A$1008=$A12)*('Utility Results'!$C$4:$C$1008="Northeast peers"),'Utility Results'!$N$4:$N$1008))} -> 251.2457 | D12: {=MEDIAN(IF(('Utility Results'!$A$4:$A$1008=$A12)*('Utility Results'!$C$4:$C$1008="Midwest peers"),'Utility Results'!$N$4:$N$1008))} -> 248.90143 | E12: ='Group Results'!M13 -> 132.47331 | F12: {=MEDIAN(IF(('Utility Results'!$A$4:$A$1008=$A12)*('Utility Results'!$C$4:$C$1008="Northeast peers"),'Utility Results'!$O$4:$O$1008))} -> 139.69674 | G12: {=MEDIAN(IF(('Utility Results'!$A$4:$A$1008=$A12)*('Utility Results'!$C$4:$C$1008="Midwest peers"),'Utility Results'!$O$4:$O$1008))} -> 160.0162
A13: 2009 | B13: ='Group Results'!L14 -> 197.2789 | C13: {=MEDIAN(IF(('Utility Results'!$A$4:$A$1008=$A13)*('Utility Results'!$C$4:$C$1008="Northeast peers"),'Utility Results'!$N$4:$N$1008))} -> 257.26523 | D13: {=MEDIAN(IF(('Utility Results'!$A$4:$A$1008=$A13)*('Utility Results'!$C$4:$C$1008="Midwest peers"),'Utility Results'!$N$4:$N$1008))} -> 246.93396 | E13: ='Group Results'!M14 -> 128.62625 | F13: {=MEDIAN(IF(('Utility Results'!$A$4:$A$1008=$A13)*('Utility Results'!$C$4:$C$1008="Northeast peers"),'Utility Results'!$O$4:$O$1008))} -> 147.76377 | G13: {=MEDIAN(IF(('Utility Results'!$A$4:$A$1008=$A13)*('Utility Results'!$C$4:$C$1008="Midwest peers"),'Utility Results'!$O$4:$O$1008))} -> 134.21479
A14: 2010 | B14: ='Group Results'!L15 -> 199.95826 | C14: {=MEDIAN(IF(('Utility Results'!$A$4:$A$1008=$A14)*('Utility Results'!$C$4:$C$1008="Northeast peers"),'Utility Results'!$N$4:$N$1008))} -> 288.83722 | D14: {=MEDIAN(IF(('Utility Results'!$A$4:$A$1008=$A14)*('Utility Results'!$C$4:$C$1008="Midwest peers"),'Utility Results'!$N$4:$N$1008))} -> 262.5041 | E14: ='Group Results'!M15 -> 123.76631 | F14: {=MEDIAN(IF(('Utility Results'!$A$4:$A$1008=$A14)*('Utility Results'!$C$4:$C$1008="Northeast peers"),'Utility Results'!$O$4:$O$1008))} -> 168.32012 | G14: {=MEDIAN(IF(('Utility Results'!$A$4:$A$1008=$A14)*('Utility Results'!$C$4:$C$1008="Midwest peers"),'Utility Results'!$O$4:$O$1008))} -> 127.06219
A15: 2011 | B15: ='Group Results'!L16 -> 236.48444 | C15: {=MEDIAN(IF(('Utility Results'!$A$4:$A$1008=$A15)*('Utility Results'!$C$4:$C$1008="Northeast peers"),'Utility Results'!$N$4:$N$1008))} -> 320.81246 | D15: {=MEDIAN(IF(('Utility Results'!$A$4:$A$1008=$A15)*('Utility Results'!$C$4:$C$1008="Midwest peers"),'Utility Results'!$N$4:$N$1008))} -> 269.47601 | E15: ='Group Results'!M16 -> 117.00142 | F15: {=MEDIAN(IF(('Utility Results'!$A$4:$A$1008=$A15)*('Utility Results'!$C$4:$C$1008="Northeast peers"),'Utility Results'!$O$4:$O$1008))} -> 167.75495 | G15: {=MEDIAN(IF(('Utility Results'!$A$4:$A$1008=$A15)*('Utility Results'!$C$4:$C$1008="Midwest peers"),'Utility Results'!$O$4:$O$1008))} -> 143.51191
... A29: 2025 | B29: ='Group Results'!L30 -> 418.15015 | C29: {=MEDIAN(IF(('Utility Results'!$A$4:$A$1008=$A29)*('Utility Results'!$C$4:$C$1008="Northeast peers"),'Utility Results'!$N$4:$N$1008))} -> 501.4543 | D29: {=MEDIAN(IF(('Utility Results'!$A$4:$A$1008=$A29)*('Utility Results'!$C$4:$C$1008="Midwest peers"),'Utility Results'!$N$4:$N$1008))} -> 396.85614 | E29: ='Group Results'!M30 -> 310.63182 | F29: {=MEDIAN(IF(('Utility Results'!$A$4:$A$1008=$A29)*('Utility Results'!$C$4:$C$1008="Northeast peers"),'Utility Results'!$O$4:$O$1008))} -> 422.99015 | G29: {=MEDIAN(IF(('Utility Results'!$A$4:$A$1008=$A29)*('Utility Results'!$C$4:$C$1008="Midwest peers"),'Utility Results'!$O$4:$O$1008))} -> 585.21138

Sheet Reconciliation
A1: Line items compared with reported subtotals, by utility and year
A2: Tolerance (share of reported subtotal): | D2: 0.005
A3: Distribution O&M: accounts 580–598 line items vs PUDL subtotal distribution_expenses. Customer costs: accounts 901–910 line items vs customer_account_expenses + customer_service_and_information_expenses. Capital additions: distribution plant line items (p. 204) vs PUDL subtotal distribution_plant.
A5: Year | B5: Utility | C5: Distribution O&M line items ($mm) | D5: Reported distribution expenses ($mm) | E5: Difference (%) | F5: Customer cost line items ($mm) | G5: Reported customer accounts + service ($mm) | H5: Difference (%) | I5: Capital additions line items ($mm) | J5: Reported distribution plant additions ($mm) | K5: Difference (%) | L5: Status
A6: 2000 | B6: AEP Ohio (Ohio Power) | C6: 98.937796 | D6: 98.937796 | E6: =IF(OR(D6="",D6=0),"",(C6-D6)/D6) -> 0 | F6: 76.065082 | G6: 76.065082 | H6: =IF(OR(G6="",G6=0),"",(F6-G6)/G6) -> 0 | I6: 145.20209 | J6: 145.20209 | K6: =IF(OR(J6="",J6=0),"",(I6-J6)/J6) -> 0 | L6: =IF(OR(D6="",G6="",J6=""),"No reported subtotal",IF(AND(ABS(N(E6))<=$D$2,ABS(N(H6))<=$D$2,ABS(N(K6))<=$D$2),"Reconciles within tolerance","Outside tolerance")) -> Reconciles within tolerance
A7: 2001 | B7: AEP Ohio (Ohio Power) | C7: 101.18151 | D7: 101.18151 | E7: =IF(OR(D7="",D7=0),"",(C7-D7)/D7) -> 0 | F7: 85.498352 | G7: 85.498352 | H7: =IF(OR(G7="",G7=0),"",(F7-G7)/G7) -> 0 | I7: 133.76301 | J7: 133.76301 | K7: =IF(OR(J7="",J7=0),"",(I7-J7)/J7) -> 0 | L7: =IF(OR(D7="",G7="",J7=""),"No reported subtotal",IF(AND(ABS(N(E7))<=$D$2,ABS(N(H7))<=$D$2,ABS(N(K7))<=$D$2),"Reconciles within tolerance","Outside tolerance")) -> Reconciles within tolerance
A8: 2002 | B8: AEP Ohio (Ohio Power) | C8: 100.22896 | D8: 100.22896 | E8: =IF(OR(D8="",D8=0),"",(C8-D8)/D8) -> 0 | F8: 83.462876 | G8: 83.462876 | H8: =IF(OR(G8="",G8=0),"",(F8-G8)/G8) -> 0 | I8: 116.49444 | J8: 116.49444 | K8: =IF(OR(J8="",J8=0),"",(I8-J8)/J8) -> 0 | L8: =IF(OR(D8="",G8="",J8=""),"No reported subtotal",IF(AND(ABS(N(E8))<=$D$2,ABS(N(H8))<=$D$2,ABS(N(K8))<=$D$2),"Reconciles within tolerance","Outside tolerance")) -> Reconciles within tolerance
A9: 2003 | B9: AEP Ohio (Ohio Power) | C9: 115.75754 | D9: 115.75754 | E9: =IF(OR(D9="",D9=0),"",(C9-D9)/D9) -> 0 | F9: 87.940149 | G9: 87.940149 | H9: =IF(OR(G9="",G9=0),"",(F9-G9)/G9) -> 0 | I9: 117.53452 | J9: 117.53452 | K9: =IF(OR(J9="",J9=0),"",(I9-J9)/J9) -> 0 | L9: =IF(OR(D9="",G9="",J9=""),"No reported subtotal",IF(AND(ABS(N(E9))<=$D$2,ABS(N(H9))<=$D$2,ABS(N(K9))<=$D$2),"Reconciles within tolerance","Outside tolerance")) -> Reconciles within tolerance
A10: 2004 | B10: AEP Ohio (Ohio Power) | C10: 141.91405 | D10: 141.91405 | E10: =IF(OR(D10="",D10=0),"",(C10-D10)/D10) -> 0 | F10: 96.147976 | G10: 96.147976 | H10: =IF(OR(G10="",G10=0),"",(F10-G10)/G10) -> 0 | I10: 129.38981 | J10: 129.38981 | K10: =IF(OR(J10="",J10=0),"",(I10-J10)/J10) -> 0 | L10: =IF(OR(D10="",G10="",J10=""),"No reported subtotal",IF(AND(ABS(N(E10))<=$D$2,ABS(N(H10))<=$D$2,ABS(N(K10))<=$D$2),"Reconciles within tolerance","Outside tolerance")) -> Reconciles within tolerance
A11: 2005 | B11: AEP Ohio (Ohio Power) | C11: 139.96691 | D11: 139.96691 | E11: =IF(OR(D11="",D11=0),"",(C11-D11)/D11) -> 0 | F11: 93.40766 | G11: 93.40766 | H11: =IF(OR(G11="",G11=0),"",(F11-G11)/G11) -> 0 | I11: 134.44074 | J11: 134.44074 | K11: =IF(OR(J11="",J11=0),"",(I11-J11)/J11) -> 0 | L11: =IF(OR(D11="",G11="",J11=""),"No reported subtotal",IF(AND(ABS(N(E11))<=$D$2,ABS(N(H11))<=$D$2,ABS(N(K11))<=$D$2),"Reconciles within tolerance","Outside tolerance")) -> Reconciles within tolerance
A12: 2006 | B12: AEP Ohio (Ohio Power) | C12: 113.73831 | D12: 113.73831 | E12: =IF(OR(D12="",D12=0),"",(C12-D12)/D12) -> 0 | F12: 95.901185 | G12: 95.901185 | H12: =IF(OR(G12="",G12=0),"",(F12-G12)/G12) -> 0 | I12: 250.29192 | J12: 250.29192 | K12: =IF(OR(J12="",J12=0),"",(I12-J12)/J12) -> 0 | L12: =IF(OR(D12="",G12="",J12=""),"No reported subtotal",IF(AND(ABS(N(E12))<=$D$2,ABS(N(H12))<=$D$2,ABS(N(K12))<=$D$2),"Reconciles within tolerance","Outside tolerance")) -> Reconciles within tolerance
A13: 2007 | B13: AEP Ohio (Ohio Power) | C13: 128.85737 | D13: 128.85737 | E13: =IF(OR(D13="",D13=0),"",(C13-D13)/D13) -> 0 | F13: 94.402228 | G13: 94.402228 | H13: =IF(OR(G13="",G13=0),"",(F13-G13)/G13) -> 0 | I13: 198.16119 | J13: 198.16119 | K13: =IF(OR(J13="",J13=0),"",(I13-J13)/J13) -> 0 | L13: =IF(OR(D13="",G13="",J13=""),"No reported subtotal",IF(AND(ABS(N(E13))<=$D$2,ABS(N(H13))<=$D$2,ABS(N(K13))<=$D$2),"Reconciles within tolerance","Outside tolerance")) -> Reconciles within tolerance
A14: 2008 | B14: AEP Ohio (Ohio Power) | C14: 131.91483 | D14: 131.91483 | E14: =IF(OR(D14="",D14=0),"",(C14-D14)/D14) -> 0 | F14: 119.408 | G14: 119.408 | H14: =IF(OR(G14="",G14=0),"",(F14-G14)/G14) -> 0 | I14: 201.18727 | J14: 201.18727 | K14: =IF(OR(J14="",J14=0),"",(I14-J14)/J14) -> 0 | L14: =IF(OR(D14="",G14="",J14=""),"No reported subtotal",IF(AND(ABS(N(E14))<=$D$2,ABS(N(H14))<=$D$2,ABS(N(K14))<=$D$2),"Reconciles within tolerance","Outside tolerance")) -> Reconciles within tolerance
A15: 2009 | B15: AEP Ohio (Ohio Power) | C15: 153.80512 | D15: 153.80512 | E15: =IF(OR(D15="",D15=0),"",(C15-D15)/D15) -> 0 | F15: 102.72209 | G15: 102.72209 | H15: =IF(OR(G15="",G15=0),"",(F15-G15)/G15) -> 0 | I15: 269.12845 | J15: 269.12845 | K15: =IF(OR(J15="",J15=0),"",(I15-J15)/J15) -> 0 | L15: =IF(OR(D15="",G15="",J15=""),"No reported subtotal",IF(AND(ABS(N(E15))<=$D$2,ABS(N(H15))<=$D$2,ABS(N(K15))<=$D$2),"Reconciles within tolerance","Outside tolerance")) -> Reconciles within tolerance
A16: 2010 | B16: AEP Ohio (Ohio Power) | C16: 178.62729 | D16: 178.62729 | E16: =IF(OR(D16="",D16=0),"",(C16-D16)/D16) -> 0 | F16: 179.15741 | G16: 179.15741 | H16: =IF(OR(G16="",G16=0),"",(F16-G16)/G16) -> 0 | I16: 160.33133 | J16: 160.33133 | K16: =IF(OR(J16="",J16=0),"",(I16-J16)/J16) -> 0 | L16: =IF(OR(D16="",G16="",J16=""),"No reported subtotal",IF(AND(ABS(N(E16))<=$D$2,ABS(N(H16))<=$D$2,ABS(N(K16))<=$D$2),"Reconciles within tolerance","Outside tolerance")) -> Reconciles within tolerance
A17: 2011 | B17: AEP Ohio (Ohio Power) | C17: 141.7453 | D17: 141.7453 | E17: =IF(OR(D17="",D17=0),"",(C17-D17)/D17) -> 0 | F17: 236.1872 | G17: 236.1872 | H17: =IF(OR(G17="",G17=0),"",(F17-G17)/G17) -> 0 | I17: 163.89282 | J17: 163.89282 | K17: =IF(OR(J17="",J17=0),"",(I17-J17)/J17) -> 0 | L17: =IF(OR(D17="",G17="",J17=""),"No reported subtotal",IF(AND(ABS(N(E17))<=$D$2,ABS(N(H17))<=$D$2,ABS(N(K17))<=$D$2),"Reconciles within tolerance","Outside tolerance")) -> Reconciles within tolerance
... A1010: 2025 | B1010: Wisconsin Public Service | C1010: 45.865031 | D1010: 45.865031 | E1010: =IF(OR(D1010="",D1010=0),"",(C1010-D1010)/D1010) -> 0 | F1010: 41.917457 | G1010: 41.917457 | H1010: =IF(OR(G1010="",G1010=0),"",(F1010-G1010)/G1010) -> 0 | I1010: 211.63783 | J1010: 211.63783 | K1010: =IF(OR(J1010="",J1010=0),"",(I1010-J1010)/J1010) -> 0 | L1010: =IF(OR(D1010="",G1010="",J1010=""),"No reported subtotal",IF(AND(ABS(N(E1010))<=$D$2,ABS(N(H1010))<=$D$2,ABS(N(K1010))<=$D$2),"Reconciles within tolerance","Outside tolerance")) -> Reconciles within tolerance
A1012: Utility-years outside tolerance: | E1012: =COUNTIF(L6:L1010,"Outside tolerance") -> 0
A1013: Utility-years with no reported subtotal: | E1013: =COUNTIF(L6:L1010,"No reported subtotal") -> 0

Sheet Peer Groups
A1: Utilities in the comparison
A3: Series name | B3: Group | C3: State(s) | D3: FERC respondent ID | E3: Years used | F3: PUDL respondent name
A4: Cleveland Electric Illuminating | B4: FirstEnergy | C4: OH | D4: 175 | E4: 2000–2025 | F4: Cleveland Electric Illuminating Company, The
A5: FirstEnergy Pennsylvania Electric | B5: FirstEnergy | C5: PA | D5: 451 | E5: 2024–2025 | F5: firstenergy pennsylvania electric company
A6: Jersey Central Power & Light | B6: FirstEnergy | C6: NJ | D6: 173 | E6: 2000–2025 | F6: Jersey Central Power & Light Company
A7: Metropolitan Edison | B7: FirstEnergy | C7: PA | D7: 179 | E7: 2000–2023 | F7: Metropolitan Edison Company
A8: Monongahela Power | B8: FirstEnergy | C8: WV | D8: 238 | E8: 2000–2025 | F8: MONONGAHELA POWER COMPANY
A9: Ohio Edison | B9: FirstEnergy | C9: OH | D9: 174 | E9: 2000–2025 | F9: Ohio Edison Company
A10: Pennsylvania Electric | B10: FirstEnergy | C10: PA | D10: 178 | E10: 2000–2023 | F10: Pennsylvania Electric Company
A11: Pennsylvania Power | B11: FirstEnergy | C11: PA | D11: 177 | E11: 2000–2023 | F11: Pennsylvania Power Company
A12: Potomac Edison | B12: FirstEnergy | C12: MD/WV | D12: 240 | E12: 2000–2025 | F12: THE POTOMAC EDISON COMPANY
A13: Toledo Edison | B13: FirstEnergy | C13: OH | D13: 176 | E13: 2000–2025 | F13: Toledo Edison Company, The
A14: West Penn Power | B14: FirstEnergy | C14: PA | D14: 237 | E14: 2000–2023 | F14: WEST PENN POWER COMPANY
A15: AEP Ohio (Ohio Power) | B15: Northeast peers | C15: OH | D15: 204 | E15: 2000–2025 | F15: Ohio Power Company
... A46: Wisconsin Public Service | B46: Midwest peers | C46: WI | D46: 187 | E46: 2000–2025 | F46: Wisconsin Public Service Corporation
A48: Northeast peers: investor-owned distribution utilities in FirstEnergy’s states (Ohio, Pennsylvania, New Jersey, Maryland, West Virginia) and adjoining Delaware, the District of Columbia and Virginia, chosen 2026-10-24.
A49: Midwest peers: the 17-utility group from the Midwest functional-share workbook (selection criteria on that workbook’s Peer Group sheet).
A50: FirstEnergy consolidated: the FirstEnergy distribution companies listed, summed in every year (current companies, including years before FirstEnergy owned them). Transmission-only subsidiaries (American Transmission Systems, Mid-Atlantic Interstate Transmission, Trans-Allegheny Interstate Line) are excluded.

Sheet Category Map
A1: Measure | B1: Source | C1: Accounts / rows
A2: Distribution O&M | B2: FERC Form 1 pp. 320–323 (Schedule 320) | C2: Accounts 580–598 line items; energy-storage O&M lines labeled distribution (2021–2025).
A3: Customer costs | B3: FERC Form 1 pp. 320–323 (Schedule 320) | C3: Accounts 901–905 (customer accounts) and 907–910 (customer service and information). Sales expenses 911–916 excluded.
A4: Distribution depreciation | B4: FERC Form 1 p. 336 Section A | C4: Plant function = distribution, row depreciation_amortization_total (accounts 403, 404, 405 and 403.1).
A5: Distribution capital additions | B5: FERC Form 1 pp. 204–207 (Schedule 204) | C5: Additions column, distribution plant line items (accounts 360–374 and energy storage equipment – distribution plant). Transfers, retirements and adjustments excluded.
A6: Distribution plant in service | B6: FERC Form 1 pp. 204–207 (Schedule 204) | C6: Ending balance, same line items. Shown on Data sheet for context.
A7: Customers | B7: FERC Form 1 p. 300; EIA-861 | C7: p. 300 average number of customers per month, sales to ultimate consumers; EIA-861 customers, service types bundled and delivery, all states.

Sheet Assumptions
A1: Adjustable inputs
A3: Customer-count substitution threshold | B3: 0.95 | C3: Where the FERC Form 1 p. 300 count is below this share of the EIA-861 count (bundled + delivery-only customers), the EIA-861 count is used.
A5: Constant-dollar base year | C5: Enter a base year and the GDP price index for each year (BEA NIPA Table 1.1.9, line 1, or FRED series A191RD3A086NBEA) to fill the constant-dollar columns on Group Results. The index was not retrieved for this workbook because the analysis environment’s network policy blocks BEA and FRED.
A7: Year | B7: GDP price index (enter)
A8: 2000
A9: 2001
A10: 2002
A11: 2003
A12: 2004
A13: 2005
A14: 2006
A15: 2007
A16: 2008
A17: 2009
A18: 2010
A19: 2011
... A33: 2025

Sheet Data
A1: Year | B1: Utility | C1: Group | D1: State | E1: Distribution O&M ($mm) | F1: Customer costs ($mm) | G1: Distribution depreciation ($mm) | H1: Distribution capital additions ($mm) | I1: Distribution plant in service, year end ($mm) | J1: Customers: FERC Form 1 p. 300 | K1: Customers: EIA-861 (bundled + delivery) | L1: Customers used | M1: Customer count source | N1: Total costs ($mm)
A2: 2000 | B2: Cleveland Electric Illuminating | C2: FirstEnergy | D2: OH | E2: 58.333212 | F2: 52.097101 | G2: 39.712796 | H2: 29.98762 | I2: 1174.3038 | J2: 743158 | L2: =IF(AND(K2<>"",J2<Assumptions!$B$3*K2),K2,J2) -> 743158 | M2: =IF(L2=J2,"FERC Form 1","EIA-861") -> FERC Form 1 | N2: =E2+F2+G2 -> 150.14311
A3: 2001 | B3: Cleveland Electric Illuminating | C3: FirstEnergy | D3: OH | E3: 50.480125 | F3: 22.972715 | G3: 40.252961 | H3: 31.219281 | I3: 1198.4419 | J3: 746261 | K3: 746261 | L3: =IF(AND(K3<>"",J3<Assumptions!$B$3*K3),K3,J3) -> 746261 | M3: =IF(L3=J3,"FERC Form 1","EIA-861") -> FERC Form 1 | N3: =E3+F3+G3 -> 113.7058
A4: 2002 | B4: Cleveland Electric Illuminating | C4: FirstEnergy | D4: OH | E4: 51.587632 | F4: 18.535717 | G4: 41.217447 | H4: 35.893336 | I4: 1229.1073 | J4: 751430 | K4: 751430 | L4: =IF(AND(K4<>"",J4<Assumptions!$B$3*K4),K4,J4) -> 751430 | M4: =IF(L4=J4,"FERC Form 1","EIA-861") -> FERC Form 1 | N4: =E4+F4+G4 -> 111.3408
A5: 2003 | B5: Cleveland Electric Illuminating | C5: FirstEnergy | D5: OH | E5: 56.673713 | F5: 26.916272 | G5: 42.665787 | H5: 57.245981 | I5: 1275.8514 | J5: 752331 | K5: 752331 | L5: =IF(AND(K5<>"",J5<Assumptions!$B$3*K5),K5,J5) -> 752331 | M5: =IF(L5=J5,"FERC Form 1","EIA-861") -> FERC Form 1 | N5: =E5+F5+G5 -> 126.25577
A6: 2004 | B6: Cleveland Electric Illuminating | C6: FirstEnergy | D6: OH | E6: 41.35222 | F6: 27.202062 | G6: 44.137398 | H6: 54.075849 | I6: 1324.3494 | J6: 753315 | K6: 753315 | L6: =IF(AND(K6<>"",J6<Assumptions!$B$3*K6),K6,J6) -> 753315 | M6: =IF(L6=J6,"FERC Form 1","EIA-861") -> FERC Form 1 | N6: =E6+F6+G6 -> 112.69168
A7: 2005 | B7: Cleveland Electric Illuminating | C7: FirstEnergy | D7: OH | E7: 51.431396 | F7: 29.955962 | G7: 46.074046 | H7: 77.57642 | I7: 1395.5125 | J7: 761559 | K7: 761560 | L7: =IF(AND(K7<>"",J7<Assumptions!$B$3*K7),K7,J7) -> 761559 | M7: =IF(L7=J7,"FERC Form 1","EIA-861") -> FERC Form 1 | N7: =E7+F7+G7 -> 127.4614
A8: 2006 | B8: Cleveland Electric Illuminating | C8: FirstEnergy | D8: OH | E8: 51.339538 | F8: 32.10322 | G8: 50.581681 | H8: 74.851378 | I8: 1466.3826 | J8: 761997 | K8: 761973 | L8: =IF(AND(K8<>"",J8<Assumptions!$B$3*K8),K8,J8) -> 761997 | M8: =IF(L8=J8,"FERC Form 1","EIA-861") -> FERC Form 1 | N8: =E8+F8+G8 -> 134.02444
A9: 2007 | B9: Cleveland Electric Illuminating | C9: FirstEnergy | D9: OH | E9: 52.79573 | F9: 35.715981 | G9: 51.127455 | H9: 110.73309 | I9: 1554.5393 | J9: 758319 | K9: 758320 | L9: =IF(AND(K9<>"",J9<Assumptions!$B$3*K9),K9,J9) -> 758319 | M9: =IF(L9=J9,"FERC Form 1","EIA-861") -> FERC Form 1 | N9: =E9+F9+G9 -> 139.63917
A10: 2008 | B10: Cleveland Electric Illuminating | C10: FirstEnergy | D10: OH | E10: 62.06567 | F10: 31.318751 | G10: 54.358327 | H10: 107.67591 | I10: 1639.9282 | J10: 755807 | K10: 755807 | L10: =IF(AND(K10<>"",J10<Assumptions!$B$3*K10),K10,J10) -> 755807 | M10: =IF(L10=J10,"FERC Form 1","EIA-861") -> FERC Form 1 | N10: =E10+F10+G10 -> 147.74275
A11: 2009 | B11: Cleveland Electric Illuminating | C11: FirstEnergy | D11: OH | E11: 38.396299 | F11: 28.678265 | G11: 54.620738 | H11: 87.02553 | I11: 1713.5926 | J11: 753865 | K11: 753865 | L11: =IF(AND(K11<>"",J11<Assumptions!$B$3*K11),K11,J11) -> 753865 | M11: =IF(L11=J11,"FERC Form 1","EIA-861") -> FERC Form 1 | N11: =E11+F11+G11 -> 121.6953
A12: 2010 | B12: Cleveland Electric Illuminating | C12: FirstEnergy | D12: OH | E12: 42.838939 | F12: 29.946873 | G12: 55.919917 | H12: 91.107647 | I12: 1790.4198 | J12: 752207 | K12: 752207 | L12: =IF(AND(K12<>"",J12<Assumptions!$B$3*K12),K12,J12) -> 752207 | M12: =IF(L12=J12,"FERC Form 1","EIA-861") -> FERC Form 1 | N12: =E12+F12+G12 -> 128.70573
A13: 2011 | B13: Cleveland Electric Illuminating | C13: FirstEnergy | D13: OH | E13: 39.997748 | F13: 29.591602 | G13: 59.790164 | H13: 88.096472 | I13: 1912.3032 | J13: 748935 | K13: 748935 | L13: =IF(AND(K13<>"",J13<Assumptions!$B$3*K13),K13,J13) -> 748935 | M13: =IF(L13=J13,"FERC Form 1","EIA-861") -> FERC Form 1 | N13: =E13+F13+G13 -> 129.37951
A14: 2012 | B14: Cleveland Electric Illuminating | C14: FirstEnergy | D14: OH | E14: 48.791592 | F14: 46.834057 | G14: 62.826979 | H14: 139.99176 | I14: 2023.6054 | J14: 745328 | K14: 745327 | L14: =IF(AND(K14<>"",J14<Assumptions!$B$3*K14),K14,J14) -> 745328 | M14: =IF(L14=J14,"FERC Form 1","EIA-861") -> FERC Form 1 | N14: =E14+F14+G14 -> 158.45263
... A27: 2025 | B27: Cleveland Electric Illuminating | C27: FirstEnergy | D27: OH | E27: 75.895897 | F27: 32.911024 | G27: 122.00261 | H27: 176.35815 | I27: 3264.5272 | J27: 759848 | K27: 759847 | L27: =IF(AND(K27<>"",J27<Assumptions!$B$3*K27),K27,J27) -> 759848 | M27: =IF(L27=J27,"FERC Form 1","EIA-861") -> FERC Form 1 | N27: =E27+F27+G27 -> 230.80953
A28: 2024 | B28: FirstEnergy Pennsylvania Electric | C28: FirstEnergy | D28: PA | E28: 312.48491 | F28: 263.34154 | G28: 257.83873 | H28: 491.39028 | I28: 10293.759 | J28: 2090443 | L28: =IF(AND(K28<>"",J28<Assumptions!$B$3*K28),K28,J28) -> 2090443 | M28: =IF(L28=J28,"FERC Form 1","EIA-861") -> FERC Form 1 | N28: =E28+F28+G28 -> 833.66518
A29: 2025 | B29: FirstEnergy Pennsylvania Electric | C29: FirstEnergy | D29: PA | E29: 414.53737 | F29: 349.88289 | G29: 291.09111 | H29: 814.8243 | I29: 11770.717 | J29: 2097100 | L29: =IF(AND(K29<>"",J29<Assumptions!$B$3*K29),K29,J29) -> 2097100 | M29: =IF(L29=J29,"FERC Form 1","EIA-861") -> FERC Form 1 | N29: =E29+F29+G29 -> 1055.5114
A30: 2000 | B30: Jersey Central Power & Light | C30: FirstEnergy | D30: NJ | E30: 102.35468 | F30: 97.350554 | G30: 78.199154 | H30: 107.60812 | I30: 2205.2994 | J30: 1002120 | L30: =IF(AND(K30<>"",J30<Assumptions!$B$3*K30),K30,J30) -> 1002120 | M30: =IF(L30=J30,"FERC Form 1","EIA-861") -> FERC Form 1 | N30: =E30+F30+G30 -> 277.90439
A31: 2001 | B31: Jersey Central Power & Light | C31: FirstEnergy | D31: NJ | E31: 108.17677 | F31: 75.218281 | G31: 84.196498 | H31: 127.16348 | I31: 2317.0631 | J31: 1017712 | K31: 1017712 | L31: =IF(AND(K31<>"",J31<Assumptions!$B$3*K31),K31,J31) -> 1017712 | M31: =IF(L31=J31,"FERC Form 1","EIA-861") -> FERC Form 1 | N31: =E31+F31+G31 -> 267.59155
A32: 2002 | B32: Jersey Central Power & Light | C32: FirstEnergy | D32: NJ | E32: 91.692371 | F32: 72.891725 | G32: 83.152863 | H32: 108.67218 | I32: 2392.2088 | J32: 1033938 | K32: 1033937 | L32: =IF(AND(K32<>"",J32<Assumptions!$B$3*K32),K32,J32) -> 1033938 | M32: =IF(L32=J32,"FERC Form 1","EIA-861") -> FERC Form 1 | N32: =E32+F32+G32 -> 247.73696
A33: 2003 | B33: Jersey Central Power & Light | C33: FirstEnergy | D33: NJ | E33: 144.98347 | F33: 88.798045 | G33: 68.756809 | H33: 86.208935 | I33: 2472.1155 | J33: 1045395 | K33: 1045395 | L33: =IF(AND(K33<>"",J33<Assumptions!$B$3*K33),K33,J33) -> 1045395 | M33: =IF(L33=J33,"FERC Form 1","EIA-861") -> FERC Form 1 | N33: =E33+F33+G33 -> 302.53832
A34: 2004 | B34: Jersey Central Power & Light | C34: FirstEnergy | D34: NJ | E34: 114.99262 | F34: 114.63535 | G34: 48.829156 | H34: 116.51618 | I34: 2572.2671 | J34: 1054959 | K34: 1054959 | L34: =IF(AND(K34<>"",J34<Assumptions!$B$3*K34),K34,J34) -> 1054959 | M34: =IF(L34=J34,"FERC Form 1","EIA-861") -> FERC Form 1 | N34: =E34+F34+G34 -> 278.45712
A35: 2005 | B35: Jersey Central Power & Light | C35: FirstEnergy | D35: NJ | E35: 118.0966 | F35: 124.25074 | G35: 51.276744 | H35: 148.92443 | I35: 2712.166 | J35: 1067246 | K35: 1067247 | L35: =IF(AND(K35<>"",J35<Assumptions!$B$3*K35),K35,J35) -> 1067246 | M35: =IF(L35=J35,"FERC Form 1","EIA-861") -> FERC Form 1 | N35: =E35+F35+G35 -> 293.62408
A36: 2006 | B36: Jersey Central Power & Light | C36: FirstEnergy | D36: NJ | E36: 102.82123 | F36: 121.84644 | G36: 56.322603 | H36: 144.41168 | I36: 2818.8607 | J36: 1077948 | K36: 1081904 | L36: =IF(AND(K36<>"",J36<Assumptions!$B$3*K36),K36,J36) -> 1077948 | M36: =IF(L36=J36,"FERC Form 1","EIA-861") -> FERC Form 1 | N36: =E36+F36+G36 -> 280.99027
A37: 2007 | B37: Jersey Central Power & Light | C37: FirstEnergy | D37: NJ | E37: 115.50053 | F37: 122.4401 | G37: 57.477109 | H37: 117.04135 | I37: 2897.6916 | J37: 1085244 | K37: 1085245 | L37: =IF(AND(K37<>"",J37<Assumptions!$B$3*K37),K37,J37) -> 1085244 | M37: =IF(L37=J37,"FERC Form 1","EIA-861") -> FERC Form 1 | N37: =E37+F37+G37 -> 295.41774
A38: 2008 | B38: Jersey Central Power & Light | C38: FirstEnergy | D38: NJ | E38: 113.11486 | F38: 136.87344 | G38: 62.833947 | H38: 135.73893 | I38: 2990.0169 | J38: 1089980 | K38: 1089980 | L38: =IF(AND(K38<>"",J38<Assumptions!$B$3*K38),K38,J38) -> 1089980 | M38: =IF(L38=J38,"FERC Form 1","EIA-861") -> FERC Form 1 | N38: =E38+F38+G38 -> 312.82225
A39: 2009 | B39: Jersey Central Power & Light | C39: FirstEnergy | D39: NJ | E39: 75.945317 | F39: 137.83203 | G39: 65.01907 | H39: 143.56382 | I39: 3110.7514 | J39: 1093885 | K39: 1093885 | L39: =IF(AND(K39<>"",J39<Assumptions!$B$3*K39),K39,J39) -> 1093885 | M39: =IF(L39=J39,"FERC Form 1","EIA-861") -> FERC Form 1 | N39: =E39+F39+G39 -> 278.79642
A40: 2010 | B40: Jersey Central Power & Light | C40: FirstEnergy | D40: NJ | E40: 89.786661 | F40: 140.00094 | G40: 70.168072 | H40: 144.67036 | I40: 3230.5803 | J40: 1097078 | K40: 1097078 | L40: =IF(AND(K40<>"",J40<Assumptions!$B$3*K40),K40,J40) -> 1097078 | M40: =IF(L40=J40,"FERC Form 1","EIA-861") -> FERC Form 1 | N40: =E40+F40+G40 -> 299.95567
A41: 2011 | B41: Jersey Central Power & Light | C41: FirstEnergy | D41: NJ | E41: 143.93586 | F41: 155.58431 | G41: 104.82742 | H41: 96.485478 | I41: 3468.1859 | J41: 1099194 | K41: 1099194 | L41: =IF(AND(K41<>"",J41<Assumptions!$B$3*K41),K41,J41) -> 1099194 | M41: =IF(L41=J41,"FERC Form 1","EIA-861") -> FERC Form 1 | N41: =E41+F41+G41 -> 404.34759
A42: 2012 | B42: Jersey Central Power & Light | C42: FirstEnergy | D42: NJ | E42: 195.37018 | F42: 168.57341 | G42: 245.74948 | H42: 583.95723 | I42: 4026.4546 | J42: 1100165 | K42: 1100165 | L42: =IF(AND(K42<>"",J42<Assumptions!$B$3*K42),K42,J42) -> 1100165 | M42: =IF(L42=J42,"FERC Form 1","EIA-861") -> FERC Form 1 | N42: =E42+F42+G42 -> 609.69307
... A55: 2025 | B55: Jersey Central Power & Light | C55: FirstEnergy | D55: NJ | E55: 253.40012 | F55: 182.51496 | G55: 193.12159 | H55: 399.38442 | I55: 6355.8949 | J55: 1181664 | K55: 1181665 | L55: =IF(AND(K55<>"",J55<Assumptions!$B$3*K55),K55,J55) -> 1181664 | M55: =IF(L55=J55,"FERC Form 1","EIA-861") -> FERC Form 1 | N55: =E55+F55+G55 -> 629.03667
A56: 2000 | B56: Metropolitan Edison | C56: FirstEnergy | D56: PA | E56: 35.78359 | F56: 45.498449 | G56: 25.302159 | H56: 41.130203 | I56: 1072.0618 | J56: 491905 | L56: =IF(AND(K56<>"",J56<Assumptions!$B$3*K56),K56,J56) -> 491905 | M56: =IF(L56=J56,"FERC Form 1","EIA-861") -> FERC Form 1 | N56: =E56+F56+G56 -> 106.5842
A57: 2001 | B57: Metropolitan Edison | C57: FirstEnergy | D57: PA | E57: 39.462252 | F57: 39.455152 | G57: 28.008562 | H57: 47.429784 | I57: 1110.2943 | J57: 498988 | K57: 498988 | L57: =IF(AND(K57<>"",J57<Assumptions!$B$3*K57),K57,J57) -> 498988 | M57: =IF(L57=J57,"FERC Form 1","EIA-861") -> FERC Form 1 | N57: =E57+F57+G57 -> 106.92597
A58: 2002 | B58: Metropolitan Edison | C58: FirstEnergy | D58: PA | E58: 36.783415 | F58: 30.343009 | G58: 25.386747 | H58: 34.908563 | I58: 1136.1601 | J58: 506134 | K58: 506116 | L58: =IF(AND(K58<>"",J58<Assumptions!$B$3*K58),K58,J58) -> 506134 | M58: =IF(L58=J58,"FERC Form 1","EIA-861") -> FERC Form 1 | N58: =E58+F58+G58 -> 92.513171
A59: 2003 | B59: Metropolitan Edison | C59: FirstEnergy | D59: PA | E59: 48.5669 | F59: 34.914746 | G59: 24.794417 | H59: 34.240901 | I59: 1167.4372 | J59: 513023 | K59: 513023 | L59: =IF(AND(K59<>"",J59<Assumptions!$B$3*K59),K59,J59) -> 513023 | M59: =IF(L59=J59,"FERC Form 1","EIA-861") -> FERC Form 1 | N59: =E59+F59+G59 -> 108.27606
A60: 2004 | B60: Metropolitan Edison | C60: FirstEnergy | D60: PA | E60: 41.245477 | F60: 26.697829 | G60: 25.148946 | H60: 48.168135 | I60: 1203.749 | J60: 520687 | K60: 520687 | L60: =IF(AND(K60<>"",J60<Assumptions!$B$3*K60),K60,J60) -> 520687 | M60: =IF(L60=J60,"FERC Form 1","EIA-861") -> FERC Form 1 | N60: =E60+F60+G60 -> 93.092252
A61: 2005 | B61: Metropolitan Edison | C61: FirstEnergy | D61: PA | E61: 36.860847 | F61: 33.427865 | G61: 25.568029 | H61: 75.085664 | I61: 1273.284 | J61: 530011 | K61: 530011 | L61: =IF(AND(K61<>"",J61<Assumptions!$B$3*K61),K61,J61) -> 530011 | M61: =IF(L61=J61,"FERC Form 1","EIA-861") -> FERC Form 1 | N61: =E61+F61+G61 -> 95.856741
A62: 2006 | B62: Metropolitan Edison | C62: FirstEnergy | D62: PA | E62: 41.163652 | F62: 32.78154 | G62: 26.73162 | H62: 65.904204 | I62: 1319.1549 | J62: 538150 | K62: 541680 | L62: =IF(AND(K62<>"",J62<Assumptions!$B$3*K62),K62,J62) -> 538150 | M62: =IF(L62=J62,"FERC Form 1","EIA-861") -> FERC Form 1 | N62: =E62+F62+G62 -> 100.67681
A63: 2007 | B63: Metropolitan Edison | C63: FirstEnergy | D63: PA | E63: 50.335894 | F63: 40.951743 | G63: 28.034456 | H63: 78.743978 | I63: 1387.376 | J63: 543811 | K63: 543811 | L63: =IF(AND(K63<>"",J63<Assumptions!$B$3*K63),K63,J63) -> 543811 | M63: =IF(L63=J63,"FERC Form 1","EIA-861") -> FERC Form 1 | N63: =E63+F63+G63 -> 119.32209
A64: 2008 | B64: Metropolitan Edison | C64: FirstEnergy | D64: PA | E64: 44.378985 | F64: 47.939829 | G64: 29.732254 | H64: 77.724798 | I64: 1455.1458 | J64: 547557 | K64: 547557 | L64: =IF(AND(K64<>"",J64<Assumptions!$B$3*K64),K64,J64) -> 547557 | M64: =IF(L64=J64,"FERC Form 1","EIA-861") -> FERC Form 1 | N64: =E64+F64+G64 -> 122.05107
A65: 2009 | B65: Metropolitan Edison | C65: FirstEnergy | D65: PA | E65: 33.373649 | F65: 49.683748 | G65: 31.651436 | H65: 93.683433 | I65: 1540.4264 | J65: 549818 | K65: 549819 | L65: =IF(AND(K65<>"",J65<Assumptions!$B$3*K65),K65,J65) -> 549818 | M65: =IF(L65=J65,"FERC Form 1","EIA-861") -> FERC Form 1 | N65: =E65+F65+G65 -> 114.70883
A66: 2010 | B66: Metropolitan Edison | C66: FirstEnergy | D66: PA | E66: 37.612011 | F66: 57.619894 | G66: 33.718037 | H66: 79.37353 | I66: 1613.1439 | J66: 551776 | K66: 551776 | L66: =IF(AND(K66<>"",J66<Assumptions!$B$3*K66),K66,J66) -> 551776 | M66: =IF(L66=J66,"FERC Form 1","EIA-861") -> FERC Form 1 | N66: =E66+F66+G66 -> 128.94994
A67: 2011 | B67: Metropolitan Edison | C67: FirstEnergy | D67: PA | E67: 48.484714 | F67: 74.4068 | G67: 47.65817 | H67: 78.13427 | I67: 1801.9188 | J67: 552631 | K67: 552631 | L67: =IF(AND(K67<>"",J67<Assumptions!$B$3*K67),K67,J67) -> 552631 | M67: =IF(L67=J67,"FERC Form 1","EIA-861") -> FERC Form 1 | N67: =E67+F67+G67 -> 170.54968
A68: 2012 | B68: Metropolitan Edison | C68: FirstEnergy | D68: PA | E68: 49.313186 | F68: 75.539323 | G68: 57.631061 | H68: 126.96415 | I68: 1918.6657 | J68: 553405 | K68: 553405 | L68: =IF(AND(K68<>"",J68<Assumptions!$B$3*K68),K68,J68) -> 553405 | M68: =IF(L68=J68,"FERC Form 1","EIA-861") -> FERC Form 1 | N68: =E68+F68+G68 -> 182.48357
... A79: 2023 | B79: Metropolitan Edison | C79: FirstEnergy | D79: PA | E79: 85.83434 | F79: 67.421184 | G79: 73.635331 | H79: 142.15877 | I79: 2933.5663 | J79: 588329 | K79: 588330 | L79: =IF(AND(K79<>"",J79<Assumptions!$B$3*K79),K79,J79) -> 588329 | M79: =IF(L79=J79,"FERC Form 1","EIA-861") -> FERC Form 1 | N79: =E79+F79+G79 -> 226.89085
A80: 2000 | B80: Monongahela Power | C80: FirstEnergy | D80: WV | E80: 34.314597 | F80: 15.751245 | G80: 20.224646 | H80: 38.784727 | I80: 823.09218 | J80: 387020 | L80: =IF(AND(K80<>"",J80<Assumptions!$B$3*K80),K80,J80) -> 387020 | M80: =IF(L80=J80,"FERC Form 1","EIA-861") -> FERC Form 1 | N80: =E80+F80+G80 -> 70.290488
A81: 2001 | B81: Monongahela Power | C81: FirstEnergy | D81: WV | E81: 34.525993 | F81: 17.278048 | G81: 20.822996 | H81: 36.548398 | I81: 853.91001 | J81: 389846 | K81: 389846 | L81: =IF(AND(K81<>"",J81<Assumptions!$B$3*K81),K81,J81) -> 389846 | M81: =IF(L81=J81,"FERC Form 1","EIA-861") -> FERC Form 1 | N81: =E81+F81+G81 -> 72.627037
A82: 2002 | B82: Monongahela Power | C82: FirstEnergy | D82: WV | E82: 33.857655 | F82: 15.410839 | G82: 21.586505 | H82: 35.769778 | I82: 883.05621 | J82: 393724 | K82: 393724 | L82: =IF(AND(K82<>"",J82<Assumptions!$B$3*K82),K82,J82) -> 393724 | M82: =IF(L82=J82,"FERC Form 1","EIA-861") -> FERC Form 1 | N82: =E82+F82+G82 -> 70.854999
A83: 2003 | B83: Monongahela Power | C83: FirstEnergy | D83: WV | E83: 37.518821 | F83: 18.966324 | G83: 22.318934 | H83: 33.176787 | I83: 912.02224 | J83: 395761 | K83: 395761 | L83: =IF(AND(K83<>"",J83<Assumptions!$B$3*K83),K83,J83) -> 395761 | M83: =IF(L83=J83,"FERC Form 1","EIA-861") -> FERC Form 1 | N83: =E83+F83+G83 -> 78.804079
A84: 2004 | B84: Monongahela Power | C84: FirstEnergy | D84: WV | E84: 36.706485 | F84: 11.143442 | G84: 23.20201 | H84: 39.156748 | I84: 945.43468 | J84: 397679 | K84: 397679 | L84: =IF(AND(K84<>"",J84<Assumptions!$B$3*K84),K84,J84) -> 397679 | M84: =IF(L84=J84,"FERC Form 1","EIA-861") -> FERC Form 1 | N84: =E84+F84+G84 -> 71.051937
A85: 2005 | B85: Monongahela Power | C85: FirstEnergy | D85: WV | E85: 41.870748 | F85: 12.457215 | G85: 23.90309 | H85: 43.855421 | I85: 930.89068 | J85: 400554 | K85: 400554 | L85: =IF(AND(K85<>"",J85<Assumptions!$B$3*K85),K85,J85) -> 400554 | M85: =IF(L85=J85,"FERC Form 1","EIA-861") -> FERC Form 1 | N85: =E85+F85+G85 -> 78.231053
A86: 2006 | B86: Monongahela Power | C86: FirstEnergy | D86: WV | E86: 34.708845 | F86: 11.839697 | G86: 23.506377 | H86: 42.259139 | I86: 968.22775 | J86: 375017 | K86: 375017 | L86: =IF(AND(K86<>"",J86<Assumptions!$B$3*K86),K86,J86) -> 375017 | M86: =IF(L86=J86,"FERC Form 1","EIA-861") -> FERC Form 1 | N86: =E86+F86+G86 -> 70.054919
A87: 2007 | B87: Monongahela Power | C87: FirstEnergy | D87: WV | E87: 32.082473 | F87: 12.089468 | G87: 24.715442 | H87: 43.147362 | I87: 1007.4592 | J87: 378558 | K87: 378558 | L87: =IF(AND(K87<>"",J87<Assumptions!$B$3*K87),K87,J87) -> 378558 | M87: =IF(L87=J87,"FERC Form 1","EIA-861") -> FERC Form 1 | N87: =E87+F87+G87 -> 68.887383
A88: 2008 | B88: Monongahela Power | C88: FirstEnergy | D88: WV | E88: 38.926662 | F88: 12.405926 | G88: 26.007636 | H88: 51.599979 | I88: 1054.1555 | J88: 381193 | K88: 381193 | L88: =IF(AND(K88<>"",J88<Assumptions!$B$3*K88),K88,J88) -> 381193 | M88: =IF(L88=J88,"FERC Form 1","EIA-861") -> FERC Form 1 | N88: =E88+F88+G88 -> 77.340224
A89: 2009 | B89: Monongahela Power | C89: FirstEnergy | D89: WV | E89: 46.802719 | F89: 13.526001 | G89: 27.44778 | H89: 66.716743 | I89: 1116.4156 | J89: 383621 | K89: 383621 | L89: =IF(AND(K89<>"",J89<Assumptions!$B$3*K89),K89,J89) -> 383621 | M89: =IF(L89=J89,"FERC Form 1","EIA-861") -> FERC Form 1 | N89: =E89+F89+G89 -> 87.7765
A90: 2010 | B90: Monongahela Power | C90: FirstEnergy | D90: WV | E90: 33.482406 | F90: 15.048501 | G90: 29.029225 | H90: 55.421482 | I90: 1167.5933 | J90: 385504 | K90: 385504 | L90: =IF(AND(K90<>"",J90<Assumptions!$B$3*K90),K90,J90) -> 385504 | M90: =IF(L90=J90,"FERC Form 1","EIA-861") -> FERC Form 1 | N90: =E90+F90+G90 -> 77.560132
A91: 2011 | B91: Monongahela Power | C91: FirstEnergy | D91: WV | E91: 31.191505 | F91: 13.466318 | G91: 30.094058 | H91: 65.290304 | I91: 1227.8366 | J91: 386819 | K91: 386819 | L91: =IF(AND(K91<>"",J91<Assumptions!$B$3*K91),K91,J91) -> 386819 | M91: =IF(L91=J91,"FERC Form 1","EIA-861") -> FERC Form 1 | N91: =E91+F91+G91 -> 74.751881
A92: 2012 | B92: Monongahela Power | C92: FirstEnergy | D92: WV | E92: 57.294248 | F92: 15.532182 | G92: 32.078144 | H92: 153.5632 | I92: 1377.9929 | J92: 386908 | K92: 386908 | L92: =IF(AND(K92<>"",J92<Assumptions!$B$3*K92),K92,J92) -> 386908 | M92: =IF(L92=J92,"FERC Form 1","EIA-861") -> FERC Form 1 | N92: =E92+F92+G92 -> 104.90457
... A105: 2025 | B105: Monongahela Power | C105: FirstEnergy | D105: WV | E105: 88.905731 | F105: 20.05001 | G105: 63.945075 | H105: 147.15529 | I105: 2561.2779 | J105: 397332 | K105: 397362 | L105: =IF(AND(K105<>"",J105<Assumptions!$B$3*K105),K105,J105) -> 397332 | M105: =IF(L105=J105,"FERC Form 1","EIA-861") -> FERC Form 1 | N105: =E105+F105+G105 -> 172.90082
A106: 2000 | B106: Ohio Edison | C106: FirstEnergy | D106: OH | E106: 65.821602 | F106: 76.311504 | G106: 31.565034 | H106: 42.14557 | I106: 1421.1143 | J106: 993655 | L106: =IF(AND(K106<>"",J106<Assumptions!$B$3*K106),K106,J106) -> 993655 | M106: =IF(L106=J106,"FERC Form 1","EIA-861") -> FERC Form 1 | N106: =E106+F106+G106 -> 173.69814
A107: 2001 | B107: Ohio Edison | C107: FirstEnergy | D107: OH | E107: 59.986585 | F107: 28.516316 | G107: 32.443553 | H107: 36.984621 | I107: 1451.9576 | J107: 1001534 | K107: 1001534 | L107: =IF(AND(K107<>"",J107<Assumptions!$B$3*K107),K107,J107) -> 1001534 | M107: =IF(L107=J107,"FERC Form 1","EIA-861") -> FERC Form 1 | N107: =E107+F107+G107 -> 120.94645
A108: 2002 | B108: Ohio Edison | C108: FirstEnergy | D108: OH | E108: 68.793589 | F108: 28.432718 | G108: 33.325507 | H108: 46.759608 | I108: 1493.4324 | J108: 1008197 | K108: 1008277 | L108: =IF(AND(K108<>"",J108<Assumptions!$B$3*K108),K108,J108) -> 1008197 | M108: =IF(L108=J108,"FERC Form 1","EIA-861") -> FERC Form 1 | N108: =E108+F108+G108 -> 130.55181
A109: 2003 | B109: Ohio Edison | C109: FirstEnergy | D109: OH | E109: 65.774331 | F109: 37.044664 | G109: 32.847726 | H109: 74.483116 | I109: 1540.8311 | J109: 1015524 | K109: 1015524 | L109: =IF(AND(K109<>"",J109<Assumptions!$B$3*K109),K109,J109) -> 1015524 | M109: =IF(L109=J109,"FERC Form 1","EIA-861") -> FERC Form 1 | N109: =E109+F109+G109 -> 135.66672
A110: 2004 | B110: Ohio Edison | C110: FirstEnergy | D110: OH | E110: 56.634001 | F110: 28.940185 | G110: 35.823833 | H110: 57.346892 | I110: 1593.7635 | J110: 1023509 | K110: 1023509 | L110: =IF(AND(K110<>"",J110<Assumptions!$B$3*K110),K110,J110) -> 1023509 | M110: =IF(L110=J110,"FERC Form 1","EIA-861") -> FERC Form 1 | N110: =E110+F110+G110 -> 121.39802
A111: 2005 | B111: Ohio Edison | C111: FirstEnergy | D111: OH | E111: 67.644179 | F111: 43.619135 | G111: 37.642242 | H111: 85.767533 | I111: 1675.1742 | J111: 1034352 | K111: 1034352 | L111: =IF(AND(K111<>"",J111<Assumptions!$B$3*K111),K111,J111) -> 1034352 | M111: =IF(L111=J111,"FERC Form 1","EIA-861") -> FERC Form 1 | N111: =E111+F111+G111 -> 148.90556
A112: 2006 | B112: Ohio Edison | C112: FirstEnergy | D112: OH | E112: 69.919579 | F112: 50.663099 | G112: 47.360543 | H112: 87.009231 | I112: 1747.8662 | J112: 1040151 | K112: 1041985 | L112: =IF(AND(K112<>"",J112<Assumptions!$B$3*K112),K112,J112) -> 1040151 | M112: =IF(L112=J112,"FERC Form 1","EIA-861") -> FERC Form 1 | N112: =E112+F112+G112 -> 167.94322
A113: 2007 | B113: Ohio Edison | C113: FirstEnergy | D113: OH | E113: 79.267378 | F113: 53.294791 | G113: 49.126002 | H113: 81.799272 | I113: 1810.8698 | J113: 1040662 | K113: 1040662 | L113: =IF(AND(K113<>"",J113<Assumptions!$B$3*K113),K113,J113) -> 1040662 | M113: =IF(L113=J113,"FERC Form 1","EIA-861") -> FERC Form 1 | N113: =E113+F113+G113 -> 181.68817
A114: 2008 | B114: Ohio Edison | C114: FirstEnergy | D114: OH | E114: 85.367149 | F114: 44.50551 | G114: 51.374363 | H114: 102.76679 | I114: 1902.5973 | J114: 1040518 | K114: 1040518 | L114: =IF(AND(K114<>"",J114<Assumptions!$B$3*K114),K114,J114) -> 1040518 | M114: =IF(L114=J114,"FERC Form 1","EIA-861") -> FERC Form 1 | N114: =E114+F114+G114 -> 181.24702
A115: 2009 | B115: Ohio Edison | C115: FirstEnergy | D115: OH | E115: 61.648408 | F115: 42.287213 | G115: 54.384744 | H115: 102.77787 | I115: 1994.4953 | J115: 1037998 | K115: 1037998 | L115: =IF(AND(K115<>"",J115<Assumptions!$B$3*K115),K115,J115) -> 1037998 | M115: =IF(L115=J115,"FERC Form 1","EIA-861") -> FERC Form 1 | N115: =E115+F115+G115 -> 158.32037
A116: 2010 | B116: Ohio Edison | C116: FirstEnergy | D116: OH | E116: 48.693719 | F116: 30.493184 | G116: 57.091095 | H116: 104.39735 | I116: 2083.5439 | J116: 1036981 | K116: 1036981 | L116: =IF(AND(K116<>"",J116<Assumptions!$B$3*K116),K116,J116) -> 1036981 | M116: =IF(L116=J116,"FERC Form 1","EIA-861") -> FERC Form 1 | N116: =E116+F116+G116 -> 136.278
A117: 2011 | B117: Ohio Edison | C117: FirstEnergy | D117: OH | E117: 49.901851 | F117: 51.227553 | G117: 61.088546 | H117: 94.088052 | I117: 2221.9188 | J117: 1034534 | K117: 1034534 | L117: =IF(AND(K117<>"",J117<Assumptions!$B$3*K117),K117,J117) -> 1034534 | M117: =IF(L117=J117,"FERC Form 1","EIA-861") -> FERC Form 1 | N117: =E117+F117+G117 -> 162.21795
A118: 2012 | B118: Ohio Edison | C118: FirstEnergy | D118: OH | E118: 62.272178 | F118: 50.774782 | G118: 64.220297 | H118: 172.21855 | I118: 2371.2828 | J118: 1031761 | K118: 1031761 | L118: =IF(AND(K118<>"",J118<Assumptions!$B$3*K118),K118,J118) -> 1031761 | M118: =IF(L118=J118,"FERC Form 1","EIA-861") -> FERC Form 1 | N118: =E118+F118+G118 -> 177.26726
... A131: 2025 | B131: Ohio Edison | C131: FirstEnergy | D131: OH | E131: 102.65056 | F131: 47.502114 | G131: 129.09625 | H131: 224.63404 | I131: 3948.4585 | J131: 1077593 | K131: 1077592 | L131: =IF(AND(K131<>"",J131<Assumptions!$B$3*K131),K131,J131) -> 1077593 | M131: =IF(L131=J131,"FERC Form 1","EIA-861") -> FERC Form 1 | N131: =E131+F131+G131 -> 279.24893
A132: 2000 | B132: Pennsylvania Electric | C132: FirstEnergy | D132: PA | E132: 49.803059 | F132: 53.697075 | G132: 37.934021 | H132: 61.998848 | I132: 1334.7659 | J132: 579087 | L132: =IF(AND(K132<>"",J132<Assumptions!$B$3*K132),K132,J132) -> 579087 | M132: =IF(L132=J132,"FERC Form 1","EIA-861") -> FERC Form 1 | N132: =E132+F132+G132 -> 141.43416
A133: 2001 | B133: Pennsylvania Electric | C133: FirstEnergy | D133: PA | E133: 51.822678 | F133: 49.41901 | G133: 37.65054 | H133: 51.945458 | I133: 1371.2034 | J133: 580940 | K133: 580940 | L133: =IF(AND(K133<>"",J133<Assumptions!$B$3*K133),K133,J133) -> 580940 | M133: =IF(L133=J133,"FERC Form 1","EIA-861") -> FERC Form 1 | N133: =E133+F133+G133 -> 138.89223
A134: 2002 | B134: Pennsylvania Electric | C134: FirstEnergy | D134: PA | E134: 48.900268 | F134: 35.691151 | G134: 34.909007 | H134: 34.84487 | I134: 1392.5792 | J134: 583462 | K134: 583301 | L134: =IF(AND(K134<>"",J134<Assumptions!$B$3*K134),K134,J134) -> 583462 | M134: =IF(L134=J134,"FERC Form 1","EIA-861") -> FERC Form 1 | N134: =E134+F134+G134 -> 119.50043
A135: 2003 | B135: Pennsylvania Electric | C135: FirstEnergy | D135: PA | E135: 62.726865 | F135: 42.747473 | G135: 32.21792 | H135: 31.491864 | I135: 1420.6314 | J135: 584210 | K135: 584210 | L135: =IF(AND(K135<>"",J135<Assumptions!$B$3*K135),K135,J135) -> 584210 | M135: =IF(L135=J135,"FERC Form 1","EIA-861") -> FERC Form 1 | N135: =E135+F135+G135 -> 137.69226
A136: 2004 | B136: Pennsylvania Electric | C136: FirstEnergy | D136: PA | E136: 50.656719 | F136: 31.955049 | G136: 34.131462 | H136: 50.41922 | I136: 1462.8116 | J136: 585658 | K136: 585658 | L136: =IF(AND(K136<>"",J136<Assumptions!$B$3*K136),K136,J136) -> 585658 | M136: =IF(L136=J136,"FERC Form 1","EIA-861") -> FERC Form 1 | N136: =E136+F136+G136 -> 116.74323
A137: 2005 | B137: Pennsylvania Electric | C137: FirstEnergy | D137: PA | E137: 45.542067 | F137: 38.463967 | G137: 36.087676 | H137: 86.454622 | I137: 1545.9044 | J137: 587533 | K137: 587533 | L137: =IF(AND(K137<>"",J137<Assumptions!$B$3*K137),K137,J137) -> 587533 | M137: =IF(L137=J137,"FERC Form 1","EIA-861") -> FERC Form 1 | N137: =E137+F137+G137 -> 120.09371
A138: 2006 | B138: Pennsylvania Electric | C138: FirstEnergy | D138: PA | E138: 47.392626 | F138: 35.108852 | G138: 35.86157 | H138: 95.374444 | I138: 1625.9987 | J138: 588437 | K138: 589159 | L138: =IF(AND(K138<>"",J138<Assumptions!$B$3*K138),K138,J138) -> 588437 | M138: =IF(L138=J138,"FERC Form 1","EIA-861") -> FERC Form 1 | N138: =E138+F138+G138 -> 118.36305
A139: 2007 | B139: Pennsylvania Electric | C139: FirstEnergy | D139: PA | E139: 56.238848 | F139: 44.636909 | G139: 37.507732 | H139: 66.634233 | I139: 1679.233 | J139: 588871 | K139: 588871 | L139: =IF(AND(K139<>"",J139<Assumptions!$B$3*K139),K139,J139) -> 588871 | M139: =IF(L139=J139,"FERC Form 1","EIA-861") -> FERC Form 1 | N139: =E139+F139+G139 -> 138.38349
A140: 2008 | B140: Pennsylvania Electric | C140: FirstEnergy | D140: PA | E140: 52.213199 | F140: 51.775525 | G140: 38.895563 | H140: 103.21017 | I140: 1768.1683 | J140: 589017 | K140: 589017 | L140: =IF(AND(K140<>"",J140<Assumptions!$B$3*K140),K140,J140) -> 589017 | M140: =IF(L140=J140,"FERC Form 1","EIA-861") -> FERC Form 1 | N140: =E140+F140+G140 -> 142.88429
A141: 2009 | B141: Pennsylvania Electric | C141: FirstEnergy | D141: PA | E141: 41.267212 | F141: 53.499046 | G141: 39.829016 | H141: 101.04476 | I141: 1853.9703 | J141: 589201 | K141: 589201 | L141: =IF(AND(K141<>"",J141<Assumptions!$B$3*K141),K141,J141) -> 589201 | M141: =IF(L141=J141,"FERC Form 1","EIA-861") -> FERC Form 1 | N141: =E141+F141+G141 -> 134.59527
A142: 2010 | B142: Pennsylvania Electric | C142: FirstEnergy | D142: PA | E142: 32.959775 | F142: 57.830661 | G142: 42.467892 | H142: 98.107228 | I142: 1936.7809 | J142: 589852 | K142: 589852 | L142: =IF(AND(K142<>"",J142<Assumptions!$B$3*K142),K142,J142) -> 589852 | M142: =IF(L142=J142,"FERC Form 1","EIA-861") -> FERC Form 1 | N142: =E142+F142+G142 -> 133.25833
A143: 2011 | B143: Pennsylvania Electric | C143: FirstEnergy | D143: PA | E143: 35.953693 | F143: 72.623239 | G143: 50.444309 | H143: 78.314762 | I143: 2153.47 | J143: 589651 | K143: 585871 | L143: =IF(AND(K143<>"",J143<Assumptions!$B$3*K143),K143,J143) -> 589651 | M143: =IF(L143=J143,"FERC Form 1","EIA-861") -> FERC Form 1 | N143: =E143+F143+G143 -> 159.02124
A144: 2012 | B144: Pennsylvania Electric | C144: FirstEnergy | D144: PA | E144: 51.867448 | F144: 73.485887 | G144: 57.0946 | H144: 120.81836 | I144: 2261.8561 | J144: 589505 | K144: 589505 | L144: =IF(AND(K144<>"",J144<Assumptions!$B$3*K144),K144,J144) -> 589505 | M144: =IF(L144=J144,"FERC Form 1","EIA-861") -> FERC Form 1 | N144: =E144+F144+G144 -> 182.44794
... A155: 2023 | B155: Pennsylvania Electric | C155: FirstEnergy | D155: PA | E155: 92.429144 | F155: 76.286707 | G155: 74.047233 | H155: 152.02367 | I155: 3317.5853 | J155: 588213 | K155: 588212 | L155: =IF(AND(K155<>"",J155<Assumptions!$B$3*K155),K155,J155) -> 588213 | M155: =IF(L155=J155,"FERC Form 1","EIA-861") -> FERC Form 1 | N155: =E155+F155+G155 -> 242.76308
A156: 2000 | B156: Pennsylvania Power | C156: FirstEnergy | D156: PA | E156: 10.959921 | F156: 8.22639 | G156: 6.374134 | H156: 9.280058 | I156: 253.48162 | J156: 134634 | L156: =IF(AND(K156<>"",J156<Assumptions!$B$3*K156),K156,J156) -> 134634 | M156: =IF(L156=J156,"FERC Form 1","EIA-861") -> FERC Form 1 | N156: =E156+F156+G156 -> 25.560445
A157: 2001 | B157: Pennsylvania Power | C157: FirstEnergy | D157: PA | E157: 8.554656 | F157: 6.832228 | G157: 6.568438 | H157: 11.030107 | I157: 262.14701 | J157: 151266 | K157: 151267 | L157: =IF(AND(K157<>"",J157<Assumptions!$B$3*K157),K157,J157) -> 151266 | M157: =IF(L157=J157,"FERC Form 1","EIA-861") -> FERC Form 1 | N157: =E157+F157+G157 -> 21.955322
A158: 2002 | B158: Pennsylvania Power | C158: FirstEnergy | D158: PA | E158: 9.28718 | F158: 5.175261 | G158: 6.774501 | H158: 11.934342 | I158: 273.24678 | J158: 154281 | K158: 154281 | L158: =IF(AND(K158<>"",J158<Assumptions!$B$3*K158),K158,J158) -> 154281 | M158: =IF(L158=J158,"FERC Form 1","EIA-861") -> FERC Form 1 | N158: =E158+F158+G158 -> 21.236942
A159: 2003 | B159: Pennsylvania Power | C159: FirstEnergy | D159: PA | E159: 12.999695 | F159: 13.166787 | G159: 7.046611 | H159: 15.265575 | I159: 284.53321 | J159: 155446 | K159: 155446 | L159: =IF(AND(K159<>"",J159<Assumptions!$B$3*K159),K159,J159) -> 155446 | M159: =IF(L159=J159,"FERC Form 1","EIA-861") -> FERC Form 1 | N159: =E159+F159+G159 -> 33.213093
A160: 2004 | B160: Pennsylvania Power | C160: FirstEnergy | D160: PA | E160: 8.729951 | F160: 6.437959 | G160: 7.342615 | H160: 15.134883 | I160: 298.74825 | J160: 156499 | K160: 156499 | L160: =IF(AND(K160<>"",J160<Assumptions!$B$3*K160),K160,J160) -> 156499 | M160: =IF(L160=J160,"FERC Form 1","EIA-861") -> FERC Form 1 | N160: =E160+F160+G160 -> 22.510525
A161: 2005 | B161: Pennsylvania Power | C161: FirstEnergy | D161: PA | E161: 9.901775 | F161: 9.229207 | G161: 7.787741 | H161: 23.287318 | I161: 322.39857 | J161: 157660 | K161: 157660 | L161: =IF(AND(K161<>"",J161<Assumptions!$B$3*K161),K161,J161) -> 157660 | M161: =IF(L161=J161,"FERC Form 1","EIA-861") -> FERC Form 1 | N161: =E161+F161+G161 -> 26.918723
A162: 2006 | B162: Pennsylvania Power | C162: FirstEnergy | D162: PA | E162: 11.821837 | F162: 8.822817 | G162: 8.370952 | H162: 16.085515 | I162: 336.16511 | J162: 158369 | K162: 158864 | L162: =IF(AND(K162<>"",J162<Assumptions!$B$3*K162),K162,J162) -> 158369 | M162: =IF(L162=J162,"FERC Form 1","EIA-861") -> FERC Form 1 | N162: =E162+F162+G162 -> 29.015606
A163: 2007 | B163: Pennsylvania Power | C163: FirstEnergy | D163: PA | E163: 14.401114 | F163: 9.510333 | G163: 6.947685 | H163: 20.31776 | I163: 353.79915 | J163: 158987 | K163: 158987 | L163: =IF(AND(K163<>"",J163<Assumptions!$B$3*K163),K163,J163) -> 158987 | M163: =IF(L163=J163,"FERC Form 1","EIA-861") -> FERC Form 1 | N163: =E163+F163+G163 -> 30.859132
A164: 2008 | B164: Pennsylvania Power | C164: FirstEnergy | D164: PA | E164: 17.614376 | F164: 14.083897 | G164: 7.035039 | H164: 30.590305 | I164: 382.2578 | J164: 159346 | K164: 159346 | L164: =IF(AND(K164<>"",J164<Assumptions!$B$3*K164),K164,J164) -> 159346 | M164: =IF(L164=J164,"FERC Form 1","EIA-861") -> FERC Form 1 | N164: =E164+F164+G164 -> 38.733312
A165: 2009 | B165: Pennsylvania Power | C165: FirstEnergy | D165: PA | E165: 8.393165 | F165: 17.672757 | G165: 8.216305 | H165: 25.437635 | I165: 405.7395 | J165: 159558 | K165: 159558 | L165: =IF(AND(K165<>"",J165<Assumptions!$B$3*K165),K165,J165) -> 159558 | M165: =IF(L165=J165,"FERC Form 1","EIA-861") -> FERC Form 1 | N165: =E165+F165+G165 -> 34.282227
A166: 2010 | B166: Pennsylvania Power | C166: FirstEnergy | D166: PA | E166: 8.076725 | F166: 19.705197 | G166: 8.310658 | H166: 22.297959 | I166: 425.12586 | J166: 159886 | K166: 159886 | L166: =IF(AND(K166<>"",J166<Assumptions!$B$3*K166),K166,J166) -> 159886 | M166: =IF(L166=J166,"FERC Form 1","EIA-861") -> FERC Form 1 | N166: =E166+F166+G166 -> 36.09258
A167: 2011 | B167: Pennsylvania Power | C167: FirstEnergy | D167: PA | E167: 7.916894 | F167: 23.243362 | G167: 9.553776 | H167: 19.711283 | I167: 463.8917 | J167: 160250 | K167: 160250 | L167: =IF(AND(K167<>"",J167<Assumptions!$B$3*K167),K167,J167) -> 160250 | M167: =IF(L167=J167,"FERC Form 1","EIA-861") -> FERC Form 1 | N167: =E167+F167+G167 -> 40.714032
A168: 2012 | B168: Pennsylvania Power | C168: FirstEnergy | D168: PA | E168: 11.926235 | F168: 22.474686 | G168: 10.435015 | H168: 30.195916 | I168: 491.66444 | J168: 160725 | K168: 160725 | L168: =IF(AND(K168<>"",J168<Assumptions!$B$3*K168),K168,J168) -> 160725 | M168: =IF(L168=J168,"FERC Form 1","EIA-861") -> FERC Form 1 | N168: =E168+F168+G168 -> 44.835936
...
