Workbook

Sheet Notes
A1: Midwest IOU peer group: functional shares of non-generation O&M plus depreciation, 1995–2025
A2: Prepared 2026-10-25. Generation is excluded from this version. Supersedes the earlier 2026-10-25 version, which included generation, the version of 2026-10-24, which had 17 peers (no Illinois utilities), and the version of 2026-10-14, which used an earlier PUDL download (see Source and version).
A3: Measure
A4: Cost = operation and maintenance expense (FERC Form 1 pp. 320–323) plus depreciation and amortization expense (FERC Form 1 p. 336), electric utility only, nominal dollars, for transmission, distribution, regional market operation, customer accounts, service and sales, and administrative and general. Generation is excluded: O&M accounts 500–557 (including fuel and purchased power) and 577–578, and depreciation of production and energy-storage plant. Ohio and Illinois are retail-choice states in which the distribution utilities do not own generation, so the comparison is limited to the functions all peers perform.
A5: Not included: return on rate base, income and other taxes, interest.
A6: Account 565 (transmission of electricity by others) is included in Transmission.
A7: Shares are dollar-weighted: each category’s peer-group total divided by the peer-group non-generation total for the year. Utility Shares gives the same calculation for each utility.
A8: Sheets
A9: Peer Shares – aggregate shares of non-generation cost by year, with the O&M and depreciation portions of each year’s total.
A10: Utility Shares – shares of non-generation cost by utility and year.
A11: Reconciliation – line items compared with reported total O&M and total depreciation for every utility-year, with the tolerance in a labeled input cell.
A12: Transmission Transfers – transfers of peer transmission systems to transmission-only companies, with sources and the corresponding change in account 565.
... A40: Blue text: input values taken from PUDL or from the sources named on the sheet. Black text: formulas that refer only to cells on the same sheet. Green text: formulas that refer to another sheet. Yellow fill: the reconciliation tolerance, an adjustable input.

Sheet Peer Shares
A1: Peer-group aggregate shares of non-generation O&M plus depreciation
A2: Generation is excluded (O&M accounts 500–557 and 577–578, production depreciation). Dollar-weighted: each share is the category’s peer-group total divided by the peer-group non-generation total. Account 565 is included in Transmission. Source: Data sheet (PUDL v2026.10.0); see Notes.
A4: Year | B4: Utilities reporting | C4: Non-generation total ($mm) | D4: Transmission | E4: Distribution | F4: RTO/market operation | G4: Customer accounts, service & sales | H4: A&G and general | I4: Acct 565 (incl. in Transmission) | J4: Check: shares sum | K4: O&M portion of total | L4: Depreciation portion of total
A5: 1995 | B5: =COUNTIFS('Utility Shares'!$A:$A,$A5) -> 19 | C5: =SUMIFS(Data!$E$2:$E$2657,Data!$A$2:$A$2657,$A5)+SUMIFS(Data!$G$2:$G$2657,Data!$A$2:$A$2657,$A5) -> 5553.4981 | D5: =IFERROR((SUMIFS(Data!$E$2:$E$2657,Data!$A$2:$A$2657,$A5,Data!$D$2:$D$2657,"Transmission")+SUMIFS(Data!$G$2:$G$2657,Data!$A$2:$A$2657,$A5,Data!$D$2:$D$2657,"Transmission"))/$C5,0) -> 0.087193603 | E5: =IFERROR((SUMIFS(Data!$E$2:$E$2657,Data!$A$2:$A$2657,$A5,Data!$D$2:$D$2657,"Distribution")+SUMIFS(Data!$G$2:$G$2657,Data!$A$2:$A$2657,$A5,Data!$D$2:$D$2657,"Distribution"))/$C5,0) -> 0.31344485 | F5: =IFERROR((SUMIFS(Data!$E$2:$E$2657,Data!$A$2:$A$2657,$A5,Data!$D$2:$D$2657,"RTO/market operation")+SUMIFS(Data!$G$2:$G$2657,Data!$A$2:$A$2657,$A5,Data!$D$2:$D$2657,"RTO/market operation"))/$C5,0) -> 0 | G5: =IFERROR((SUMIFS(Data!$E$2:$E$2657,Data!$A$2:$A$2657,$A5,Data!$D$2:$D$2657,"Customer accounts, service & sales")+SUMIFS(Data!$G$2:$G$2657,Data!$A$2:$A$2657,$A5,Data!$D$2:$D$2657,"Customer accounts, service & sales"))/$C5,0) -> 0.15443601 | H5: =IFERROR((SUMIFS(Data!$E$2:$E$2657,Data!$A$2:$A$2657,$A5,Data!$D$2:$D$2657,"A&G and general")+SUMIFS(Data!$G$2:$G$2657,Data!$A$2:$A$2657,$A5,Data!$D$2:$D$2657,"A&G and general"))/$C5,0) -> 0.44492554 | I5: =IFERROR(SUMIFS(Data!$F$2:$F$2657,Data!$A$2:$A$2657,$A5)/$C5,0) -> -0.0062376998 | J5: =SUM(D5:H5) -> 1 | K5: =IFERROR(SUMIFS(Data!$E$2:$E$2657,Data!$A$2:$A$2657,$A5)/$C5,0) -> 0.77138146 | L5: =IFERROR(SUMIFS(Data!$G$2:$G$2657,Data!$A$2:$A$2657,$A5)/$C5,0) -> 0.22861854
A6: 1996 | B6: =COUNTIFS('Utility Shares'!$A:$A,$A6) -> 19 | C6: =SUMIFS(Data!$E$2:$E$2657,Data!$A$2:$A$2657,$A6)+SUMIFS(Data!$G$2:$G$2657,Data!$A$2:$A$2657,$A6) -> 5584.261 | D6: =IFERROR((SUMIFS(Data!$E$2:$E$2657,Data!$A$2:$A$2657,$A6,Data!$D$2:$D$2657,"Transmission")+SUMIFS(Data!$G$2:$G$2657,Data!$A$2:$A$2657,$A6,Data!$D$2:$D$2657,"Transmission"))/$C6,0) -> 0.092986737 | E6: =IFERROR((SUMIFS(Data!$E$2:$E$2657,Data!$A$2:$A$2657,$A6,Data!$D$2:$D$2657,"Distribution")+SUMIFS(Data!$G$2:$G$2657,Data!$A$2:$A$2657,$A6,Data!$D$2:$D$2657,"Distribution"))/$C6,0) -> 0.32453878 | F6: =IFERROR((SUMIFS(Data!$E$2:$E$2657,Data!$A$2:$A$2657,$A6,Data!$D$2:$D$2657,"RTO/market operation")+SUMIFS(Data!$G$2:$G$2657,Data!$A$2:$A$2657,$A6,Data!$D$2:$D$2657,"RTO/market operation"))/$C6,0) -> 0 | G6: =IFERROR((SUMIFS(Data!$E$2:$E$2657,Data!$A$2:$A$2657,$A6,Data!$D$2:$D$2657,"Customer accounts, service & sales")+SUMIFS(Data!$G$2:$G$2657,Data!$A$2:$A$2657,$A6,Data!$D$2:$D$2657,"Customer accounts, service & sales"))/$C6,0) -> 0.16947742 | H6: =IFERROR((SUMIFS(Data!$E$2:$E$2657,Data!$A$2:$A$2657,$A6,Data!$D$2:$D$2657,"A&G and general")+SUMIFS(Data!$G$2:$G$2657,Data!$A$2:$A$2657,$A6,Data!$D$2:$D$2657,"A&G and general"))/$C6,0) -> 0.41299706 | I6: =IFERROR(SUMIFS(Data!$F$2:$F$2657,Data!$A$2:$A$2657,$A6)/$C6,0) -> -0.003916465 | J6: =SUM(D6:H6) -> 1 | K6: =IFERROR(SUMIFS(Data!$E$2:$E$2657,Data!$A$2:$A$2657,$A6)/$C6,0) -> 0.75729247 | L6: =IFERROR(SUMIFS(Data!$G$2:$G$2657,Data!$A$2:$A$2657,$A6)/$C6,0) -> 0.24270753
A7: 1997 | B7: =COUNTIFS('Utility Shares'!$A:$A,$A7) -> 18 | C7: =SUMIFS(Data!$E$2:$E$2657,Data!$A$2:$A$2657,$A7)+SUMIFS(Data!$G$2:$G$2657,Data!$A$2:$A$2657,$A7) -> 4605.8205 | D7: =IFERROR((SUMIFS(Data!$E$2:$E$2657,Data!$A$2:$A$2657,$A7,Data!$D$2:$D$2657,"Transmission")+SUMIFS(Data!$G$2:$G$2657,Data!$A$2:$A$2657,$A7,Data!$D$2:$D$2657,"Transmission"))/$C7,0) -> 0.09817598 | E7: =IFERROR((SUMIFS(Data!$E$2:$E$2657,Data!$A$2:$A$2657,$A7,Data!$D$2:$D$2657,"Distribution")+SUMIFS(Data!$G$2:$G$2657,Data!$A$2:$A$2657,$A7,Data!$D$2:$D$2657,"Distribution"))/$C7,0) -> 0.3104333 | F7: =IFERROR((SUMIFS(Data!$E$2:$E$2657,Data!$A$2:$A$2657,$A7,Data!$D$2:$D$2657,"RTO/market operation")+SUMIFS(Data!$G$2:$G$2657,Data!$A$2:$A$2657,$A7,Data!$D$2:$D$2657,"RTO/market operation"))/$C7,0) -> 0 | G7: =IFERROR((SUMIFS(Data!$E$2:$E$2657,Data!$A$2:$A$2657,$A7,Data!$D$2:$D$2657,"Customer accounts, service & sales")+SUMIFS(Data!$G$2:$G$2657,Data!$A$2:$A$2657,$A7,Data!$D$2:$D$2657,"Customer accounts, service & sales"))/$C7,0) -> 0.17036429 | H7: =IFERROR((SUMIFS(Data!$E$2:$E$2657,Data!$A$2:$A$2657,$A7,Data!$D$2:$D$2657,"A&G and general")+SUMIFS(Data!$G$2:$G$2657,Data!$A$2:$A$2657,$A7,Data!$D$2:$D$2657,"A&G and general"))/$C7,0) -> 0.42102643 | I7: =IFERROR(SUMIFS(Data!$F$2:$F$2657,Data!$A$2:$A$2657,$A7)/$C7,0) -> 0.0029553381 | J7: =SUM(D7:H7) -> 1 | K7: =IFERROR(SUMIFS(Data!$E$2:$E$2657,Data!$A$2:$A$2657,$A7)/$C7,0) -> 0.7515751 | L7: =IFERROR(SUMIFS(Data!$G$2:$G$2657,Data!$A$2:$A$2657,$A7)/$C7,0) -> 0.2484249
A8: 1998 | B8: =COUNTIFS('Utility Shares'!$A:$A,$A8) -> 19 | C8: =SUMIFS(Data!$E$2:$E$2657,Data!$A$2:$A$2657,$A8)+SUMIFS(Data!$G$2:$G$2657,Data!$A$2:$A$2657,$A8) -> 6337.769 | D8: =IFERROR((SUMIFS(Data!$E$2:$E$2657,Data!$A$2:$A$2657,$A8,Data!$D$2:$D$2657,"Transmission")+SUMIFS(Data!$G$2:$G$2657,Data!$A$2:$A$2657,$A8,Data!$D$2:$D$2657,"Transmission"))/$C8,0) -> 0.093675971 | E8: =IFERROR((SUMIFS(Data!$E$2:$E$2657,Data!$A$2:$A$2657,$A8,Data!$D$2:$D$2657,"Distribution")+SUMIFS(Data!$G$2:$G$2657,Data!$A$2:$A$2657,$A8,Data!$D$2:$D$2657,"Distribution"))/$C8,0) -> 0.32231769 | F8: =IFERROR((SUMIFS(Data!$E$2:$E$2657,Data!$A$2:$A$2657,$A8,Data!$D$2:$D$2657,"RTO/market operation")+SUMIFS(Data!$G$2:$G$2657,Data!$A$2:$A$2657,$A8,Data!$D$2:$D$2657,"RTO/market operation"))/$C8,0) -> 0 | G8: =IFERROR((SUMIFS(Data!$E$2:$E$2657,Data!$A$2:$A$2657,$A8,Data!$D$2:$D$2657,"Customer accounts, service & sales")+SUMIFS(Data!$G$2:$G$2657,Data!$A$2:$A$2657,$A8,Data!$D$2:$D$2657,"Customer accounts, service & sales"))/$C8,0) -> 0.17369661 | H8: =IFERROR((SUMIFS(Data!$E$2:$E$2657,Data!$A$2:$A$2657,$A8,Data!$D$2:$D$2657,"A&G and general")+SUMIFS(Data!$G$2:$G$2657,Data!$A$2:$A$2657,$A8,Data!$D$2:$D$2657,"A&G and general"))/$C8,0) -> 0.41030973 | I8: =IFERROR(SUMIFS(Data!$F$2:$F$2657,Data!$A$2:$A$2657,$A8)/$C8,0) -> 0.006510672 | J8: =SUM(D8:H8) -> 1 | K8: =IFERROR(SUMIFS(Data!$E$2:$E$2657,Data!$A$2:$A$2657,$A8)/$C8,0) -> 0.75619811 | L8: =IFERROR(SUMIFS(Data!$G$2:$G$2657,Data!$A$2:$A$2657,$A8)/$C8,0) -> 0.24380189
A9: 1999 | B9: =COUNTIFS('Utility Shares'!$A:$A,$A9) -> 19 | C9: =SUMIFS(Data!$E$2:$E$2657,Data!$A$2:$A$2657,$A9)+SUMIFS(Data!$G$2:$G$2657,Data!$A$2:$A$2657,$A9) -> 6608.7734 | D9: =IFERROR((SUMIFS(Data!$E$2:$E$2657,Data!$A$2:$A$2657,$A9,Data!$D$2:$D$2657,"Transmission")+SUMIFS(Data!$G$2:$G$2657,Data!$A$2:$A$2657,$A9,Data!$D$2:$D$2657,"Transmission"))/$C9,0) -> 0.090250553 | E9: =IFERROR((SUMIFS(Data!$E$2:$E$2657,Data!$A$2:$A$2657,$A9,Data!$D$2:$D$2657,"Distribution")+SUMIFS(Data!$G$2:$G$2657,Data!$A$2:$A$2657,$A9,Data!$D$2:$D$2657,"Distribution"))/$C9,0) -> 0.32974931 | F9: =IFERROR((SUMIFS(Data!$E$2:$E$2657,Data!$A$2:$A$2657,$A9,Data!$D$2:$D$2657,"RTO/market operation")+SUMIFS(Data!$G$2:$G$2657,Data!$A$2:$A$2657,$A9,Data!$D$2:$D$2657,"RTO/market operation"))/$C9,0) -> 0 | G9: =IFERROR((SUMIFS(Data!$E$2:$E$2657,Data!$A$2:$A$2657,$A9,Data!$D$2:$D$2657,"Customer accounts, service & sales")+SUMIFS(Data!$G$2:$G$2657,Data!$A$2:$A$2657,$A9,Data!$D$2:$D$2657,"Customer accounts, service & sales"))/$C9,0) -> 0.17444528 | H9: =IFERROR((SUMIFS(Data!$E$2:$E$2657,Data!$A$2:$A$2657,$A9,Data!$D$2:$D$2657,"A&G and general")+SUMIFS(Data!$G$2:$G$2657,Data!$A$2:$A$2657,$A9,Data!$D$2:$D$2657,"A&G and general"))/$C9,0) -> 0.40555485 | I9: =IFERROR(SUMIFS(Data!$F$2:$F$2657,Data!$A$2:$A$2657,$A9)/$C9,0) -> 0.0034491988 | J9: =SUM(D9:H9) -> 1 | K9: =IFERROR(SUMIFS(Data!$E$2:$E$2657,Data!$A$2:$A$2657,$A9)/$C9,0) -> 0.75394548 | L9: =IFERROR(SUMIFS(Data!$G$2:$G$2657,Data!$A$2:$A$2657,$A9)/$C9,0) -> 0.24605452
A10: 2000 | B10: =COUNTIFS('Utility Shares'!$A:$A,$A10) -> 19 | C10: =SUMIFS(Data!$E$2:$E$2657,Data!$A$2:$A$2657,$A10)+SUMIFS(Data!$G$2:$G$2657,Data!$A$2:$A$2657,$A10) -> 6638.9201 | D10: =IFERROR((SUMIFS(Data!$E$2:$E$2657,Data!$A$2:$A$2657,$A10,Data!$D$2:$D$2657,"Transmission")+SUMIFS(Data!$G$2:$G$2657,Data!$A$2:$A$2657,$A10,Data!$D$2:$D$2657,"Transmission"))/$C10,0) -> 0.089766362 | E10: =IFERROR((SUMIFS(Data!$E$2:$E$2657,Data!$A$2:$A$2657,$A10,Data!$D$2:$D$2657,"Distribution")+SUMIFS(Data!$G$2:$G$2657,Data!$A$2:$A$2657,$A10,Data!$D$2:$D$2657,"Distribution"))/$C10,0) -> 0.36059848 | F10: =IFERROR((SUMIFS(Data!$E$2:$E$2657,Data!$A$2:$A$2657,$A10,Data!$D$2:$D$2657,"RTO/market operation")+SUMIFS(Data!$G$2:$G$2657,Data!$A$2:$A$2657,$A10,Data!$D$2:$D$2657,"RTO/market operation"))/$C10,0) -> 0 | G10: =IFERROR((SUMIFS(Data!$E$2:$E$2657,Data!$A$2:$A$2657,$A10,Data!$D$2:$D$2657,"Customer accounts, service & sales")+SUMIFS(Data!$G$2:$G$2657,Data!$A$2:$A$2657,$A10,Data!$D$2:$D$2657,"Customer accounts, service & sales"))/$C10,0) -> 0.15073055 | H10: =IFERROR((SUMIFS(Data!$E$2:$E$2657,Data!$A$2:$A$2657,$A10,Data!$D$2:$D$2657,"A&G and general")+SUMIFS(Data!$G$2:$G$2657,Data!$A$2:$A$2657,$A10,Data!$D$2:$D$2657,"A&G and general"))/$C10,0) -> 0.39890461 | I10: =IFERROR(SUMIFS(Data!$F$2:$F$2657,Data!$A$2:$A$2657,$A10)/$C10,0) -> 0.0059559476 | J10: =SUM(D10:H10) -> 1 | K10: =IFERROR(SUMIFS(Data!$E$2:$E$2657,Data!$A$2:$A$2657,$A10)/$C10,0) -> 0.7386369 | L10: =IFERROR(SUMIFS(Data!$G$2:$G$2657,Data!$A$2:$A$2657,$A10)/$C10,0) -> 0.2613631
A11: 2001 | B11: =COUNTIFS('Utility Shares'!$A:$A,$A11) -> 19 | C11: =SUMIFS(Data!$E$2:$E$2657,Data!$A$2:$A$2657,$A11)+SUMIFS(Data!$G$2:$G$2657,Data!$A$2:$A$2657,$A11) -> 6724.5755 | D11: =IFERROR((SUMIFS(Data!$E$2:$E$2657,Data!$A$2:$A$2657,$A11,Data!$D$2:$D$2657,"Transmission")+SUMIFS(Data!$G$2:$G$2657,Data!$A$2:$A$2657,$A11,Data!$D$2:$D$2657,"Transmission"))/$C11,0) -> 0.10953391 | E11: =IFERROR((SUMIFS(Data!$E$2:$E$2657,Data!$A$2:$A$2657,$A11,Data!$D$2:$D$2657,"Distribution")+SUMIFS(Data!$G$2:$G$2657,Data!$A$2:$A$2657,$A11,Data!$D$2:$D$2657,"Distribution"))/$C11,0) -> 0.35710191 | F11: =IFERROR((SUMIFS(Data!$E$2:$E$2657,Data!$A$2:$A$2657,$A11,Data!$D$2:$D$2657,"RTO/market operation")+SUMIFS(Data!$G$2:$G$2657,Data!$A$2:$A$2657,$A11,Data!$D$2:$D$2657,"RTO/market operation"))/$C11,0) -> 0 | G11: =IFERROR((SUMIFS(Data!$E$2:$E$2657,Data!$A$2:$A$2657,$A11,Data!$D$2:$D$2657,"Customer accounts, service & sales")+SUMIFS(Data!$G$2:$G$2657,Data!$A$2:$A$2657,$A11,Data!$D$2:$D$2657,"Customer accounts, service & sales"))/$C11,0) -> 0.14121192 | H11: =IFERROR((SUMIFS(Data!$E$2:$E$2657,Data!$A$2:$A$2657,$A11,Data!$D$2:$D$2657,"A&G and general")+SUMIFS(Data!$G$2:$G$2657,Data!$A$2:$A$2657,$A11,Data!$D$2:$D$2657,"A&G and general"))/$C11,0) -> 0.39215226 | I11: =IFERROR(SUMIFS(Data!$F$2:$F$2657,Data!$A$2:$A$2657,$A11)/$C11,0) -> 0.043097137 | J11: =SUM(D11:H11) -> 1 | K11: =IFERROR(SUMIFS(Data!$E$2:$E$2657,Data!$A$2:$A$2657,$A11)/$C11,0) -> 0.74201215 | L11: =IFERROR(SUMIFS(Data!$G$2:$G$2657,Data!$A$2:$A$2657,$A11)/$C11,0) -> 0.25798785
A12: 2002 | B12: =COUNTIFS('Utility Shares'!$A:$A,$A12) -> 18 | C12: =SUMIFS(Data!$E$2:$E$2657,Data!$A$2:$A$2657,$A12)+SUMIFS(Data!$G$2:$G$2657,Data!$A$2:$A$2657,$A12) -> 6291.066 | D12: =IFERROR((SUMIFS(Data!$E$2:$E$2657,Data!$A$2:$A$2657,$A12,Data!$D$2:$D$2657,"Transmission")+SUMIFS(Data!$G$2:$G$2657,Data!$A$2:$A$2657,$A12,Data!$D$2:$D$2657,"Transmission"))/$C12,0) -> 0.11625879 | E12: =IFERROR((SUMIFS(Data!$E$2:$E$2657,Data!$A$2:$A$2657,$A12,Data!$D$2:$D$2657,"Distribution")+SUMIFS(Data!$G$2:$G$2657,Data!$A$2:$A$2657,$A12,Data!$D$2:$D$2657,"Distribution"))/$C12,0) -> 0.34467786 | F12: =IFERROR((SUMIFS(Data!$E$2:$E$2657,Data!$A$2:$A$2657,$A12,Data!$D$2:$D$2657,"RTO/market operation")+SUMIFS(Data!$G$2:$G$2657,Data!$A$2:$A$2657,$A12,Data!$D$2:$D$2657,"RTO/market operation"))/$C12,0) -> 0 | G12: =IFERROR((SUMIFS(Data!$E$2:$E$2657,Data!$A$2:$A$2657,$A12,Data!$D$2:$D$2657,"Customer accounts, service & sales")+SUMIFS(Data!$G$2:$G$2657,Data!$A$2:$A$2657,$A12,Data!$D$2:$D$2657,"Customer accounts, service & sales"))/$C12,0) -> 0.15342232 | H12: =IFERROR((SUMIFS(Data!$E$2:$E$2657,Data!$A$2:$A$2657,$A12,Data!$D$2:$D$2657,"A&G and general")+SUMIFS(Data!$G$2:$G$2657,Data!$A$2:$A$2657,$A12,Data!$D$2:$D$2657,"A&G and general"))/$C12,0) -> 0.38564103 | I12: =IFERROR(SUMIFS(Data!$F$2:$F$2657,Data!$A$2:$A$2657,$A12)/$C12,0) -> 0.049832131 | J12: =SUM(D12:H12) -> 1 | K12: =IFERROR(SUMIFS(Data!$E$2:$E$2657,Data!$A$2:$A$2657,$A12)/$C12,0) -> 0.74270418 | L12: =IFERROR(SUMIFS(Data!$G$2:$G$2657,Data!$A$2:$A$2657,$A12)/$C12,0) -> 0.25729582
A13: 2003 | B13: =COUNTIFS('Utility Shares'!$A:$A,$A13) -> 18 | C13: =SUMIFS(Data!$E$2:$E$2657,Data!$A$2:$A$2657,$A13)+SUMIFS(Data!$G$2:$G$2657,Data!$A$2:$A$2657,$A13) -> 6769.0614 | D13: =IFERROR((SUMIFS(Data!$E$2:$E$2657,Data!$A$2:$A$2657,$A13,Data!$D$2:$D$2657,"Transmission")+SUMIFS(Data!$G$2:$G$2657,Data!$A$2:$A$2657,$A13,Data!$D$2:$D$2657,"Transmission"))/$C13,0) -> 0.11638451 | E13: =IFERROR((SUMIFS(Data!$E$2:$E$2657,Data!$A$2:$A$2657,$A13,Data!$D$2:$D$2657,"Distribution")+SUMIFS(Data!$G$2:$G$2657,Data!$A$2:$A$2657,$A13,Data!$D$2:$D$2657,"Distribution"))/$C13,0) -> 0.32444386 | F13: =IFERROR((SUMIFS(Data!$E$2:$E$2657,Data!$A$2:$A$2657,$A13,Data!$D$2:$D$2657,"RTO/market operation")+SUMIFS(Data!$G$2:$G$2657,Data!$A$2:$A$2657,$A13,Data!$D$2:$D$2657,"RTO/market operation"))/$C13,0) -> 0 | G13: =IFERROR((SUMIFS(Data!$E$2:$E$2657,Data!$A$2:$A$2657,$A13,Data!$D$2:$D$2657,"Customer accounts, service & sales")+SUMIFS(Data!$G$2:$G$2657,Data!$A$2:$A$2657,$A13,Data!$D$2:$D$2657,"Customer accounts, service & sales"))/$C13,0) -> 0.13921524 | H13: =IFERROR((SUMIFS(Data!$E$2:$E$2657,Data!$A$2:$A$2657,$A13,Data!$D$2:$D$2657,"A&G and general")+SUMIFS(Data!$G$2:$G$2657,Data!$A$2:$A$2657,$A13,Data!$D$2:$D$2657,"A&G and general"))/$C13,0) -> 0.41995639 | I13: =IFERROR(SUMIFS(Data!$F$2:$F$2657,Data!$A$2:$A$2657,$A13)/$C13,0) -> 0.055512896 | J13: =SUM(D13:H13) -> 1 | K13: =IFERROR(SUMIFS(Data!$E$2:$E$2657,Data!$A$2:$A$2657,$A13)/$C13,0) -> 0.75749784 | L13: =IFERROR(SUMIFS(Data!$G$2:$G$2657,Data!$A$2:$A$2657,$A13)/$C13,0) -> 0.24250216
A14: 2004 | B14: =COUNTIFS('Utility Shares'!$A:$A,$A14) -> 18 | C14: =SUMIFS(Data!$E$2:$E$2657,Data!$A$2:$A$2657,$A14)+SUMIFS(Data!$G$2:$G$2657,Data!$A$2:$A$2657,$A14) -> 6962.0021 | D14: =IFERROR((SUMIFS(Data!$E$2:$E$2657,Data!$A$2:$A$2657,$A14,Data!$D$2:$D$2657,"Transmission")+SUMIFS(Data!$G$2:$G$2657,Data!$A$2:$A$2657,$A14,Data!$D$2:$D$2657,"Transmission"))/$C14,0) -> 0.14113329 | E14: =IFERROR((SUMIFS(Data!$E$2:$E$2657,Data!$A$2:$A$2657,$A14,Data!$D$2:$D$2657,"Distribution")+SUMIFS(Data!$G$2:$G$2657,Data!$A$2:$A$2657,$A14,Data!$D$2:$D$2657,"Distribution"))/$C14,0) -> 0.31915068 | F14: =IFERROR((SUMIFS(Data!$E$2:$E$2657,Data!$A$2:$A$2657,$A14,Data!$D$2:$D$2657,"RTO/market operation")+SUMIFS(Data!$G$2:$G$2657,Data!$A$2:$A$2657,$A14,Data!$D$2:$D$2657,"RTO/market operation"))/$C14,0) -> 0 | G14: =IFERROR((SUMIFS(Data!$E$2:$E$2657,Data!$A$2:$A$2657,$A14,Data!$D$2:$D$2657,"Customer accounts, service & sales")+SUMIFS(Data!$G$2:$G$2657,Data!$A$2:$A$2657,$A14,Data!$D$2:$D$2657,"Customer accounts, service & sales"))/$C14,0) -> 0.13134706 | H14: =IFERROR((SUMIFS(Data!$E$2:$E$2657,Data!$A$2:$A$2657,$A14,Data!$D$2:$D$2657,"A&G and general")+SUMIFS(Data!$G$2:$G$2657,Data!$A$2:$A$2657,$A14,Data!$D$2:$D$2657,"A&G and general"))/$C14,0) -> 0.40836897 | I14: =IFERROR(SUMIFS(Data!$F$2:$F$2657,Data!$A$2:$A$2657,$A14)/$C14,0) -> 0.052785098 | J14: =SUM(D14:H14) -> 1 | K14: =IFERROR(SUMIFS(Data!$E$2:$E$2657,Data!$A$2:$A$2657,$A14)/$C14,0) -> 0.75004411 | L14: =IFERROR(SUMIFS(Data!$G$2:$G$2657,Data!$A$2:$A$2657,$A14)/$C14,0) -> 0.24995589
A15: 2005 | B15: =COUNTIFS('Utility Shares'!$A:$A,$A15) -> 19 | C15: =SUMIFS(Data!$E$2:$E$2657,Data!$A$2:$A$2657,$A15)+SUMIFS(Data!$G$2:$G$2657,Data!$A$2:$A$2657,$A15) -> 7824.2558 | D15: =IFERROR((SUMIFS(Data!$E$2:$E$2657,Data!$A$2:$A$2657,$A15,Data!$D$2:$D$2657,"Transmission")+SUMIFS(Data!$G$2:$G$2657,Data!$A$2:$A$2657,$A15,Data!$D$2:$D$2657,"Transmission"))/$C15,0) -> 0.17256808 | E15: =IFERROR((SUMIFS(Data!$E$2:$E$2657,Data!$A$2:$A$2657,$A15,Data!$D$2:$D$2657,"Distribution")+SUMIFS(Data!$G$2:$G$2657,Data!$A$2:$A$2657,$A15,Data!$D$2:$D$2657,"Distribution"))/$C15,0) -> 0.33196391 | F15: =IFERROR((SUMIFS(Data!$E$2:$E$2657,Data!$A$2:$A$2657,$A15,Data!$D$2:$D$2657,"RTO/market operation")+SUMIFS(Data!$G$2:$G$2657,Data!$A$2:$A$2657,$A15,Data!$D$2:$D$2657,"RTO/market operation"))/$C15,0) -> 0 | G15: =IFERROR((SUMIFS(Data!$E$2:$E$2657,Data!$A$2:$A$2657,$A15,Data!$D$2:$D$2657,"Customer accounts, service & sales")+SUMIFS(Data!$G$2:$G$2657,Data!$A$2:$A$2657,$A15,Data!$D$2:$D$2657,"Customer accounts, service & sales"))/$C15,0) -> 0.12827262 | H15: =IFERROR((SUMIFS(Data!$E$2:$E$2657,Data!$A$2:$A$2657,$A15,Data!$D$2:$D$2657,"A&G and general")+SUMIFS(Data!$G$2:$G$2657,Data!$A$2:$A$2657,$A15,Data!$D$2:$D$2657,"A&G and general"))/$C15,0) -> 0.36719539 | I15: =IFERROR(SUMIFS(Data!$F$2:$F$2657,Data!$A$2:$A$2657,$A15)/$C15,0) -> 0.068429875 | J15: =SUM(D15:H15) -> 1 | K15: =IFERROR(SUMIFS(Data!$E$2:$E$2657,Data!$A$2:$A$2657,$A15)/$C15,0) -> 0.75880012 | L15: =IFERROR(SUMIFS(Data!$G$2:$G$2657,Data!$A$2:$A$2657,$A15)/$C15,0) -> 0.24119988
A16: 2006 | B16: =COUNTIFS('Utility Shares'!$A:$A,$A16) -> 17 | C16: =SUMIFS(Data!$E$2:$E$2657,Data!$A$2:$A$2657,$A16)+SUMIFS(Data!$G$2:$G$2657,Data!$A$2:$A$2657,$A16) -> 8136.5722 | D16: =IFERROR((SUMIFS(Data!$E$2:$E$2657,Data!$A$2:$A$2657,$A16,Data!$D$2:$D$2657,"Transmission")+SUMIFS(Data!$G$2:$G$2657,Data!$A$2:$A$2657,$A16,Data!$D$2:$D$2657,"Transmission"))/$C16,0) -> 0.18719931 | E16: =IFERROR((SUMIFS(Data!$E$2:$E$2657,Data!$A$2:$A$2657,$A16,Data!$D$2:$D$2657,"Distribution")+SUMIFS(Data!$G$2:$G$2657,Data!$A$2:$A$2657,$A16,Data!$D$2:$D$2657,"Distribution"))/$C16,0) -> 0.30238382 | F16: =IFERROR((SUMIFS(Data!$E$2:$E$2657,Data!$A$2:$A$2657,$A16,Data!$D$2:$D$2657,"RTO/market operation")+SUMIFS(Data!$G$2:$G$2657,Data!$A$2:$A$2657,$A16,Data!$D$2:$D$2657,"RTO/market operation"))/$C16,0) -> 0.0037363274 | G16: =IFERROR((SUMIFS(Data!$E$2:$E$2657,Data!$A$2:$A$2657,$A16,Data!$D$2:$D$2657,"Customer accounts, service & sales")+SUMIFS(Data!$G$2:$G$2657,Data!$A$2:$A$2657,$A16,Data!$D$2:$D$2657,"Customer accounts, service & sales"))/$C16,0) -> 0.12527128 | H16: =IFERROR((SUMIFS(Data!$E$2:$E$2657,Data!$A$2:$A$2657,$A16,Data!$D$2:$D$2657,"A&G and general")+SUMIFS(Data!$G$2:$G$2657,Data!$A$2:$A$2657,$A16,Data!$D$2:$D$2657,"A&G and general"))/$C16,0) -> 0.38140926 | I16: =IFERROR(SUMIFS(Data!$F$2:$F$2657,Data!$A$2:$A$2657,$A16)/$C16,0) -> 0.085085051 | J16: =SUM(D16:H16) -> 1 | K16: =IFERROR(SUMIFS(Data!$E$2:$E$2657,Data!$A$2:$A$2657,$A16)/$C16,0) -> 0.72760909 | L16: =IFERROR(SUMIFS(Data!$G$2:$G$2657,Data!$A$2:$A$2657,$A16)/$C16,0) -> 0.27239091
... A35: 2025 | B35: =COUNTIFS('Utility Shares'!$A:$A,$A35) -> 19 | C35: =SUMIFS(Data!$E$2:$E$2657,Data!$A$2:$A$2657,$A35)+SUMIFS(Data!$G$2:$G$2657,Data!$A$2:$A$2657,$A35) -> 17691.271 | D35: =IFERROR((SUMIFS(Data!$E$2:$E$2657,Data!$A$2:$A$2657,$A35,Data!$D$2:$D$2657,"Transmission")+SUMIFS(Data!$G$2:$G$2657,Data!$A$2:$A$2657,$A35,Data!$D$2:$D$2657,"Transmission"))/$C35,0) -> 0.293286 | E35: =IFERROR((SUMIFS(Data!$E$2:$E$2657,Data!$A$2:$A$2657,$A35,Data!$D$2:$D$2657,"Distribution")+SUMIFS(Data!$G$2:$G$2657,Data!$A$2:$A$2657,$A35,Data!$D$2:$D$2657,"Distribution"))/$C35,0) -> 0.35107485 | F35: =IFERROR((SUMIFS(Data!$E$2:$E$2657,Data!$A$2:$A$2657,$A35,Data!$D$2:$D$2657,"RTO/market operation")+SUMIFS(Data!$G$2:$G$2657,Data!$A$2:$A$2657,$A35,Data!$D$2:$D$2657,"RTO/market operation"))/$C35,0) -> 0.0047601564 | G35: =IFERROR((SUMIFS(Data!$E$2:$E$2657,Data!$A$2:$A$2657,$A35,Data!$D$2:$D$2657,"Customer accounts, service & sales")+SUMIFS(Data!$G$2:$G$2657,Data!$A$2:$A$2657,$A35,Data!$D$2:$D$2657,"Customer accounts, service & sales"))/$C35,0) -> 0.11946787 | H35: =IFERROR((SUMIFS(Data!$E$2:$E$2657,Data!$A$2:$A$2657,$A35,Data!$D$2:$D$2657,"A&G and general")+SUMIFS(Data!$G$2:$G$2657,Data!$A$2:$A$2657,$A35,Data!$D$2:$D$2657,"A&G and general"))/$C35,0) -> 0.23141112 | I35: =IFERROR(SUMIFS(Data!$F$2:$F$2657,Data!$A$2:$A$2657,$A35)/$C35,0) -> 0.18645164 | J35: =SUM(D35:H35) -> 1 | K35: =IFERROR(SUMIFS(Data!$E$2:$E$2657,Data!$A$2:$A$2657,$A35)/$C35,0) -> 0.67575031 | L35: =IFERROR(SUMIFS(Data!$G$2:$G$2657,Data!$A$2:$A$2657,$A35)/$C35,0) -> 0.32424969

Sheet Utility Shares
A1: Year | B1: Utility | C1: State | D1: Non-generation total ($mm) | E1: Transmission | F1: Distribution | G1: RTO/market operation | H1: Customer accounts, service & sales | I1: A&G and general | J1: Acct 565 (incl. in Transmission) | K1: Check: shares sum
A2: 1995 | B2: ALLETE (Minnesota Power) | C2: MN | D2: =SUMIFS(Data!$E$2:$E$2657,Data!$A$2:$A$2657,$A2,Data!$B$2:$B$2657,$B2)+SUMIFS(Data!$G$2:$G$2657,Data!$A$2:$A$2657,$A2,Data!$B$2:$B$2657,$B2) -> 89.718785 | E2: =IFERROR((SUMIFS(Data!$E$2:$E$2657,Data!$A$2:$A$2657,$A2,Data!$B$2:$B$2657,$B2,Data!$D$2:$D$2657,"Transmission")+SUMIFS(Data!$G$2:$G$2657,Data!$A$2:$A$2657,$A2,Data!$B$2:$B$2657,$B2,Data!$D$2:$D$2657,"Transmission"))/$D2,0) -> 0.10622106 | F2: =IFERROR((SUMIFS(Data!$E$2:$E$2657,Data!$A$2:$A$2657,$A2,Data!$B$2:$B$2657,$B2,Data!$D$2:$D$2657,"Distribution")+SUMIFS(Data!$G$2:$G$2657,Data!$A$2:$A$2657,$A2,Data!$B$2:$B$2657,$B2,Data!$D$2:$D$2657,"Distribution"))/$D2,0) -> 0.240842 | G2: =IFERROR((SUMIFS(Data!$E$2:$E$2657,Data!$A$2:$A$2657,$A2,Data!$B$2:$B$2657,$B2,Data!$D$2:$D$2657,"RTO/market operation")+SUMIFS(Data!$G$2:$G$2657,Data!$A$2:$A$2657,$A2,Data!$B$2:$B$2657,$B2,Data!$D$2:$D$2657,"RTO/market operation"))/$D2,0) -> 0 | H2: =IFERROR((SUMIFS(Data!$E$2:$E$2657,Data!$A$2:$A$2657,$A2,Data!$B$2:$B$2657,$B2,Data!$D$2:$D$2657,"Customer accounts, service & sales")+SUMIFS(Data!$G$2:$G$2657,Data!$A$2:$A$2657,$A2,Data!$B$2:$B$2657,$B2,Data!$D$2:$D$2657,"Customer accounts, service & sales"))/$D2,0) -> 0.23002834 | I2: =IFERROR((SUMIFS(Data!$E$2:$E$2657,Data!$A$2:$A$2657,$A2,Data!$B$2:$B$2657,$B2,Data!$D$2:$D$2657,"A&G and general")+SUMIFS(Data!$G$2:$G$2657,Data!$A$2:$A$2657,$A2,Data!$B$2:$B$2657,$B2,Data!$D$2:$D$2657,"A&G and general"))/$D2,0) -> 0.4229086 | J2: =IFERROR(SUMIFS(Data!$F$2:$F$2657,Data!$A$2:$A$2657,$A2,Data!$B$2:$B$2657,$B2)/$D2,0) -> 0.002714582 | K2: =SUM(E2:I2) -> 1
A3: 1995 | B3: Ameren Illinois | C3: IL | D3: =SUMIFS(Data!$E$2:$E$2657,Data!$A$2:$A$2657,$A3,Data!$B$2:$B$2657,$B3)+SUMIFS(Data!$G$2:$G$2657,Data!$A$2:$A$2657,$A3,Data!$B$2:$B$2657,$B3) -> 466.97125 | E3: =IFERROR((SUMIFS(Data!$E$2:$E$2657,Data!$A$2:$A$2657,$A3,Data!$B$2:$B$2657,$B3,Data!$D$2:$D$2657,"Transmission")+SUMIFS(Data!$G$2:$G$2657,Data!$A$2:$A$2657,$A3,Data!$B$2:$B$2657,$B3,Data!$D$2:$D$2657,"Transmission"))/$D3,0) -> 0.07482709 | F3: =IFERROR((SUMIFS(Data!$E$2:$E$2657,Data!$A$2:$A$2657,$A3,Data!$B$2:$B$2657,$B3,Data!$D$2:$D$2657,"Distribution")+SUMIFS(Data!$G$2:$G$2657,Data!$A$2:$A$2657,$A3,Data!$B$2:$B$2657,$B3,Data!$D$2:$D$2657,"Distribution"))/$D3,0) -> 0.3033503 | G3: =IFERROR((SUMIFS(Data!$E$2:$E$2657,Data!$A$2:$A$2657,$A3,Data!$B$2:$B$2657,$B3,Data!$D$2:$D$2657,"RTO/market operation")+SUMIFS(Data!$G$2:$G$2657,Data!$A$2:$A$2657,$A3,Data!$B$2:$B$2657,$B3,Data!$D$2:$D$2657,"RTO/market operation"))/$D3,0) -> 0 | H3: =IFERROR((SUMIFS(Data!$E$2:$E$2657,Data!$A$2:$A$2657,$A3,Data!$B$2:$B$2657,$B3,Data!$D$2:$D$2657,"Customer accounts, service & sales")+SUMIFS(Data!$G$2:$G$2657,Data!$A$2:$A$2657,$A3,Data!$B$2:$B$2657,$B3,Data!$D$2:$D$2657,"Customer accounts, service & sales"))/$D3,0) -> 0.10321936 | I3: =IFERROR((SUMIFS(Data!$E$2:$E$2657,Data!$A$2:$A$2657,$A3,Data!$B$2:$B$2657,$B3,Data!$D$2:$D$2657,"A&G and general")+SUMIFS(Data!$G$2:$G$2657,Data!$A$2:$A$2657,$A3,Data!$B$2:$B$2657,$B3,Data!$D$2:$D$2657,"A&G and general"))/$D3,0) -> 0.51860324 | J3: =IFERROR(SUMIFS(Data!$F$2:$F$2657,Data!$A$2:$A$2657,$A3,Data!$B$2:$B$2657,$B3)/$D3,0) -> 1.5778273e-05 | K3: =SUM(E3:I3) -> 1
A4: 1995 | B4: Commonwealth Edison (ComEd) | C4: IL | D4: =SUMIFS(Data!$E$2:$E$2657,Data!$A$2:$A$2657,$A4,Data!$B$2:$B$2657,$B4)+SUMIFS(Data!$G$2:$G$2657,Data!$A$2:$A$2657,$A4,Data!$B$2:$B$2657,$B4) -> 1233.2446 | E4: =IFERROR((SUMIFS(Data!$E$2:$E$2657,Data!$A$2:$A$2657,$A4,Data!$B$2:$B$2657,$B4,Data!$D$2:$D$2657,"Transmission")+SUMIFS(Data!$G$2:$G$2657,Data!$A$2:$A$2657,$A4,Data!$B$2:$B$2657,$B4,Data!$D$2:$D$2657,"Transmission"))/$D4,0) -> 0.080642753 | F4: =IFERROR((SUMIFS(Data!$E$2:$E$2657,Data!$A$2:$A$2657,$A4,Data!$B$2:$B$2657,$B4,Data!$D$2:$D$2657,"Distribution")+SUMIFS(Data!$G$2:$G$2657,Data!$A$2:$A$2657,$A4,Data!$B$2:$B$2657,$B4,Data!$D$2:$D$2657,"Distribution"))/$D4,0) -> 0.30475218 | G4: =IFERROR((SUMIFS(Data!$E$2:$E$2657,Data!$A$2:$A$2657,$A4,Data!$B$2:$B$2657,$B4,Data!$D$2:$D$2657,"RTO/market operation")+SUMIFS(Data!$G$2:$G$2657,Data!$A$2:$A$2657,$A4,Data!$B$2:$B$2657,$B4,Data!$D$2:$D$2657,"RTO/market operation"))/$D4,0) -> 0 | H4: =IFERROR((SUMIFS(Data!$E$2:$E$2657,Data!$A$2:$A$2657,$A4,Data!$B$2:$B$2657,$B4,Data!$D$2:$D$2657,"Customer accounts, service & sales")+SUMIFS(Data!$G$2:$G$2657,Data!$A$2:$A$2657,$A4,Data!$B$2:$B$2657,$B4,Data!$D$2:$D$2657,"Customer accounts, service & sales"))/$D4,0) -> 0.13621169 | I4: =IFERROR((SUMIFS(Data!$E$2:$E$2657,Data!$A$2:$A$2657,$A4,Data!$B$2:$B$2657,$B4,Data!$D$2:$D$2657,"A&G and general")+SUMIFS(Data!$G$2:$G$2657,Data!$A$2:$A$2657,$A4,Data!$B$2:$B$2657,$B4,Data!$D$2:$D$2657,"A&G and general"))/$D4,0) -> 0.47839338 | J4: =IFERROR(SUMIFS(Data!$F$2:$F$2657,Data!$A$2:$A$2657,$A4,Data!$B$2:$B$2657,$B4)/$D4,0) -> 0.00018009728 | K4: =SUM(E4:I4) -> 1
A5: 1995 | B5: Consumers Energy | C5: MI | D5: =SUMIFS(Data!$E$2:$E$2657,Data!$A$2:$A$2657,$A5,Data!$B$2:$B$2657,$B5)+SUMIFS(Data!$G$2:$G$2657,Data!$A$2:$A$2657,$A5,Data!$B$2:$B$2657,$B5) -> 447.91099 | E5: =IFERROR((SUMIFS(Data!$E$2:$E$2657,Data!$A$2:$A$2657,$A5,Data!$B$2:$B$2657,$B5,Data!$D$2:$D$2657,"Transmission")+SUMIFS(Data!$G$2:$G$2657,Data!$A$2:$A$2657,$A5,Data!$B$2:$B$2657,$B5,Data!$D$2:$D$2657,"Transmission"))/$D5,0) -> 0.086435158 | F5: =IFERROR((SUMIFS(Data!$E$2:$E$2657,Data!$A$2:$A$2657,$A5,Data!$B$2:$B$2657,$B5,Data!$D$2:$D$2657,"Distribution")+SUMIFS(Data!$G$2:$G$2657,Data!$A$2:$A$2657,$A5,Data!$B$2:$B$2657,$B5,Data!$D$2:$D$2657,"Distribution"))/$D5,0) -> 0.38311152 | G5: =IFERROR((SUMIFS(Data!$E$2:$E$2657,Data!$A$2:$A$2657,$A5,Data!$B$2:$B$2657,$B5,Data!$D$2:$D$2657,"RTO/market operation")+SUMIFS(Data!$G$2:$G$2657,Data!$A$2:$A$2657,$A5,Data!$B$2:$B$2657,$B5,Data!$D$2:$D$2657,"RTO/market operation"))/$D5,0) -> 0 | H5: =IFERROR((SUMIFS(Data!$E$2:$E$2657,Data!$A$2:$A$2657,$A5,Data!$B$2:$B$2657,$B5,Data!$D$2:$D$2657,"Customer accounts, service & sales")+SUMIFS(Data!$G$2:$G$2657,Data!$A$2:$A$2657,$A5,Data!$B$2:$B$2657,$B5,Data!$D$2:$D$2657,"Customer accounts, service & sales"))/$D5,0) -> 0.17217348 | I5: =IFERROR((SUMIFS(Data!$E$2:$E$2657,Data!$A$2:$A$2657,$A5,Data!$B$2:$B$2657,$B5,Data!$D$2:$D$2657,"A&G and general")+SUMIFS(Data!$G$2:$G$2657,Data!$A$2:$A$2657,$A5,Data!$B$2:$B$2657,$B5,Data!$D$2:$D$2657,"A&G and general"))/$D5,0) -> 0.35827985 | J5: =IFERROR(SUMIFS(Data!$F$2:$F$2657,Data!$A$2:$A$2657,$A5,Data!$B$2:$B$2657,$B5)/$D5,0) -> 0 | K5: =SUM(E5:I5) -> 1
A6: 1995 | B6: DTE Electric | C6: MI | D6: =SUMIFS(Data!$E$2:$E$2657,Data!$A$2:$A$2657,$A6,Data!$B$2:$B$2657,$B6)+SUMIFS(Data!$G$2:$G$2657,Data!$A$2:$A$2657,$A6,Data!$B$2:$B$2657,$B6) -> 756.03948 | E6: =IFERROR((SUMIFS(Data!$E$2:$E$2657,Data!$A$2:$A$2657,$A6,Data!$B$2:$B$2657,$B6,Data!$D$2:$D$2657,"Transmission")+SUMIFS(Data!$G$2:$G$2657,Data!$A$2:$A$2657,$A6,Data!$B$2:$B$2657,$B6,Data!$D$2:$D$2657,"Transmission"))/$D6,0) -> 0.080249751 | F6: =IFERROR((SUMIFS(Data!$E$2:$E$2657,Data!$A$2:$A$2657,$A6,Data!$B$2:$B$2657,$B6,Data!$D$2:$D$2657,"Distribution")+SUMIFS(Data!$G$2:$G$2657,Data!$A$2:$A$2657,$A6,Data!$B$2:$B$2657,$B6,Data!$D$2:$D$2657,"Distribution"))/$D6,0) -> 0.3322246 | G6: =IFERROR((SUMIFS(Data!$E$2:$E$2657,Data!$A$2:$A$2657,$A6,Data!$B$2:$B$2657,$B6,Data!$D$2:$D$2657,"RTO/market operation")+SUMIFS(Data!$G$2:$G$2657,Data!$A$2:$A$2657,$A6,Data!$B$2:$B$2657,$B6,Data!$D$2:$D$2657,"RTO/market operation"))/$D6,0) -> 0 | H6: =IFERROR((SUMIFS(Data!$E$2:$E$2657,Data!$A$2:$A$2657,$A6,Data!$B$2:$B$2657,$B6,Data!$D$2:$D$2657,"Customer accounts, service & sales")+SUMIFS(Data!$G$2:$G$2657,Data!$A$2:$A$2657,$A6,Data!$B$2:$B$2657,$B6,Data!$D$2:$D$2657,"Customer accounts, service & sales"))/$D6,0) -> 0.11424144 | I6: =IFERROR((SUMIFS(Data!$E$2:$E$2657,Data!$A$2:$A$2657,$A6,Data!$B$2:$B$2657,$B6,Data!$D$2:$D$2657,"A&G and general")+SUMIFS(Data!$G$2:$G$2657,Data!$A$2:$A$2657,$A6,Data!$B$2:$B$2657,$B6,Data!$D$2:$D$2657,"A&G and general"))/$D6,0) -> 0.47328421 | J6: =IFERROR(SUMIFS(Data!$F$2:$F$2657,Data!$A$2:$A$2657,$A6,Data!$B$2:$B$2657,$B6)/$D6,0) -> -1.9073078e-06 | K6: =SUM(E6:I6) -> 1
A7: 1995 | B7: Duke Energy Indiana | C7: IN | D7: =SUMIFS(Data!$E$2:$E$2657,Data!$A$2:$A$2657,$A7,Data!$B$2:$B$2657,$B7)+SUMIFS(Data!$G$2:$G$2657,Data!$A$2:$A$2657,$A7,Data!$B$2:$B$2657,$B7) -> 281.87085 | E7: =IFERROR((SUMIFS(Data!$E$2:$E$2657,Data!$A$2:$A$2657,$A7,Data!$B$2:$B$2657,$B7,Data!$D$2:$D$2657,"Transmission")+SUMIFS(Data!$G$2:$G$2657,Data!$A$2:$A$2657,$A7,Data!$B$2:$B$2657,$B7,Data!$D$2:$D$2657,"Transmission"))/$D7,0) -> 0.084719204 | F7: =IFERROR((SUMIFS(Data!$E$2:$E$2657,Data!$A$2:$A$2657,$A7,Data!$B$2:$B$2657,$B7,Data!$D$2:$D$2657,"Distribution")+SUMIFS(Data!$G$2:$G$2657,Data!$A$2:$A$2657,$A7,Data!$B$2:$B$2657,$B7,Data!$D$2:$D$2657,"Distribution"))/$D7,0) -> 0.25887843 | G7: =IFERROR((SUMIFS(Data!$E$2:$E$2657,Data!$A$2:$A$2657,$A7,Data!$B$2:$B$2657,$B7,Data!$D$2:$D$2657,"RTO/market operation")+SUMIFS(Data!$G$2:$G$2657,Data!$A$2:$A$2657,$A7,Data!$B$2:$B$2657,$B7,Data!$D$2:$D$2657,"RTO/market operation"))/$D7,0) -> 0 | H7: =IFERROR((SUMIFS(Data!$E$2:$E$2657,Data!$A$2:$A$2657,$A7,Data!$B$2:$B$2657,$B7,Data!$D$2:$D$2657,"Customer accounts, service & sales")+SUMIFS(Data!$G$2:$G$2657,Data!$A$2:$A$2657,$A7,Data!$B$2:$B$2657,$B7,Data!$D$2:$D$2657,"Customer accounts, service & sales"))/$D7,0) -> 0.18168259 | I7: =IFERROR((SUMIFS(Data!$E$2:$E$2657,Data!$A$2:$A$2657,$A7,Data!$B$2:$B$2657,$B7,Data!$D$2:$D$2657,"A&G and general")+SUMIFS(Data!$G$2:$G$2657,Data!$A$2:$A$2657,$A7,Data!$B$2:$B$2657,$B7,Data!$D$2:$D$2657,"A&G and general"))/$D7,0) -> 0.47471977 | J7: =IFERROR(SUMIFS(Data!$F$2:$F$2657,Data!$A$2:$A$2657,$A7,Data!$B$2:$B$2657,$B7)/$D7,0) -> 0.0015607893 | K7: =SUM(E7:I7) -> 1
A8: 1995 | B8: Indiana Michigan Power | C8: IN/MI | D8: =SUMIFS(Data!$E$2:$E$2657,Data!$A$2:$A$2657,$A8,Data!$B$2:$B$2657,$B8)+SUMIFS(Data!$G$2:$G$2657,Data!$A$2:$A$2657,$A8,Data!$B$2:$B$2657,$B8) -> 182.46151 | E8: =IFERROR((SUMIFS(Data!$E$2:$E$2657,Data!$A$2:$A$2657,$A8,Data!$B$2:$B$2657,$B8,Data!$D$2:$D$2657,"Transmission")+SUMIFS(Data!$G$2:$G$2657,Data!$A$2:$A$2657,$A8,Data!$B$2:$B$2657,$B8,Data!$D$2:$D$2657,"Transmission"))/$D8,0) -> -0.060894519 | F8: =IFERROR((SUMIFS(Data!$E$2:$E$2657,Data!$A$2:$A$2657,$A8,Data!$B$2:$B$2657,$B8,Data!$D$2:$D$2657,"Distribution")+SUMIFS(Data!$G$2:$G$2657,Data!$A$2:$A$2657,$A8,Data!$B$2:$B$2657,$B8,Data!$D$2:$D$2657,"Distribution"))/$D8,0) -> 0.37053425 | G8: =IFERROR((SUMIFS(Data!$E$2:$E$2657,Data!$A$2:$A$2657,$A8,Data!$B$2:$B$2657,$B8,Data!$D$2:$D$2657,"RTO/market operation")+SUMIFS(Data!$G$2:$G$2657,Data!$A$2:$A$2657,$A8,Data!$B$2:$B$2657,$B8,Data!$D$2:$D$2657,"RTO/market operation"))/$D8,0) -> 0 | H8: =IFERROR((SUMIFS(Data!$E$2:$E$2657,Data!$A$2:$A$2657,$A8,Data!$B$2:$B$2657,$B8,Data!$D$2:$D$2657,"Customer accounts, service & sales")+SUMIFS(Data!$G$2:$G$2657,Data!$A$2:$A$2657,$A8,Data!$B$2:$B$2657,$B8,Data!$D$2:$D$2657,"Customer accounts, service & sales"))/$D8,0) -> 0.14620455 | I8: =IFERROR((SUMIFS(Data!$E$2:$E$2657,Data!$A$2:$A$2657,$A8,Data!$B$2:$B$2657,$B8,Data!$D$2:$D$2657,"A&G and general")+SUMIFS(Data!$G$2:$G$2657,Data!$A$2:$A$2657,$A8,Data!$B$2:$B$2657,$B8,Data!$D$2:$D$2657,"A&G and general"))/$D8,0) -> 0.54415572 | J8: =IFERROR(SUMIFS(Data!$F$2:$F$2657,Data!$A$2:$A$2657,$A8,Data!$B$2:$B$2657,$B8)/$D8,0) -> -0.25577277 | K8: =SUM(E8:I8) -> 1
A9: 1995 | B9: Indianapolis Power & Light (AES Indiana) | C9: IN | D9: =SUMIFS(Data!$E$2:$E$2657,Data!$A$2:$A$2657,$A9,Data!$B$2:$B$2657,$B9)+SUMIFS(Data!$G$2:$G$2657,Data!$A$2:$A$2657,$A9,Data!$B$2:$B$2657,$B9) -> 152.43452 | E9: =IFERROR((SUMIFS(Data!$E$2:$E$2657,Data!$A$2:$A$2657,$A9,Data!$B$2:$B$2657,$B9,Data!$D$2:$D$2657,"Transmission")+SUMIFS(Data!$G$2:$G$2657,Data!$A$2:$A$2657,$A9,Data!$B$2:$B$2657,$B9,Data!$D$2:$D$2657,"Transmission"))/$D9,0) -> 0.074071319 | F9: =IFERROR((SUMIFS(Data!$E$2:$E$2657,Data!$A$2:$A$2657,$A9,Data!$B$2:$B$2657,$B9,Data!$D$2:$D$2657,"Distribution")+SUMIFS(Data!$G$2:$G$2657,Data!$A$2:$A$2657,$A9,Data!$B$2:$B$2657,$B9,Data!$D$2:$D$2657,"Distribution"))/$D9,0) -> 0.38204587 | G9: =IFERROR((SUMIFS(Data!$E$2:$E$2657,Data!$A$2:$A$2657,$A9,Data!$B$2:$B$2657,$B9,Data!$D$2:$D$2657,"RTO/market operation")+SUMIFS(Data!$G$2:$G$2657,Data!$A$2:$A$2657,$A9,Data!$B$2:$B$2657,$B9,Data!$D$2:$D$2657,"RTO/market operation"))/$D9,0) -> 0 | H9: =IFERROR((SUMIFS(Data!$E$2:$E$2657,Data!$A$2:$A$2657,$A9,Data!$B$2:$B$2657,$B9,Data!$D$2:$D$2657,"Customer accounts, service & sales")+SUMIFS(Data!$G$2:$G$2657,Data!$A$2:$A$2657,$A9,Data!$B$2:$B$2657,$B9,Data!$D$2:$D$2657,"Customer accounts, service & sales"))/$D9,0) -> 0.11678813 | I9: =IFERROR((SUMIFS(Data!$E$2:$E$2657,Data!$A$2:$A$2657,$A9,Data!$B$2:$B$2657,$B9,Data!$D$2:$D$2657,"A&G and general")+SUMIFS(Data!$G$2:$G$2657,Data!$A$2:$A$2657,$A9,Data!$B$2:$B$2657,$B9,Data!$D$2:$D$2657,"A&G and general"))/$D9,0) -> 0.42709468 | J9: =IFERROR(SUMIFS(Data!$F$2:$F$2657,Data!$A$2:$A$2657,$A9,Data!$B$2:$B$2657,$B9)/$D9,0) -> 0 | K9: =SUM(E9:I9) -> 1
A10: 1995 | B10: Interstate Power & Light | C10: IA | D10: =SUMIFS(Data!$E$2:$E$2657,Data!$A$2:$A$2657,$A10,Data!$B$2:$B$2657,$B10)+SUMIFS(Data!$G$2:$G$2657,Data!$A$2:$A$2657,$A10,Data!$B$2:$B$2657,$B10) -> 180.85664 | E10: =IFERROR((SUMIFS(Data!$E$2:$E$2657,Data!$A$2:$A$2657,$A10,Data!$B$2:$B$2657,$B10,Data!$D$2:$D$2657,"Transmission")+SUMIFS(Data!$G$2:$G$2657,Data!$A$2:$A$2657,$A10,Data!$B$2:$B$2657,$B10,Data!$D$2:$D$2657,"Transmission"))/$D10,0) -> 0.1310422 | F10: =IFERROR((SUMIFS(Data!$E$2:$E$2657,Data!$A$2:$A$2657,$A10,Data!$B$2:$B$2657,$B10,Data!$D$2:$D$2657,"Distribution")+SUMIFS(Data!$G$2:$G$2657,Data!$A$2:$A$2657,$A10,Data!$B$2:$B$2657,$B10,Data!$D$2:$D$2657,"Distribution"))/$D10,0) -> 0.32780673 | G10: =IFERROR((SUMIFS(Data!$E$2:$E$2657,Data!$A$2:$A$2657,$A10,Data!$B$2:$B$2657,$B10,Data!$D$2:$D$2657,"RTO/market operation")+SUMIFS(Data!$G$2:$G$2657,Data!$A$2:$A$2657,$A10,Data!$B$2:$B$2657,$B10,Data!$D$2:$D$2657,"RTO/market operation"))/$D10,0) -> 0 | H10: =IFERROR((SUMIFS(Data!$E$2:$E$2657,Data!$A$2:$A$2657,$A10,Data!$B$2:$B$2657,$B10,Data!$D$2:$D$2657,"Customer accounts, service & sales")+SUMIFS(Data!$G$2:$G$2657,Data!$A$2:$A$2657,$A10,Data!$B$2:$B$2657,$B10,Data!$D$2:$D$2657,"Customer accounts, service & sales"))/$D10,0) -> 0.094287777 | I10: =IFERROR((SUMIFS(Data!$E$2:$E$2657,Data!$A$2:$A$2657,$A10,Data!$B$2:$B$2657,$B10,Data!$D$2:$D$2657,"A&G and general")+SUMIFS(Data!$G$2:$G$2657,Data!$A$2:$A$2657,$A10,Data!$B$2:$B$2657,$B10,Data!$D$2:$D$2657,"A&G and general"))/$D10,0) -> 0.4468633 | J10: =IFERROR(SUMIFS(Data!$F$2:$F$2657,Data!$A$2:$A$2657,$A10,Data!$B$2:$B$2657,$B10)/$D10,0) -> 0.0225484 | K10: =SUM(E10:I10) -> 1
A11: 1995 | B11: Madison Gas & Electric | C11: WI | D11: =SUMIFS(Data!$E$2:$E$2657,Data!$A$2:$A$2657,$A11,Data!$B$2:$B$2657,$B11)+SUMIFS(Data!$G$2:$G$2657,Data!$A$2:$A$2657,$A11,Data!$B$2:$B$2657,$B11) -> 42.807555 | E11: =IFERROR((SUMIFS(Data!$E$2:$E$2657,Data!$A$2:$A$2657,$A11,Data!$B$2:$B$2657,$B11,Data!$D$2:$D$2657,"Transmission")+SUMIFS(Data!$G$2:$G$2657,Data!$A$2:$A$2657,$A11,Data!$B$2:$B$2657,$B11,Data!$D$2:$D$2657,"Transmission"))/$D11,0) -> 0.10310792 | F11: =IFERROR((SUMIFS(Data!$E$2:$E$2657,Data!$A$2:$A$2657,$A11,Data!$B$2:$B$2657,$B11,Data!$D$2:$D$2657,"Distribution")+SUMIFS(Data!$G$2:$G$2657,Data!$A$2:$A$2657,$A11,Data!$B$2:$B$2657,$B11,Data!$D$2:$D$2657,"Distribution"))/$D11,0) -> 0.26162826 | G11: =IFERROR((SUMIFS(Data!$E$2:$E$2657,Data!$A$2:$A$2657,$A11,Data!$B$2:$B$2657,$B11,Data!$D$2:$D$2657,"RTO/market operation")+SUMIFS(Data!$G$2:$G$2657,Data!$A$2:$A$2657,$A11,Data!$B$2:$B$2657,$B11,Data!$D$2:$D$2657,"RTO/market operation"))/$D11,0) -> 0 | H11: =IFERROR((SUMIFS(Data!$E$2:$E$2657,Data!$A$2:$A$2657,$A11,Data!$B$2:$B$2657,$B11,Data!$D$2:$D$2657,"Customer accounts, service & sales")+SUMIFS(Data!$G$2:$G$2657,Data!$A$2:$A$2657,$A11,Data!$B$2:$B$2657,$B11,Data!$D$2:$D$2657,"Customer accounts, service & sales"))/$D11,0) -> 0.20657305 | I11: =IFERROR((SUMIFS(Data!$E$2:$E$2657,Data!$A$2:$A$2657,$A11,Data!$B$2:$B$2657,$B11,Data!$D$2:$D$2657,"A&G and general")+SUMIFS(Data!$G$2:$G$2657,Data!$A$2:$A$2657,$A11,Data!$B$2:$B$2657,$B11,Data!$D$2:$D$2657,"A&G and general"))/$D11,0) -> 0.42869078 | J11: =IFERROR(SUMIFS(Data!$F$2:$F$2657,Data!$A$2:$A$2657,$A11,Data!$B$2:$B$2657,$B11)/$D11,0) -> 0.0054208188 | K11: =SUM(E11:I11) -> 1
A12: 1995 | B12: MidAmerican Energy | C12: IA | D12: =SUMIFS(Data!$E$2:$E$2657,Data!$A$2:$A$2657,$A12,Data!$B$2:$B$2657,$B12)+SUMIFS(Data!$G$2:$G$2657,Data!$A$2:$A$2657,$A12,Data!$B$2:$B$2657,$B12) -> 261.5407 | E12: =IFERROR((SUMIFS(Data!$E$2:$E$2657,Data!$A$2:$A$2657,$A12,Data!$B$2:$B$2657,$B12,Data!$D$2:$D$2657,"Transmission")+SUMIFS(Data!$G$2:$G$2657,Data!$A$2:$A$2657,$A12,Data!$B$2:$B$2657,$B12,Data!$D$2:$D$2657,"Transmission"))/$D12,0) -> 0.084450248 | F12: =IFERROR((SUMIFS(Data!$E$2:$E$2657,Data!$A$2:$A$2657,$A12,Data!$B$2:$B$2657,$B12,Data!$D$2:$D$2657,"Distribution")+SUMIFS(Data!$G$2:$G$2657,Data!$A$2:$A$2657,$A12,Data!$B$2:$B$2657,$B12,Data!$D$2:$D$2657,"Distribution"))/$D12,0) -> 0.30172791 | G12: =IFERROR((SUMIFS(Data!$E$2:$E$2657,Data!$A$2:$A$2657,$A12,Data!$B$2:$B$2657,$B12,Data!$D$2:$D$2657,"RTO/market operation")+SUMIFS(Data!$G$2:$G$2657,Data!$A$2:$A$2657,$A12,Data!$B$2:$B$2657,$B12,Data!$D$2:$D$2657,"RTO/market operation"))/$D12,0) -> 0 | H12: =IFERROR((SUMIFS(Data!$E$2:$E$2657,Data!$A$2:$A$2657,$A12,Data!$B$2:$B$2657,$B12,Data!$D$2:$D$2657,"Customer accounts, service & sales")+SUMIFS(Data!$G$2:$G$2657,Data!$A$2:$A$2657,$A12,Data!$B$2:$B$2657,$B12,Data!$D$2:$D$2657,"Customer accounts, service & sales"))/$D12,0) -> 0.12861103 | I12: =IFERROR((SUMIFS(Data!$E$2:$E$2657,Data!$A$2:$A$2657,$A12,Data!$B$2:$B$2657,$B12,Data!$D$2:$D$2657,"A&G and general")+SUMIFS(Data!$G$2:$G$2657,Data!$A$2:$A$2657,$A12,Data!$B$2:$B$2657,$B12,Data!$D$2:$D$2657,"A&G and general"))/$D12,0) -> 0.48521082 | J12: =IFERROR(SUMIFS(Data!$F$2:$F$2657,Data!$A$2:$A$2657,$A12,Data!$B$2:$B$2657,$B12)/$D12,0) -> 0.0018981061 | K12: =SUM(E12:I12) -> 1
A13: 1995 | B13: NIPSCO | C13: IN | D13: =SUMIFS(Data!$E$2:$E$2657,Data!$A$2:$A$2657,$A13,Data!$B$2:$B$2657,$B13)+SUMIFS(Data!$G$2:$G$2657,Data!$A$2:$A$2657,$A13,Data!$B$2:$B$2657,$B13) -> 197.6338 | E13: =IFERROR((SUMIFS(Data!$E$2:$E$2657,Data!$A$2:$A$2657,$A13,Data!$B$2:$B$2657,$B13,Data!$D$2:$D$2657,"Transmission")+SUMIFS(Data!$G$2:$G$2657,Data!$A$2:$A$2657,$A13,Data!$B$2:$B$2657,$B13,Data!$D$2:$D$2657,"Transmission"))/$D13,0) -> 0.13937136 | F13: =IFERROR((SUMIFS(Data!$E$2:$E$2657,Data!$A$2:$A$2657,$A13,Data!$B$2:$B$2657,$B13,Data!$D$2:$D$2657,"Distribution")+SUMIFS(Data!$G$2:$G$2657,Data!$A$2:$A$2657,$A13,Data!$B$2:$B$2657,$B13,Data!$D$2:$D$2657,"Distribution"))/$D13,0) -> 0.27589843 | G13: =IFERROR((SUMIFS(Data!$E$2:$E$2657,Data!$A$2:$A$2657,$A13,Data!$B$2:$B$2657,$B13,Data!$D$2:$D$2657,"RTO/market operation")+SUMIFS(Data!$G$2:$G$2657,Data!$A$2:$A$2657,$A13,Data!$B$2:$B$2657,$B13,Data!$D$2:$D$2657,"RTO/market operation"))/$D13,0) -> 0 | H13: =IFERROR((SUMIFS(Data!$E$2:$E$2657,Data!$A$2:$A$2657,$A13,Data!$B$2:$B$2657,$B13,Data!$D$2:$D$2657,"Customer accounts, service & sales")+SUMIFS(Data!$G$2:$G$2657,Data!$A$2:$A$2657,$A13,Data!$B$2:$B$2657,$B13,Data!$D$2:$D$2657,"Customer accounts, service & sales"))/$D13,0) -> 0.12247373 | I13: =IFERROR((SUMIFS(Data!$E$2:$E$2657,Data!$A$2:$A$2657,$A13,Data!$B$2:$B$2657,$B13,Data!$D$2:$D$2657,"A&G and general")+SUMIFS(Data!$G$2:$G$2657,Data!$A$2:$A$2657,$A13,Data!$B$2:$B$2657,$B13,Data!$D$2:$D$2657,"A&G and general"))/$D13,0) -> 0.46225648 | J13: =IFERROR(SUMIFS(Data!$F$2:$F$2657,Data!$A$2:$A$2657,$A13,Data!$B$2:$B$2657,$B13)/$D13,0) -> 0.0010356225 | K13: =SUM(E13:I13) -> 1
... A584: 2025 | B584: Wisconsin Public Service | C584: WI | D584: =SUMIFS(Data!$E$2:$E$2657,Data!$A$2:$A$2657,$A584,Data!$B$2:$B$2657,$B584)+SUMIFS(Data!$G$2:$G$2657,Data!$A$2:$A$2657,$A584,Data!$B$2:$B$2657,$B584) -> 413.25671 | E584: =IFERROR((SUMIFS(Data!$E$2:$E$2657,Data!$A$2:$A$2657,$A584,Data!$B$2:$B$2657,$B584,Data!$D$2:$D$2657,"Transmission")+SUMIFS(Data!$G$2:$G$2657,Data!$A$2:$A$2657,$A584,Data!$B$2:$B$2657,$B584,Data!$D$2:$D$2657,"Transmission"))/$D584,0) -> 0.43897974 | F584: =IFERROR((SUMIFS(Data!$E$2:$E$2657,Data!$A$2:$A$2657,$A584,Data!$B$2:$B$2657,$B584,Data!$D$2:$D$2657,"Distribution")+SUMIFS(Data!$G$2:$G$2657,Data!$A$2:$A$2657,$A584,Data!$B$2:$B$2657,$B584,Data!$D$2:$D$2657,"Distribution"))/$D584,0) -> 0.27154684 | G584: =IFERROR((SUMIFS(Data!$E$2:$E$2657,Data!$A$2:$A$2657,$A584,Data!$B$2:$B$2657,$B584,Data!$D$2:$D$2657,"RTO/market operation")+SUMIFS(Data!$G$2:$G$2657,Data!$A$2:$A$2657,$A584,Data!$B$2:$B$2657,$B584,Data!$D$2:$D$2657,"RTO/market operation"))/$D584,0) -> 0.0048134487 | H584: =IFERROR((SUMIFS(Data!$E$2:$E$2657,Data!$A$2:$A$2657,$A584,Data!$B$2:$B$2657,$B584,Data!$D$2:$D$2657,"Customer accounts, service & sales")+SUMIFS(Data!$G$2:$G$2657,Data!$A$2:$A$2657,$A584,Data!$B$2:$B$2657,$B584,Data!$D$2:$D$2657,"Customer accounts, service & sales"))/$D584,0) -> 0.10143361 | I584: =IFERROR((SUMIFS(Data!$E$2:$E$2657,Data!$A$2:$A$2657,$A584,Data!$B$2:$B$2657,$B584,Data!$D$2:$D$2657,"A&G and general")+SUMIFS(Data!$G$2:$G$2657,Data!$A$2:$A$2657,$A584,Data!$B$2:$B$2657,$B584,Data!$D$2:$D$2657,"A&G and general"))/$D584,0) -> 0.18322637 | J584: =IFERROR(SUMIFS(Data!$F$2:$F$2657,Data!$A$2:$A$2657,$A584,Data!$B$2:$B$2657,$B584)/$D584,0) -> 0.42294433 | K584: =SUM(E584:I584) -> 1

Sheet Reconciliation
A1: Reconciliation of line items to reported totals, by utility and year
A2: Tolerance (share of reported total): | D2: 0.005
A3: Line-item O&M: sum of the O&M line items used in this workbook (credit accounts 504, 522, 922, 929 as negative). Reported O&M: PUDL row operations_and_maintenance_expenses_electric. Depreciation function rows: p. 336 depreciation_amortization_total for each plant function, after removing duplicate rows (column H). Reported depreciation: the p. 336 total-function row.
A5: Year | B5: Utility | C5: Line-item O&M ($mm) | D5: Reported total electric O&M ($mm) | E5: O&M difference ($mm) | F5: O&M difference (%) | G5: Depreciation function rows ($mm) | H5: Duplicate row removed ($mm) | I5: Reported total depreciation ($mm) | J5: Depreciation difference ($mm) | K5: Depreciation difference (%) | L5: Status | M5: Helper: absolute O&M difference, included rows ($mm)
A6: 1995 | B6: ALLETE (Minnesota Power) | C6: 284.24026 | D6: 284.24026 | E6: =IF(D6="","",C6-D6) -> 0 | F6: =IF(OR(D6="",D6=0),"",E6/D6) -> 0 | G6: 36.61544 | H6: 0 | I6: 36.61544 | J6: =IF(I6="","",G6-I6) -> 0 | K6: =IF(OR(I6="",I6=0),"",J6/I6) -> 0 | L6: =IF(OR(D6="",I6=""),"No reported total for O&M or depreciation",IF(AND(ABS(F6)<=$D$2,ABS(K6)<=$D$2),"Reconciles within tolerance","Outside tolerance")) -> Reconciles within tolerance | M6: =IF(OR(E6="",LEFT(L6,8)="Excluded"),"",ABS(E6)) -> 0
A7: 1996 | B7: ALLETE (Minnesota Power) | C7: 307.19231 | D7: 307.19231 | E7: =IF(D7="","",C7-D7) -> 0 | F7: =IF(OR(D7="",D7=0),"",E7/D7) -> 0 | G7: 37.954656 | H7: 0 | I7: 37.954656 | J7: =IF(I7="","",G7-I7) -> 0 | K7: =IF(OR(I7="",I7=0),"",J7/I7) -> 0 | L7: =IF(OR(D7="",I7=""),"No reported total for O&M or depreciation",IF(AND(ABS(F7)<=$D$2,ABS(K7)<=$D$2),"Reconciles within tolerance","Outside tolerance")) -> Reconciles within tolerance | M7: =IF(OR(E7="",LEFT(L7,8)="Excluded"),"",ABS(E7)) -> 0
A8: 1997 | B8: ALLETE (Minnesota Power) | C8: 312.01781 | D8: 312.01781 | E8: =IF(D8="","",C8-D8) -> 0 | F8: =IF(OR(D8="",D8=0),"",E8/D8) -> 0 | G8: 39.398779 | H8: 0 | I8: 39.398779 | J8: =IF(I8="","",G8-I8) -> 0 | K8: =IF(OR(I8="",I8=0),"",J8/I8) -> 0 | L8: =IF(OR(D8="",I8=""),"No reported total for O&M or depreciation",IF(AND(ABS(F8)<=$D$2,ABS(K8)<=$D$2),"Reconciles within tolerance","Outside tolerance")) -> Reconciles within tolerance | M8: =IF(OR(E8="",LEFT(L8,8)="Excluded"),"",ABS(E8)) -> 0
A9: 1998 | B9: ALLETE (Minnesota Power) | C9: 323.89261 | D9: 323.89261 | E9: =IF(D9="","",C9-D9) -> 0 | F9: =IF(OR(D9="",D9=0),"",E9/D9) -> 0 | G9: 40.52345 | H9: 0 | I9: 40.52345 | J9: =IF(I9="","",G9-I9) -> 0 | K9: =IF(OR(I9="",I9=0),"",J9/I9) -> 0 | L9: =IF(OR(D9="",I9=""),"No reported total for O&M or depreciation",IF(AND(ABS(F9)<=$D$2,ABS(K9)<=$D$2),"Reconciles within tolerance","Outside tolerance")) -> Reconciles within tolerance | M9: =IF(OR(E9="",LEFT(L9,8)="Excluded"),"",ABS(E9)) -> 0
A10: 1999 | B10: ALLETE (Minnesota Power) | C10: 325.58368 | D10: 325.58368 | E10: =IF(D10="","",C10-D10) -> 0 | F10: =IF(OR(D10="",D10=0),"",E10/D10) -> 0 | G10: 39.13347 | H10: 0 | I10: 39.13347 | J10: =IF(I10="","",G10-I10) -> 0 | K10: =IF(OR(I10="",I10=0),"",J10/I10) -> 0 | L10: =IF(OR(D10="",I10=""),"No reported total for O&M or depreciation",IF(AND(ABS(F10)<=$D$2,ABS(K10)<=$D$2),"Reconciles within tolerance","Outside tolerance")) -> Reconciles within tolerance | M10: =IF(OR(E10="",LEFT(L10,8)="Excluded"),"",ABS(E10)) -> 0
A11: 2000 | B11: ALLETE (Minnesota Power) | C11: 346.31205 | D11: 346.31205 | E11: =IF(D11="","",C11-D11) -> 0 | F11: =IF(OR(D11="",D11=0),"",E11/D11) -> 0 | G11: 40.137973 | H11: 0 | I11: 40.137973 | J11: =IF(I11="","",G11-I11) -> 0 | K11: =IF(OR(I11="",I11=0),"",J11/I11) -> 0 | L11: =IF(OR(D11="",I11=""),"No reported total for O&M or depreciation",IF(AND(ABS(F11)<=$D$2,ABS(K11)<=$D$2),"Reconciles within tolerance","Outside tolerance")) -> Reconciles within tolerance | M11: =IF(OR(E11="",LEFT(L11,8)="Excluded"),"",ABS(E11)) -> 0
A12: 2001 | B12: ALLETE (Minnesota Power) | C12: 354.84481 | D12: 354.84481 | E12: =IF(D12="","",C12-D12) -> 0 | F12: =IF(OR(D12="",D12=0),"",E12/D12) -> 0 | G12: 38.350605 | H12: 0 | I12: 38.350605 | J12: =IF(I12="","",G12-I12) -> 0 | K12: =IF(OR(I12="",I12=0),"",J12/I12) -> 0 | L12: =IF(OR(D12="",I12=""),"No reported total for O&M or depreciation",IF(AND(ABS(F12)<=$D$2,ABS(K12)<=$D$2),"Reconciles within tolerance","Outside tolerance")) -> Reconciles within tolerance | M12: =IF(OR(E12="",LEFT(L12,8)="Excluded"),"",ABS(E12)) -> 0
A13: 2002 | B13: ALLETE (Minnesota Power) | C13: 321.44805 | D13: 321.44805 | E13: =IF(D13="","",C13-D13) -> 0 | F13: =IF(OR(D13="",D13=0),"",E13/D13) -> 0 | G13: 38.216688 | H13: 0 | I13: 38.216688 | J13: =IF(I13="","",G13-I13) -> 0 | K13: =IF(OR(I13="",I13=0),"",J13/I13) -> 0 | L13: =IF(OR(D13="",I13=""),"No reported total for O&M or depreciation",IF(AND(ABS(F13)<=$D$2,ABS(K13)<=$D$2),"Reconciles within tolerance","Outside tolerance")) -> Reconciles within tolerance | M13: =IF(OR(E13="",LEFT(L13,8)="Excluded"),"",ABS(E13)) -> 0
A14: 2003 | B14: ALLETE (Minnesota Power) | C14: 342.57603 | D14: 342.57603 | E14: =IF(D14="","",C14-D14) -> 0 | F14: =IF(OR(D14="",D14=0),"",E14/D14) -> 0 | G14: 38.797093 | H14: 0 | I14: 38.797093 | J14: =IF(I14="","",G14-I14) -> 0 | K14: =IF(OR(I14="",I14=0),"",J14/I14) -> 0 | L14: =IF(OR(D14="",I14=""),"No reported total for O&M or depreciation",IF(AND(ABS(F14)<=$D$2,ABS(K14)<=$D$2),"Reconciles within tolerance","Outside tolerance")) -> Reconciles within tolerance | M14: =IF(OR(E14="",LEFT(L14,8)="Excluded"),"",ABS(E14)) -> 0
A15: 2004 | B15: ALLETE (Minnesota Power) | C15: 385.74835 | D15: 385.74835 | E15: =IF(D15="","",C15-D15) -> 0 | F15: =IF(OR(D15="",D15=0),"",E15/D15) -> 0 | G15: 37.036726 | H15: 0 | I15: 37.036726 | J15: =IF(I15="","",G15-I15) -> 0 | K15: =IF(OR(I15="",I15=0),"",J15/I15) -> 0 | L15: =IF(OR(D15="",I15=""),"No reported total for O&M or depreciation",IF(AND(ABS(F15)<=$D$2,ABS(K15)<=$D$2),"Reconciles within tolerance","Outside tolerance")) -> Reconciles within tolerance | M15: =IF(OR(E15="",LEFT(L15,8)="Excluded"),"",ABS(E15)) -> 0
A16: 2005 | B16: ALLETE (Minnesota Power) | C16: 396.2457 | D16: 396.2457 | E16: =IF(D16="","",C16-D16) -> 0 | F16: =IF(OR(D16="",D16=0),"",E16/D16) -> 0 | G16: 36.82965 | H16: 0 | I16: 36.82965 | J16: =IF(I16="","",G16-I16) -> 0 | K16: =IF(OR(I16="",I16=0),"",J16/I16) -> 0 | L16: =IF(OR(D16="",I16=""),"No reported total for O&M or depreciation",IF(AND(ABS(F16)<=$D$2,ABS(K16)<=$D$2),"Reconciles within tolerance","Outside tolerance")) -> Reconciles within tolerance | M16: =IF(OR(E16="",LEFT(L16,8)="Excluded"),"",ABS(E16)) -> 0
A17: 2006 | B17: ALLETE (Minnesota Power) | C17: 453.86135 | D17: 453.86135 | E17: =IF(D17="","",C17-D17) -> 0 | F17: =IF(OR(D17="",D17=0),"",E17/D17) -> 0 | G17: 41.452873 | H17: 0 | I17: 41.452873 | J17: =IF(I17="","",G17-I17) -> 0 | K17: =IF(OR(I17="",I17=0),"",J17/I17) -> 0 | L17: =IF(OR(D17="",I17=""),"No reported total for O&M or depreciation",IF(AND(ABS(F17)<=$D$2,ABS(K17)<=$D$2),"Reconciles within tolerance","Outside tolerance")) -> Reconciles within tolerance | M17: =IF(OR(E17="",LEFT(L17,8)="Excluded"),"",ABS(E17)) -> 0
... A47: 2005 | B47: Ameren Illinois | C47: 1706.4663 | D47: 1706.4663 | E47: =IF(D47="","",C47-D47) -> 0 | F47: =IF(OR(D47="",D47=0),"",E47/D47) -> 0 | G47: 134.60709 | H47: 0 | I47: 134.60709 | J47: =IF(I47="","",G47-I47) -> 0 | K47: =IF(OR(I47="",I47=0),"",J47/I47) -> 0 | L47: =IF(OR(D47="",I47=""),"No reported total for O&M or depreciation",IF(AND(ABS(F47)<=$D$2,ABS(K47)<=$D$2),"Reconciles within tolerance","Outside tolerance")) -> Reconciles within tolerance | M47: =IF(OR(E47="",LEFT(L47,8)="Excluded"),"",ABS(E47)) -> 0
A48: 2006 | B48: Ameren Illinois | C48: 2141.9692 | D48: 1787.4833 | E48: =IF(D48="","",C48-D48) -> 354.48588 | F48: =IF(OR(D48="",D48=0),"",E48/D48) -> 0.19831564 | G48: 140.29823 | H48: 0 | I48: 140.29823 | J48: =IF(I48="","",G48-I48) -> 0 | K48: =IF(OR(I48="",I48=0),"",J48/I48) -> 0 | L48: Excluded from analysis (Notes, data treatment 4) | M48: =IF(OR(E48="",LEFT(L48,8)="Excluded"),"",ABS(E48))
A49: 2007 | B49: Ameren Illinois | C49: 1891.2094 | D49: 1891.2094 | E49: =IF(D49="","",C49-D49) -> 0 | F49: =IF(OR(D49="",D49=0),"",E49/D49) -> 0 | G49: 144.72827 | H49: 0 | I49: 144.72827 | J49: =IF(I49="","",G49-I49) -> 0 | K49: =IF(OR(I49="",I49=0),"",J49/I49) -> 0 | L49: =IF(OR(D49="",I49=""),"No reported total for O&M or depreciation",IF(AND(ABS(F49)<=$D$2,ABS(K49)<=$D$2),"Reconciles within tolerance","Outside tolerance")) -> Reconciles within tolerance | M49: =IF(OR(E49="",LEFT(L49,8)="Excluded"),"",ABS(E49)) -> 0
A50: 2008 | B50: Ameren Illinois | C50: 1848.7509 | D50: 1848.7509 | E50: =IF(D50="","",C50-D50) -> 0 | F50: =IF(OR(D50="",D50=0),"",E50/D50) -> 0 | G50: 151.80568 | H50: 0 | I50: 151.80568 | J50: =IF(I50="","",G50-I50) -> 0 | K50: =IF(OR(I50="",I50=0),"",J50/I50) -> 0 | L50: =IF(OR(D50="",I50=""),"No reported total for O&M or depreciation",IF(AND(ABS(F50)<=$D$2,ABS(K50)<=$D$2),"Reconciles within tolerance","Outside tolerance")) -> Reconciles within tolerance | M50: =IF(OR(E50="",LEFT(L50,8)="Excluded"),"",ABS(E50)) -> 0
A51: 2009 | B51: Ameren Illinois | C51: 1539.0796 | D51: 1539.0796 | E51: =IF(D51="","",C51-D51) -> 0 | F51: =IF(OR(D51="",D51=0),"",E51/D51) -> 0 | G51: 168.58011 | H51: 0 | I51: 168.58011 | J51: =IF(I51="","",G51-I51) -> 0 | K51: =IF(OR(I51="",I51=0),"",J51/I51) -> 0 | L51: =IF(OR(D51="",I51=""),"No reported total for O&M or depreciation",IF(AND(ABS(F51)<=$D$2,ABS(K51)<=$D$2),"Reconciles within tolerance","Outside tolerance")) -> Reconciles within tolerance | M51: =IF(OR(E51="",LEFT(L51,8)="Excluded"),"",ABS(E51)) -> 0
A52: 2010 | B52: Ameren Illinois | C52: 1377.5525 | D52: 1377.5525 | E52: =IF(D52="","",C52-D52) -> 0 | F52: =IF(OR(D52="",D52=0),"",E52/D52) -> 0 | G52: 171.78685 | H52: 0 | I52: 171.78685 | J52: =IF(I52="","",G52-I52) -> 0 | K52: =IF(OR(I52="",I52=0),"",J52/I52) -> 0 | L52: =IF(OR(D52="",I52=""),"No reported total for O&M or depreciation",IF(AND(ABS(F52)<=$D$2,ABS(K52)<=$D$2),"Reconciles within tolerance","Outside tolerance")) -> Reconciles within tolerance | M52: =IF(OR(E52="",LEFT(L52,8)="Excluded"),"",ABS(E52)) -> 0
A53: 2011 | B53: Ameren Illinois | C53: 1306.5952 | D53: 1306.5952 | E53: =IF(D53="","",C53-D53) -> 0 | F53: =IF(OR(D53="",D53=0),"",E53/D53) -> 0 | G53: 176.06646 | H53: 0 | I53: 176.06646 | J53: =IF(I53="","",G53-I53) -> 0 | K53: =IF(OR(I53="",I53=0),"",J53/I53) -> 0 | L53: =IF(OR(D53="",I53=""),"No reported total for O&M or depreciation",IF(AND(ABS(F53)<=$D$2,ABS(K53)<=$D$2),"Reconciles within tolerance","Outside tolerance")) -> Reconciles within tolerance | M53: =IF(OR(E53="",LEFT(L53,8)="Excluded"),"",ABS(E53)) -> 0
A54: 2012 | B54: Ameren Illinois | C54: 1176.8776 | D54: 1176.8776 | E54: =IF(D54="","",C54-D54) -> 0 | F54: =IF(OR(D54="",D54=0),"",E54/D54) -> 0 | G54: 182.70093 | H54: 0 | I54: 182.70093 | J54: =IF(I54="","",G54-I54) -> 0 | K54: =IF(OR(I54="",I54=0),"",J54/I54) -> 0 | L54: =IF(OR(D54="",I54=""),"No reported total for O&M or depreciation",IF(AND(ABS(F54)<=$D$2,ABS(K54)<=$D$2),"Reconciles within tolerance","Outside tolerance")) -> Reconciles within tolerance | M54: =IF(OR(E54="",LEFT(L54,8)="Excluded"),"",ABS(E54)) -> 0
A55: 2013 | B55: Ameren Illinois | C55: 899.77123 | D55: 899.77123 | E55: =IF(D55="","",C55-D55) -> 0 | F55: =IF(OR(D55="",D55=0),"",E55/D55) -> 0 | G55: 205.70518 | H55: 0 | I55: 205.70518 | J55: =IF(I55="","",G55-I55) -> 0 | K55: =IF(OR(I55="",I55=0),"",J55/I55) -> 0 | L55: =IF(OR(D55="",I55=""),"No reported total for O&M or depreciation",IF(AND(ABS(F55)<=$D$2,ABS(K55)<=$D$2),"Reconciles within tolerance","Outside tolerance")) -> Reconciles within tolerance | M55: =IF(OR(E55="",LEFT(L55,8)="Excluded"),"",ABS(E55)) -> 0
A56: 2014 | B56: Ameren Illinois | C56: 927.35921 | D56: 927.35921 | E56: =IF(D56="","",C56-D56) -> 0 | F56: =IF(OR(D56="",D56=0),"",E56/D56) -> 0 | G56: 222.44603 | H56: 0 | I56: 222.44603 | J56: =IF(I56="","",G56-I56) -> 0 | K56: =IF(OR(I56="",I56=0),"",J56/I56) -> 0 | L56: =IF(OR(D56="",I56=""),"No reported total for O&M or depreciation",IF(AND(ABS(F56)<=$D$2,ABS(K56)<=$D$2),"Reconciles within tolerance","Outside tolerance")) -> Reconciles within tolerance | M56: =IF(OR(E56="",LEFT(L56,8)="Excluded"),"",ABS(E56)) -> 0
A57: 2015 | B57: Ameren Illinois | C57: 1006.9449 | D57: 1006.9449 | E57: =IF(D57="","",C57-D57) -> 0 | F57: =IF(OR(D57="",D57=0),"",E57/D57) -> 0 | G57: 242.26477 | H57: 0 | I57: 242.26477 | J57: =IF(I57="","",G57-I57) -> 0 | K57: =IF(OR(I57="",I57=0),"",J57/I57) -> 0 | L57: =IF(OR(D57="",I57=""),"No reported total for O&M or depreciation",IF(AND(ABS(F57)<=$D$2,ABS(K57)<=$D$2),"Reconciles within tolerance","Outside tolerance")) -> Reconciles within tolerance | M57: =IF(OR(E57="",LEFT(L57,8)="Excluded"),"",ABS(E57)) -> 0
A58: 2016 | B58: Ameren Illinois | C58: 992.65207 | D58: 992.65207 | E58: =IF(D58="","",C58-D58) -> 0 | F58: =IF(OR(D58="",D58=0),"",E58/D58) -> 0 | G58: 264.86377 | H58: 0 | I58: 264.86377 | J58: =IF(I58="","",G58-I58) -> 0 | K58: =IF(OR(I58="",I58=0),"",J58/I58) -> 0 | L58: =IF(OR(D58="",I58=""),"No reported total for O&M or depreciation",IF(AND(ABS(F58)<=$D$2,ABS(K58)<=$D$2),"Reconciles within tolerance","Outside tolerance")) -> Reconciles within tolerance | M58: =IF(OR(E58="",LEFT(L58,8)="Excluded"),"",ABS(E58)) -> 0
A59: 2017 | B59: Ameren Illinois | C59: 955.44566 | D59: 955.44566 | E59: =IF(D59="","",C59-D59) -> 0 | F59: =IF(OR(D59="",D59=0),"",E59/D59) -> 0 | G59: 282.70688 | H59: 0 | I59: 282.70688 | J59: =IF(I59="","",G59-I59) -> 0 | K59: =IF(OR(I59="",I59=0),"",J59/I59) -> 0 | L59: =IF(OR(D59="",I59=""),"No reported total for O&M or depreciation",IF(AND(ABS(F59)<=$D$2,ABS(K59)<=$D$2),"Reconciles within tolerance","Outside tolerance")) -> Reconciles within tolerance | M59: =IF(OR(E59="",LEFT(L59,8)="Excluded"),"",ABS(E59)) -> 0
A60: 2018 | B60: Ameren Illinois | C60: 936.35114 | D60: 936.35114 | E60: =IF(D60="","",C60-D60) -> 0 | F60: =IF(OR(D60="",D60=0),"",E60/D60) -> 0 | G60: 309.3227 | H60: 0 | I60: 309.3227 | J60: =IF(I60="","",G60-I60) -> 0 | K60: =IF(OR(I60="",I60=0),"",J60/I60) -> 0 | L60: =IF(OR(D60="",I60=""),"No reported total for O&M or depreciation",IF(AND(ABS(F60)<=$D$2,ABS(K60)<=$D$2),"Reconciles within tolerance","Outside tolerance")) -> Reconciles within tolerance | M60: =IF(OR(E60="",LEFT(L60,8)="Excluded"),"",ABS(E60)) -> 0
... A136: 2005 | B136: DTE Electric | C136: 2857.6516 | D136: 2857.6516 | E136: =IF(D136="","",C136-D136) -> 0 | F136: =IF(OR(D136="",D136=0),"",E136/D136) -> 0 | G136: 432.89329 | H136: 0 | I136: 432.89329 | J136: =IF(I136="","",G136-I136) -> 0 | K136: =IF(OR(I136="",I136=0),"",J136/I136) -> 0 | L136: =IF(OR(D136="",I136=""),"No reported total for O&M or depreciation",IF(AND(ABS(F136)<=$D$2,ABS(K136)<=$D$2),"Reconciles within tolerance","Outside tolerance")) -> Reconciles within tolerance | M136: =IF(OR(E136="",LEFT(L136,8)="Excluded"),"",ABS(E136)) -> 0
A137: 2006 | B137: DTE Electric | C137: 2850.9912 | D137: 2850.9912 | E137: =IF(D137="","",C137-D137) -> 0 | F137: =IF(OR(D137="",D137=0),"",E137/D137) -> 0 | G137: 866.52423 | H137: 0 | J137: =IF(I137="","",G137-I137) | K137: =IF(OR(I137="",I137=0),"",J137/I137) | L137: =IF(OR(D137="",I137=""),"No reported total for O&M or depreciation",IF(AND(ABS(F137)<=$D$2,ABS(K137)<=$D$2),"Reconciles within tolerance","Outside tolerance")) -> No reported total for O&M or depreciation | M137: =IF(OR(E137="",LEFT(L137,8)="Excluded"),"",ABS(E137)) -> 0
A138: 2007 | B138: DTE Electric | C138: 3051.3545 | D138: 3051.3545 | E138: =IF(D138="","",C138-D138) -> 0 | F138: =IF(OR(D138="",D138=0),"",E138/D138) -> 0 | G138: 453.22411 | H138: 0 | I138: 453.22411 | J138: =IF(I138="","",G138-I138) -> 0 | K138: =IF(OR(I138="",I138=0),"",J138/I138) -> 0 | L138: =IF(OR(D138="",I138=""),"No reported total for O&M or depreciation",IF(AND(ABS(F138)<=$D$2,ABS(K138)<=$D$2),"Reconciles within tolerance","Outside tolerance")) -> Reconciles within tolerance | M138: =IF(OR(E138="",LEFT(L138,8)="Excluded"),"",ABS(E138)) -> 0
A139: 2008 | B139: DTE Electric | C139: 3071.1651 | D139: 3071.1651 | E139: =IF(D139="","",C139-D139) -> 0 | F139: =IF(OR(D139="",D139=0),"",E139/D139) -> 0 | G139: 473.03205 | H139: 0 | I139: 473.03205 | J139: =IF(I139="","",G139-I139) -> 0 | K139: =IF(OR(I139="",I139=0),"",J139/I139) -> 0 | L139: =IF(OR(D139="",I139=""),"No reported total for O&M or depreciation",IF(AND(ABS(F139)<=$D$2,ABS(K139)<=$D$2),"Reconciles within tolerance","Outside tolerance")) -> Reconciles within tolerance | M139: =IF(OR(E139="",LEFT(L139,8)="Excluded"),"",ABS(E139)) -> 0
A140: 2009 | B140: DTE Electric | C140: 2746.7696 | D140: 2746.7696 | E140: =IF(D140="","",C140-D140) -> 0 | F140: =IF(OR(D140="",D140=0),"",E140/D140) -> 0 | G140: 512.43481 | H140: 0 | I140: 512.43481 | J140: =IF(I140="","",G140-I140) -> 0 | K140: =IF(OR(I140="",I140=0),"",J140/I140) -> 0 | L140: =IF(OR(D140="",I140=""),"No reported total for O&M or depreciation",IF(AND(ABS(F140)<=$D$2,ABS(K140)<=$D$2),"Reconciles within tolerance","Outside tolerance")) -> Reconciles within tolerance | M140: =IF(OR(E140="",LEFT(L140,8)="Excluded"),"",ABS(E140)) -> 0
A141: 2010 | B141: DTE Electric | C141: 2919.1942 | D141: 2919.1942 | E141: =IF(D141="","",C141-D141) -> 0 | F141: =IF(OR(D141="",D141=0),"",E141/D141) -> 0 | G141: 532.62842 | H141: 0 | I141: 532.62842 | J141: =IF(I141="","",G141-I141) -> 0 | K141: =IF(OR(I141="",I141=0),"",J141/I141) -> 0 | L141: =IF(OR(D141="",I141=""),"No reported total for O&M or depreciation",IF(AND(ABS(F141)<=$D$2,ABS(K141)<=$D$2),"Reconciles within tolerance","Outside tolerance")) -> Reconciles within tolerance | M141: =IF(OR(E141="",LEFT(L141,8)="Excluded"),"",ABS(E141)) -> 0
A142: 2011 | B142: DTE Electric | C142: 3095.7072 | D142: 3095.7072 | E142: =IF(D142="","",C142-D142) -> 0 | F142: =IF(OR(D142="",D142=0),"",E142/D142) -> 0 | G142: 546.24838 | H142: 0 | I142: 546.24838 | J142: =IF(I142="","",G142-I142) -> 0 | K142: =IF(OR(I142="",I142=0),"",J142/I142) -> 0 | L142: =IF(OR(D142="",I142=""),"No reported total for O&M or depreciation",IF(AND(ABS(F142)<=$D$2,ABS(K142)<=$D$2),"Reconciles within tolerance","Outside tolerance")) -> Reconciles within tolerance | M142: =IF(OR(E142="",LEFT(L142,8)="Excluded"),"",ABS(E142)) -> 0
A143: 2012 | B143: DTE Electric | C143: 3166.7919 | D143: 3166.7919 | E143: =IF(D143="","",C143-D143) -> 0 | F143: =IF(OR(D143="",D143=0),"",E143/D143) -> 0 | G143: 535.06226 | H143: 0 | I143: 535.06226 | J143: =IF(I143="","",G143-I143) -> 0 | K143: =IF(OR(I143="",I143=0),"",J143/I143) -> 0 | L143: =IF(OR(D143="",I143=""),"No reported total for O&M or depreciation",IF(AND(ABS(F143)<=$D$2,ABS(K143)<=$D$2),"Reconciles within tolerance","Outside tolerance")) -> Reconciles within tolerance | M143: =IF(OR(E143="",LEFT(L143,8)="Excluded"),"",ABS(E143)) -> 0
A144: 2013 | B144: DTE Electric | C144: 3051.527 | D144: 3051.527 | E144: =IF(D144="","",C144-D144) -> 0 | F144: =IF(OR(D144="",D144=0),"",E144/D144) -> 0 | G144: 562.75295 | H144: 0 | I144: 562.75295 | J144: =IF(I144="","",G144-I144) -> 0 | K144: =IF(OR(I144="",I144=0),"",J144/I144) -> 0 | L144: =IF(OR(D144="",I144=""),"No reported total for O&M or depreciation",IF(AND(ABS(F144)<=$D$2,ABS(K144)<=$D$2),"Reconciles within tolerance","Outside tolerance")) -> Reconciles within tolerance | M144: =IF(OR(E144="",LEFT(L144,8)="Excluded"),"",ABS(E144)) -> 0
A145: 2014 | B145: DTE Electric | C145: 3009.9468 | D145: 3009.9468 | E145: =IF(D145="","",C145-D145) -> 0 | F145: =IF(OR(D145="",D145=0),"",E145/D145) -> 0 | G145: 594.02653 | H145: 0 | I145: 594.02653 | J145: =IF(I145="","",G145-I145) -> 0 | K145: =IF(OR(I145="",I145=0),"",J145/I145) -> 0 | L145: =IF(OR(D145="",I145=""),"No reported total for O&M or depreciation",IF(AND(ABS(F145)<=$D$2,ABS(K145)<=$D$2),"Reconciles within tolerance","Outside tolerance")) -> Reconciles within tolerance | M145: =IF(OR(E145="",LEFT(L145,8)="Excluded"),"",ABS(E145)) -> 0
A146: 2015 | B146: DTE Electric | C146: 2895.4091 | D146: 2895.4091 | E146: =IF(D146="","",C146-D146) -> 0 | F146: =IF(OR(D146="",D146=0),"",E146/D146) -> 0 | G146: 656.31761 | H146: 0 | I146: 656.31761 | J146: =IF(I146="","",G146-I146) -> 0 | K146: =IF(OR(I146="",I146=0),"",J146/I146) -> 0 | L146: =IF(OR(D146="",I146=""),"No reported total for O&M or depreciation",IF(AND(ABS(F146)<=$D$2,ABS(K146)<=$D$2),"Reconciles within tolerance","Outside tolerance")) -> Reconciles within tolerance | M146: =IF(OR(E146="",LEFT(L146,8)="Excluded"),"",ABS(E146)) -> 0
A147: 2016 | B147: DTE Electric | C147: 2979.6384 | D147: 2979.6384 | E147: =IF(D147="","",C147-D147) -> 0 | F147: =IF(OR(D147="",D147=0),"",E147/D147) -> 0 | G147: 688.27066 | H147: 0 | I147: 688.27066 | J147: =IF(I147="","",G147-I147) -> 0 | K147: =IF(OR(I147="",I147=0),"",J147/I147) -> 0 | L147: =IF(OR(D147="",I147=""),"No reported total for O&M or depreciation",IF(AND(ABS(F147)<=$D$2,ABS(K147)<=$D$2),"Reconciles within tolerance","Outside tolerance")) -> Reconciles within tolerance | M147: =IF(OR(E147="",LEFT(L147,8)="Excluded"),"",ABS(E147)) -> 0
A148: 2017 | B148: DTE Electric | C148: 2873.9002 | D148: 2873.9002 | E148: =IF(D148="","",C148-D148) -> 0 | F148: =IF(OR(D148="",D148=0),"",E148/D148) -> 0 | G148: 729.72771 | H148: 0 | I148: 729.72771 | J148: =IF(I148="","",G148-I148) -> 0 | K148: =IF(OR(I148="",I148=0),"",J148/I148) -> 0 | L148: =IF(OR(D148="",I148=""),"No reported total for O&M or depreciation",IF(AND(ABS(F148)<=$D$2,ABS(K148)<=$D$2),"Reconciles within tolerance","Outside tolerance")) -> Reconciles within tolerance | M148: =IF(OR(E148="",LEFT(L148,8)="Excluded"),"",ABS(E148)) -> 0
A149: 2018 | B149: DTE Electric | C149: 3012.0459 | D149: 3012.0459 | E149: =IF(D149="","",C149-D149) -> 0 | F149: =IF(OR(D149="",D149=0),"",E149/D149) -> 0 | G149: 774.79595 | H149: 0 | I149: 774.79595 | J149: =IF(I149="","",G149-I149) -> 0 | K149: =IF(OR(I149="",I149=0),"",J149/I149) -> 0 | L149: =IF(OR(D149="",I149=""),"No reported total for O&M or depreciation",IF(AND(ABS(F149)<=$D$2,ABS(K149)<=$D$2),"Reconciles within tolerance","Outside tolerance")) -> Reconciles within tolerance | M149: =IF(OR(E149="",LEFT(L149,8)="Excluded"),"",ABS(E149)) -> 0
... A291: 2005 | B291: Madison Gas & Electric | C291: 236.69429 | D291: 236.69429 | E291: =IF(D291="","",C291-D291) -> 0 | F291: =IF(OR(D291="",D291=0),"",E291/D291) -> 0 | G291: 19.528101 | H291: 0 | I291: 19.528101 | J291: =IF(I291="","",G291-I291) -> 0 | K291: =IF(OR(I291="",I291=0),"",J291/I291) -> 0 | L291: =IF(OR(D291="",I291=""),"No reported total for O&M or depreciation",IF(AND(ABS(F291)<=$D$2,ABS(K291)<=$D$2),"Reconciles within tolerance","Outside tolerance")) -> Reconciles within tolerance | M291: =IF(OR(E291="",LEFT(L291,8)="Excluded"),"",ABS(E291)) -> 0
A292: 2006 | B292: Madison Gas & Electric | C292: 398.18902 | D292: 233.55147 | E292: =IF(D292="","",C292-D292) -> 164.63755 | F292: =IF(OR(D292="",D292=0),"",E292/D292) -> 0.7049305 | G292: 23.003845 | H292: 0 | I292: 23.003845 | J292: =IF(I292="","",G292-I292) -> 0 | K292: =IF(OR(I292="",I292=0),"",J292/I292) -> 0 | L292: Excluded from analysis (Notes, data treatment 4) | M292: =IF(OR(E292="",LEFT(L292,8)="Excluded"),"",ABS(E292))
A293: 2007 | B293: Madison Gas & Electric | C293: 242.68004 | D293: 242.68004 | E293: =IF(D293="","",C293-D293) -> 0 | F293: =IF(OR(D293="",D293=0),"",E293/D293) -> 0 | G293: 23.672787 | H293: 0 | I293: 23.672787 | J293: =IF(I293="","",G293-I293) -> 0 | K293: =IF(OR(I293="",I293=0),"",J293/I293) -> 0 | L293: =IF(OR(D293="",I293=""),"No reported total for O&M or depreciation",IF(AND(ABS(F293)<=$D$2,ABS(K293)<=$D$2),"Reconciles within tolerance","Outside tolerance")) -> Reconciles within tolerance | M293: =IF(OR(E293="",LEFT(L293,8)="Excluded"),"",ABS(E293)) -> 0
A294: 2008 | B294: Madison Gas & Electric | C294: 262.27606 | D294: 262.27606 | E294: =IF(D294="","",C294-D294) -> 0 | F294: =IF(OR(D294="",D294=0),"",E294/D294) -> 0 | G294: 30.097864 | H294: 0 | I294: 30.097864 | J294: =IF(I294="","",G294-I294) -> 0 | K294: =IF(OR(I294="",I294=0),"",J294/I294) -> 0 | L294: =IF(OR(D294="",I294=""),"No reported total for O&M or depreciation",IF(AND(ABS(F294)<=$D$2,ABS(K294)<=$D$2),"Reconciles within tolerance","Outside tolerance")) -> Reconciles within tolerance | M294: =IF(OR(E294="",LEFT(L294,8)="Excluded"),"",ABS(E294)) -> 0
A295: 2009 | B295: Madison Gas & Electric | C295: 236.95837 | D295: 236.95837 | E295: =IF(D295="","",C295-D295) -> 0 | F295: =IF(OR(D295="",D295=0),"",E295/D295) -> 0 | G295: 31.523378 | H295: 0 | I295: 31.523378 | J295: =IF(I295="","",G295-I295) -> 0 | K295: =IF(OR(I295="",I295=0),"",J295/I295) -> 0 | L295: =IF(OR(D295="",I295=""),"No reported total for O&M or depreciation",IF(AND(ABS(F295)<=$D$2,ABS(K295)<=$D$2),"Reconciles within tolerance","Outside tolerance")) -> Reconciles within tolerance | M295: =IF(OR(E295="",LEFT(L295,8)="Excluded"),"",ABS(E295)) -> 0
A296: 2010 | B296: Madison Gas & Electric | C296: 242.8119 | D296: 242.8119 | E296: =IF(D296="","",C296-D296) -> 0 | F296: =IF(OR(D296="",D296=0),"",E296/D296) -> 0 | G296: 32.722682 | H296: 0 | I296: 32.722682 | J296: =IF(I296="","",G296-I296) -> 0 | K296: =IF(OR(I296="",I296=0),"",J296/I296) -> 0 | L296: =IF(OR(D296="",I296=""),"No reported total for O&M or depreciation",IF(AND(ABS(F296)<=$D$2,ABS(K296)<=$D$2),"Reconciles within tolerance","Outside tolerance")) -> Reconciles within tolerance | M296: =IF(OR(E296="",LEFT(L296,8)="Excluded"),"",ABS(E296)) -> 0
A297: 2011 | B297: Madison Gas & Electric | C297: 243.18228 | D297: 243.18228 | E297: =IF(D297="","",C297-D297) -> 0 | F297: =IF(OR(D297="",D297=0),"",E297/D297) -> 0 | G297: 35.349183 | H297: 0 | I297: 35.349183 | J297: =IF(I297="","",G297-I297) -> 0 | K297: =IF(OR(I297="",I297=0),"",J297/I297) -> 0 | L297: =IF(OR(D297="",I297=""),"No reported total for O&M or depreciation",IF(AND(ABS(F297)<=$D$2,ABS(K297)<=$D$2),"Reconciles within tolerance","Outside tolerance")) -> Reconciles within tolerance | M297: =IF(OR(E297="",LEFT(L297,8)="Excluded"),"",ABS(E297)) -> 0
A298: 2012 | B298: Madison Gas & Electric | C298: 254.30877 | D298: 254.30877 | E298: =IF(D298="","",C298-D298) -> 0 | F298: =IF(OR(D298="",D298=0),"",E298/D298) -> 0 | G298: 33.138369 | H298: 0 | I298: 33.138369 | J298: =IF(I298="","",G298-I298) -> 0 | K298: =IF(OR(I298="",I298=0),"",J298/I298) -> 0 | L298: =IF(OR(D298="",I298=""),"No reported total for O&M or depreciation",IF(AND(ABS(F298)<=$D$2,ABS(K298)<=$D$2),"Reconciles within tolerance","Outside tolerance")) -> Reconciles within tolerance | M298: =IF(OR(E298="",LEFT(L298,8)="Excluded"),"",ABS(E298)) -> 0
A299: 2013 | B299: Madison Gas & Electric | C299: 263.10982 | D299: 263.10982 | E299: =IF(D299="","",C299-D299) -> 0 | F299: =IF(OR(D299="",D299=0),"",E299/D299) -> 0 | G299: 32.936018 | H299: 0 | I299: 32.936018 | J299: =IF(I299="","",G299-I299) -> 0 | K299: =IF(OR(I299="",I299=0),"",J299/I299) -> 0 | L299: =IF(OR(D299="",I299=""),"No reported total for O&M or depreciation",IF(AND(ABS(F299)<=$D$2,ABS(K299)<=$D$2),"Reconciles within tolerance","Outside tolerance")) -> Reconciles within tolerance | M299: =IF(OR(E299="",LEFT(L299,8)="Excluded"),"",ABS(E299)) -> 0
A300: 2014 | B300: Madison Gas & Electric | C300: 242.12892 | D300: 242.12892 | E300: =IF(D300="","",C300-D300) -> 0 | F300: =IF(OR(D300="",D300=0),"",E300/D300) -> 0 | G300: 34.340443 | H300: 0 | I300: 34.340443 | J300: =IF(I300="","",G300-I300) -> 0 | K300: =IF(OR(I300="",I300=0),"",J300/I300) -> 0 | L300: =IF(OR(D300="",I300=""),"No reported total for O&M or depreciation",IF(AND(ABS(F300)<=$D$2,ABS(K300)<=$D$2),"Reconciles within tolerance","Outside tolerance")) -> Reconciles within tolerance | M300: =IF(OR(E300="",LEFT(L300,8)="Excluded"),"",ABS(E300)) -> 0
A301: 2015 | B301: Madison Gas & Electric | C301: 266.37582 | D301: 266.37582 | E301: =IF(D301="","",C301-D301) -> 0 | F301: =IF(OR(D301="",D301=0),"",E301/D301) -> 0 | G301: 37.419942 | H301: 0 | I301: 37.419942 | J301: =IF(I301="","",G301-I301) -> 0 | K301: =IF(OR(I301="",I301=0),"",J301/I301) -> 0 | L301: =IF(OR(D301="",I301=""),"No reported total for O&M or depreciation",IF(AND(ABS(F301)<=$D$2,ABS(K301)<=$D$2),"Reconciles within tolerance","Outside tolerance")) -> Reconciles within tolerance | M301: =IF(OR(E301="",LEFT(L301,8)="Excluded"),"",ABS(E301)) -> 0
A302: 2016 | B302: Madison Gas & Electric | C302: 254.3119 | D302: 254.3119 | E302: =IF(D302="","",C302-D302) -> 0 | F302: =IF(OR(D302="",D302=0),"",E302/D302) -> 0 | G302: 36.494426 | H302: 0 | I302: 36.494426 | J302: =IF(I302="","",G302-I302) -> 0 | K302: =IF(OR(I302="",I302=0),"",J302/I302) -> 0 | L302: =IF(OR(D302="",I302=""),"No reported total for O&M or depreciation",IF(AND(ABS(F302)<=$D$2,ABS(K302)<=$D$2),"Reconciles within tolerance","Outside tolerance")) -> Reconciles within tolerance | M302: =IF(OR(E302="",LEFT(L302,8)="Excluded"),"",ABS(E302)) -> 0
A303: 2017 | B303: Madison Gas & Electric | C303: 251.6214 | D303: 251.6214 | E303: =IF(D303="","",C303-D303) -> 0 | F303: =IF(OR(D303="",D303=0),"",E303/D303) -> 0 | G303: 44.07651 | H303: 0 | I303: 44.07651 | J303: =IF(I303="","",G303-I303) -> 0 | K303: =IF(OR(I303="",I303=0),"",J303/I303) -> 0 | L303: =IF(OR(D303="",I303=""),"No reported total for O&M or depreciation",IF(AND(ABS(F303)<=$D$2,ABS(K303)<=$D$2),"Reconciles within tolerance","Outside tolerance")) -> Reconciles within tolerance | M303: =IF(OR(E303="",LEFT(L303,8)="Excluded"),"",ABS(E303)) -> 0
A304: 2018 | B304: Madison Gas & Electric | C304: 245.73471 | D304: 245.73471 | E304: =IF(D304="","",C304-D304) -> 0 | F304: =IF(OR(D304="",D304=0),"",E304/D304) -> 0 | G304: 46.312936 | H304: 0 | I304: 46.312936 | J304: =IF(I304="","",G304-I304) -> 0 | K304: =IF(OR(I304="",I304=0),"",J304/I304) -> 0 | L304: =IF(OR(D304="",I304=""),"No reported total for O&M or depreciation",IF(AND(ABS(F304)<=$D$2,ABS(K304)<=$D$2),"Reconciles within tolerance","Outside tolerance")) -> Reconciles within tolerance | M304: =IF(OR(E304="",LEFT(L304,8)="Excluded"),"",ABS(E304)) -> 0
... A590: 2025 | B590: Wisconsin Public Service | C590: 812.28759 | D590: 812.28759 | E590: =IF(D590="","",C590-D590) -> 0 | F590: =IF(OR(D590="",D590=0),"",E590/D590) -> 0 | G590: 212.10185 | H590: 0 | I590: 212.10185 | J590: =IF(I590="","",G590-I590) -> 0 | K590: =IF(OR(I590="",I590=0),"",J590/I590) -> 0 | L590: =IF(OR(D590="",I590=""),"No reported total for O&M or depreciation",IF(AND(ABS(F590)<=$D$2,ABS(K590)<=$D$2),"Reconciles within tolerance","Outside tolerance")) -> Reconciles within tolerance | M590: =IF(OR(E590="",LEFT(L590,8)="Excluded"),"",ABS(E590)) -> 0
A592: Utility-years outside tolerance (excluding the excluded row): | F592: =COUNTIF(L6:L590,"Outside tolerance") -> 0
A593: Utility-years with no reported total: | F593: =COUNTIF(L6:L590,"No reported total*") -> 1
A594: Largest absolute O&M difference, included utility-years ($mm): | F594: =MAX(M6:M590) -> 0.947469

Sheet Transmission Transfers
A1: Transfers of peer utilities’ transmission systems to transmission-only companies
A2: Context from outside the FERC Form 1 data. Dates and parties are taken from web search results (2026-10-24) that summarize the cited documents; the documents themselves could not be opened from the analysis environment, whose network policy blocks sec.gov and the publishers listed. Verify against the cited filings before relying on the dates. Columns F–I calculate from the Data sheet.
A4: Utility | B4: Transferred to | C4: Date (per sources) | D4: Sources (as identified by search) | E4: Year compared | F4: Acct 565, year before ($mm) | G4: Acct 565, year of change ($mm) | H4: Own transmission O&M + depreciation excl. 565, year before ($mm) | I4: Own transmission O&M + depreciation excl. 565, year of change ($mm)
A5: Wisconsin Electric Power | B5: American Transmission Company LLC | C5: Began operations 2001-01-01 | D5: U.S. Department of Energy, joint transmission paper, 2009 update: https://www.energy.gov/sites/prod/files/2015/03/f20/Paper%20Joint%20Transmission%202009%20update.pdf ; SEC 10-K405 for fiscal 2001: https://www.sec.gov/Archives/edgar/data/61339/000006133902000004/yearend.htm. Per the DOE summary, the four utilities listed contributed transmission assets; NSP-Wisconsin is not among them. | E5: 2001 | F5: =SUMIFS(Data!$F$2:$F$2657,Data!$B$2:$B$2657,$A5,Data!$A$2:$A$2657,$E5-1) -> 3.857127 | G5: =SUMIFS(Data!$F$2:$F$2657,Data!$B$2:$B$2657,$A5,Data!$A$2:$A$2657,$E5-0) -> 59.659659 | H5: =SUMIFS(Data!$E$2:$E$2657,Data!$B$2:$B$2657,$A5,Data!$A$2:$A$2657,$E5-1,Data!$D$2:$D$2657,"Transmission")-SUMIFS(Data!$F$2:$F$2657,Data!$B$2:$B$2657,$A5,Data!$A$2:$A$2657,$E5-1)+SUMIFS(Data!$G$2:$G$2657,Data!$B$2:$B$2657,$A5,Data!$A$2:$A$2657,$E5-1,Data!$D$2:$D$2657,"Transmission") -> 22.439354 | I5: =SUMIFS(Data!$E$2:$E$2657,Data!$B$2:$B$2657,$A5,Data!$A$2:$A$2657,$E5-0,Data!$D$2:$D$2657,"Transmission")-SUMIFS(Data!$F$2:$F$2657,Data!$B$2:$B$2657,$A5,Data!$A$2:$A$2657,$E5-0)+SUMIFS(Data!$G$2:$G$2657,Data!$B$2:$B$2657,$A5,Data!$A$2:$A$2657,$E5-0,Data!$D$2:$D$2657,"Transmission") -> 1.136378
A6: Wisconsin Public Service | B6: American Transmission Company LLC | C6: Began operations 2001-01-01 | D6: U.S. Department of Energy, joint transmission paper, 2009 update: https://www.energy.gov/sites/prod/files/2015/03/f20/Paper%20Joint%20Transmission%202009%20update.pdf ; SEC 10-K405 for fiscal 2001: https://www.sec.gov/Archives/edgar/data/61339/000006133902000004/yearend.htm. Per the DOE summary, the four utilities listed contributed transmission assets; NSP-Wisconsin is not among them. | E6: 2001 | F6: =SUMIFS(Data!$F$2:$F$2657,Data!$B$2:$B$2657,$A6,Data!$A$2:$A$2657,$E6-1) -> 1.988676 | G6: =SUMIFS(Data!$F$2:$F$2657,Data!$B$2:$B$2657,$A6,Data!$A$2:$A$2657,$E6-0) -> 26.888973 | H6: =SUMIFS(Data!$E$2:$E$2657,Data!$B$2:$B$2657,$A6,Data!$A$2:$A$2657,$E6-1,Data!$D$2:$D$2657,"Transmission")-SUMIFS(Data!$F$2:$F$2657,Data!$B$2:$B$2657,$A6,Data!$A$2:$A$2657,$E6-1)+SUMIFS(Data!$G$2:$G$2657,Data!$B$2:$B$2657,$A6,Data!$A$2:$A$2657,$E6-1,Data!$D$2:$D$2657,"Transmission") -> 12.584422 | I6: =SUMIFS(Data!$E$2:$E$2657,Data!$B$2:$B$2657,$A6,Data!$A$2:$A$2657,$E6-0,Data!$D$2:$D$2657,"Transmission")-SUMIFS(Data!$F$2:$F$2657,Data!$B$2:$B$2657,$A6,Data!$A$2:$A$2657,$E6-0)+SUMIFS(Data!$G$2:$G$2657,Data!$B$2:$B$2657,$A6,Data!$A$2:$A$2657,$E6-0,Data!$D$2:$D$2657,"Transmission") -> 1.00659
A7: Wisconsin Power & Light | B7: American Transmission Company LLC | C7: Began operations 2001-01-01 | D7: U.S. Department of Energy, joint transmission paper, 2009 update: https://www.energy.gov/sites/prod/files/2015/03/f20/Paper%20Joint%20Transmission%202009%20update.pdf ; SEC 10-K405 for fiscal 2001: https://www.sec.gov/Archives/edgar/data/61339/000006133902000004/yearend.htm. Per the DOE summary, the four utilities listed contributed transmission assets; NSP-Wisconsin is not among them. | E7: 2001 | F7: =SUMIFS(Data!$F$2:$F$2657,Data!$B$2:$B$2657,$A7,Data!$A$2:$A$2657,$E7-1) -> 10.560805 | G7: =SUMIFS(Data!$F$2:$F$2657,Data!$B$2:$B$2657,$A7,Data!$A$2:$A$2657,$E7-0) -> 44.179696 | H7: =SUMIFS(Data!$E$2:$E$2657,Data!$B$2:$B$2657,$A7,Data!$A$2:$A$2657,$E7-1,Data!$D$2:$D$2657,"Transmission")-SUMIFS(Data!$F$2:$F$2657,Data!$B$2:$B$2657,$A7,Data!$A$2:$A$2657,$E7-1)+SUMIFS(Data!$G$2:$G$2657,Data!$B$2:$B$2657,$A7,Data!$A$2:$A$2657,$E7-1,Data!$D$2:$D$2657,"Transmission") -> 13.374626 | I7: =SUMIFS(Data!$E$2:$E$2657,Data!$B$2:$B$2657,$A7,Data!$A$2:$A$2657,$E7-0,Data!$D$2:$D$2657,"Transmission")-SUMIFS(Data!$F$2:$F$2657,Data!$B$2:$B$2657,$A7,Data!$A$2:$A$2657,$E7-0)+SUMIFS(Data!$G$2:$G$2657,Data!$B$2:$B$2657,$A7,Data!$A$2:$A$2657,$E7-0,Data!$D$2:$D$2657,"Transmission") -> 0.26231
A8: Madison Gas & Electric | B8: American Transmission Company LLC | C8: Began operations 2001-01-01 | D8: U.S. Department of Energy, joint transmission paper, 2009 update: https://www.energy.gov/sites/prod/files/2015/03/f20/Paper%20Joint%20Transmission%202009%20update.pdf ; SEC 10-K405 for fiscal 2001: https://www.sec.gov/Archives/edgar/data/61339/000006133902000004/yearend.htm. Per the DOE summary, the four utilities listed contributed transmission assets; NSP-Wisconsin is not among them. | E8: 2001 | F8: =SUMIFS(Data!$F$2:$F$2657,Data!$B$2:$B$2657,$A8,Data!$A$2:$A$2657,$E8-1) -> 2.146926 | G8: =SUMIFS(Data!$F$2:$F$2657,Data!$B$2:$B$2657,$A8,Data!$A$2:$A$2657,$E8-0) -> 9.74154 | H8: =SUMIFS(Data!$E$2:$E$2657,Data!$B$2:$B$2657,$A8,Data!$A$2:$A$2657,$E8-1,Data!$D$2:$D$2657,"Transmission")-SUMIFS(Data!$F$2:$F$2657,Data!$B$2:$B$2657,$A8,Data!$A$2:$A$2657,$E8-1)+SUMIFS(Data!$G$2:$G$2657,Data!$B$2:$B$2657,$A8,Data!$A$2:$A$2657,$E8-1,Data!$D$2:$D$2657,"Transmission") -> 4.51229 | I8: =SUMIFS(Data!$E$2:$E$2657,Data!$B$2:$B$2657,$A8,Data!$A$2:$A$2657,$E8-0,Data!$D$2:$D$2657,"Transmission")-SUMIFS(Data!$F$2:$F$2657,Data!$B$2:$B$2657,$A8,Data!$A$2:$A$2657,$E8-0)+SUMIFS(Data!$G$2:$G$2657,Data!$B$2:$B$2657,$A8,Data!$A$2:$A$2657,$E8-0,Data!$D$2:$D$2657,"Transmission") -> 1.013278
A9: Consumers Energy | B9: Michigan Electric Transmission Company (Trans-Elect) | C9: Sale closed 2002-05-01 (merger into METC LLC 2002-04-30) | D9: Renewable Energy World, “Trans-Elect finalizes purchases of Consumers Energy, AltaLink transmission systems”: https://www.renewableenergyworld.com/power-grid/transmission/trans-elect-finalizes-purchases-of-consumers-energy-altalink-transmission-systems/ ; CMS Energy SEC filing U-3A-2 amendment: https://www.sec.gov/Archives/edgar/data/201533/000020153302000008/u3a2cons-amendtxt.txt. The change in the Form 1 data appears in 2001, the year before the sale closed; the reason is not established from these data. | E9: 2001 | F9: =SUMIFS(Data!$F$2:$F$2657,Data!$B$2:$B$2657,$A9,Data!$A$2:$A$2657,$E9-1) -> 11.057502 | G9: =SUMIFS(Data!$F$2:$F$2657,Data!$B$2:$B$2657,$A9,Data!$A$2:$A$2657,$E9-0) -> 74.302484 | H9: =SUMIFS(Data!$E$2:$E$2657,Data!$B$2:$B$2657,$A9,Data!$A$2:$A$2657,$E9-1,Data!$D$2:$D$2657,"Transmission")-SUMIFS(Data!$F$2:$F$2657,Data!$B$2:$B$2657,$A9,Data!$A$2:$A$2657,$E9-1)+SUMIFS(Data!$G$2:$G$2657,Data!$B$2:$B$2657,$A9,Data!$A$2:$A$2657,$E9-1,Data!$D$2:$D$2657,"Transmission") -> 27.957262 | I9: =SUMIFS(Data!$E$2:$E$2657,Data!$B$2:$B$2657,$A9,Data!$A$2:$A$2657,$E9-0,Data!$D$2:$D$2657,"Transmission")-SUMIFS(Data!$F$2:$F$2657,Data!$B$2:$B$2657,$A9,Data!$A$2:$A$2657,$E9-0)+SUMIFS(Data!$G$2:$G$2657,Data!$B$2:$B$2657,$A9,Data!$A$2:$A$2657,$E9-0,Data!$D$2:$D$2657,"Transmission") -> 6.422397
A10: DTE Electric | B10: International Transmission Company (KKR and Trimaran affiliates) | C10: Sale closed 2003-02-28 | D10: Renewable Energy World, “DTE Energy to sell transmission business to KKR and Trimaran Capital Partners”: https://www.renewableenergyworld.com/energy-business/dte-energy-to-sell-transmission-business-to-kkr-and-trimaran-capital-partners/ ; DTE Energy SEC 8-K, July 14, 2003: https://www.sec.gov/Archives/edgar/data/936340/000095012403002308/k78162e8vk.htm. The change in the Form 1 data appears in 2002, the year before the sale closed; the reason is not established from these data. | E10: 2002 | F10: =SUMIFS(Data!$F$2:$F$2657,Data!$B$2:$B$2657,$A10,Data!$A$2:$A$2657,$E10-1) -> 56.898422 | G10: =SUMIFS(Data!$F$2:$F$2657,Data!$B$2:$B$2657,$A10,Data!$A$2:$A$2657,$E10-0) -> 116.69779 | H10: =SUMIFS(Data!$E$2:$E$2657,Data!$B$2:$B$2657,$A10,Data!$A$2:$A$2657,$E10-1,Data!$D$2:$D$2657,"Transmission")-SUMIFS(Data!$F$2:$F$2657,Data!$B$2:$B$2657,$A10,Data!$A$2:$A$2657,$E10-1)+SUMIFS(Data!$G$2:$G$2657,Data!$B$2:$B$2657,$A10,Data!$A$2:$A$2657,$E10-1,Data!$D$2:$D$2657,"Transmission") -> 20.00554 | I10: =SUMIFS(Data!$E$2:$E$2657,Data!$B$2:$B$2657,$A10,Data!$A$2:$A$2657,$E10-0,Data!$D$2:$D$2657,"Transmission")-SUMIFS(Data!$F$2:$F$2657,Data!$B$2:$B$2657,$A10,Data!$A$2:$A$2657,$E10-0)+SUMIFS(Data!$G$2:$G$2657,Data!$B$2:$B$2657,$A10,Data!$A$2:$A$2657,$E10-0,Data!$D$2:$D$2657,"Transmission") -> 8.669985
A11: Interstate Power & Light | B11: ITC Midwest LLC | C11: Sale closed 2007-12-20 | D11: Renewable Energy World, “Interstate Power and Light closes transmission assets sale with ITC Midwest”: https://www.renewableenergyworld.com/power-grid/transmission/interstate-power-and-light-closes-transmission-assets-sale-with-itc-midwest/ ; Alliant Energy SEC 8-K exhibit, February 6, 2008: https://www.sec.gov/Archives/edgar/data/352541/000010783208000017/form8k020608exh99pt1.htm | E11: 2008 | F11: =SUMIFS(Data!$F$2:$F$2657,Data!$B$2:$B$2657,$A11,Data!$A$2:$A$2657,$E11-1) -> 11.784338 | G11: =SUMIFS(Data!$F$2:$F$2657,Data!$B$2:$B$2657,$A11,Data!$A$2:$A$2657,$E11-0) -> 89.025434 | H11: =SUMIFS(Data!$E$2:$E$2657,Data!$B$2:$B$2657,$A11,Data!$A$2:$A$2657,$E11-1,Data!$D$2:$D$2657,"Transmission")-SUMIFS(Data!$F$2:$F$2657,Data!$B$2:$B$2657,$A11,Data!$A$2:$A$2657,$E11-1)+SUMIFS(Data!$G$2:$G$2657,Data!$B$2:$B$2657,$A11,Data!$A$2:$A$2657,$E11-1,Data!$D$2:$D$2657,"Transmission") -> 29.037831 | I11: =SUMIFS(Data!$E$2:$E$2657,Data!$B$2:$B$2657,$A11,Data!$A$2:$A$2657,$E11-0,Data!$D$2:$D$2657,"Transmission")-SUMIFS(Data!$F$2:$F$2657,Data!$B$2:$B$2657,$A11,Data!$A$2:$A$2657,$E11-0)+SUMIFS(Data!$G$2:$G$2657,Data!$B$2:$B$2657,$A11,Data!$A$2:$A$2657,$E11-0,Data!$D$2:$D$2657,"Transmission") -> 3.181181

Sheet Peer Group
A1: Peer group and selection criteria
A2: Selection criteria. The peer group was chosen on 2026-10-14 as the major investor-owned electric utilities in Michigan, Minnesota, Indiana, Wisconsin and Iowa; Commonwealth Edison and Ameren Illinois (Illinois) were added on 2026-10-25. The criteria below describe that selection in terms of the FERC Form 1 data; criterion 3 was set after the selection, at a level that separates the included and excluded utilities.
A3: 1. Investor-owned electric utility filing FERC Form 1, present in PUDL, with its service territory principally in one or more of the six states (Michigan, Minnesota, Indiana, Wisconsin, Iowa, Illinois).
A4: 2. Reports distribution plant (accounts 360–374) in service. Production and transmission plant are not required: Commonwealth Edison and Ameren Illinois have owned little or no generating plant since 2001–2005, and several peers transferred their transmission systems (see Transmission Transfers sheet). The 2026-10-24 version required production plant; the requirement was dropped when the two Illinois distribution utilities were added.
A5: 3. Distribution plant in service of at least $800 million at the end of 2025. Included utilities range from $823 million (Otter Tail Power) to $29,386 million (Commonwealth Edison); the largest excluded utility with distribution plant is Upper Peninsula Power at $286 million.
A7: Utility (series name) | B7: State | C7: FERC respondent ID(s) | D7: PUDL respondent name | E7: Plant data year | F7: Production plant ($mm) | G7: Transmission plant ($mm) | H7: Distribution plant ($mm)
A8: ALLETE (Minnesota Power) | B8: MN | C8: 307 | D8: ALLETE, Inc. | E8: 2025 | F8: 2785.4073 | G8: 1389.3261 | H8: 896.26573
A9: Ameren Illinois | B9: IL | C9: 6, 7, 20, 222 | D9: Central Illinois Light Company; Central Illinois Public Service Company; Illinois Power Company; Ameren Illinois Company | E9: 2025 | F9: 18.541838 | G9: 6283.4898 | H9: 9027.539
A10: Commonwealth Edison (ComEd) | B10: IL | C10: 165 | D10: Commonwealth Edison Company | E10: 2025 | G10: 7461.6664 | H10: 29386.227
A11: Consumers Energy | B11: MI | C11: 163 | D11: Consumers Energy Company | E11: 2025 | F11: 5353.9118 | H11: 13253.711
A12: DTE Electric | B12: MI | C12: 184 | D12: DTE Electric Company | E12: 2025 | F12: 11928.404 | G12: 49.083564 | H12: 15674.769
A13: Duke Energy Indiana | B13: IN | C13: 169 | D13: Duke Energy Indiana, Inc. | E13: 2025 | F13: 10724.324 | G13: 2747.275 | H13: 5805.4738
A14: Indiana Michigan Power | B14: IN/MI | C14: 201 | D14: Indiana Michigan Power Company | E14: 2025 | F14: 5465.1038 | G14: 2063.3811 | H14: 3842.0729
A15: Indianapolis Power & Light (AES Indiana) | B15: IN | C15: 279 | D15: Indianapolis Power & Light Company | E15: 2025 | F15: 4110.9949 | G15: 548.32141 | H15: 2930.6908
A16: Interstate Power & Light | B16: IA | C16: 19, 21, 220 | D16: IES Utilities Inc.; Interstate Power Company; Interstate Power and Light Company | E16: 2025 | F16: 6149.8963 | H16: 4695.8613
A17: Madison Gas & Electric | B17: WI | C17: 335 | D17: Madison Gas and Electric Company | E17: 2025 | F17: 1254.7521 | G17: 0 | H17: 956.19094
A18: MidAmerican Energy | B18: IA | C18: 251 | D18: MidAmerican Energy Company | E18: 2025 | F18: 18476.141 | G18: 3150.3145 | H18: 4700.3508
A19: NIPSCO | B19: IN | C19: 208 | D19: Northern Indiana Public Service Company | E19: 2025 | F19: 5416.6149 | G19: 2807.5909 | H19: 3935.8372
A20: NSP-Minnesota | B20: MN | C20: 229 | D20: Northern States Power Company (Minnesota) | E20: 2025 | F20: 13573.219 | G20: 5454.6358 | H20: 6965.6413
A21: NSP-Wisconsin | B21: WI | C21: 228 | D21: Northern States Power Company (Wisconsin) | E21: 2025 | F21: 534.63795 | G21: 1949.397 | H21: 1718.8527
A22: Otter Tail Power | B22: MN | C22: 272 | D22: Otter Tail Power Company | E22: 2025 | F22: 1590.5157 | G22: 846.15177 | H22: 822.60295
A23: Southern Indiana Gas & Electric | B23: IN | C23: 242 | D23: Southern Indiana Gas and Electric Company | E23: 2025 | F23: 1915.8841 | G23: 730.58596 | H23: 1446.1124
A24: Wisconsin Electric Power | B24: WI | C24: 280 | D24: Wisconsin Electric Power Company | E24: 2025 | F24: 4725.8156 | H24: 7020.9586
A25: Wisconsin Power & Light | B25: WI | C25: 219 | D25: Wisconsin Power and Light Company | E25: 2025 | F25: 6302.336 | H25: 3734.8132
A26: Wisconsin Public Service | B26: WI | C26: 187 | D26: Wisconsin Public Service Corporation | E26: 2025 | F26: 3621.6029 | H26: 2700.4862
A28: Excluded FERC Form 1 respondents in the six states considered
A29: Respondent | B29: Reason excluded | C29: FERC respondent ID(s) | D29: PUDL respondent name | E29: Plant data year (latest) | F29: Production plant ($mm) | G29: Transmission plant ($mm) | H29: Distribution plant ($mm)
A30: Upper Peninsula Power Company | B30: Criterion 3 | C30: 188 | D30: Upper Peninsula Power Company | E30: 2025 | F30: 107.62912 | H30: 286.34099
A31: Upper Michigan Energy Resources Company | B31: Criterion 3 | C31: 368 | D31: upper michigan energy resources company (pudl determined) | E31: 2025 | F31: 272.10424 | H31: 267.85165
A32: Edison Sault Electric Company | B32: Criterion 3; last year in PUDL is 2009 | C32: 14 | D32: Edison Sault Electric Company | E32: 2009 | F32: 17.335709 | H32: 68.022257
A33: Northwestern Wisconsin Electric Company | B33: Criterion 3 | C33: 399 | D33: Northwestern Wisconsin Electric Company | E33: 2025 | F33: 4.212778 | G33: 23.40332 | H33: 56.152841
A34: Superior Water, Light and Power Company | B34: Criterion 3 | C34: 395 | D34: Superior Water, Light and Power Company | E34: 2025 | F34: 1.457154 | G34: 36.916477 | H34: 50.131176
A35: Michigan Electric Transmission Company | B35: Criterion 2: transmission plant only | C35: 324, 100, 95, 91 | D35: Michigan Electric Transmission Company LLC (10/06); Michigan Electric Transmission Company, LLC; Michigan Electric Transmission Company LLC (12/9/03); Michigan Electric Transmission Company (04/02) | E35: 2025 | G35: 3987.6769
A36: AEP Indiana Michigan Transmission Company | B36: Criterion 2: transmission plant only | C36: 192 | D36: AEP Indiana Michigan Transmission Company, Inc. | E36: 2025 | G36: 4507.8016
A37: Commonwealth Edison Company of Indiana | B37: Criterion 2: transmission plant only | C37: 166 | D37: Commonwealth Edison Company of Indiana, Inc. | E37: 2025 | G37: 99.100461
A38: Indiana-Kentucky Electric Corporation | B38: Criterion 2: no distribution plant | C38: 444, 409 | D38: indiana-kentucky electric corporation; Indiana-Kentucky Electric Corporation | E38: 2025 | F38: 1688.0839 | G38: 31.412225
A39: Wisconsin River Power Company | B39: Criterion 2: no distribution plant | C39: 189 | D39: Wisconsin River Power Company | E39: 2025 | F39: 51.556341 | G39: 0 | H39: 0
A40: Mt. Carmel Public Utility Co | B40: Criterion 3 | C40: 397 | D40: Mt. Carmel Public Utility Co | E40: 2025 | G40: 8.482387 | H40: 31.940679
A41: Ameren Transmission Company of Illinois | B41: Criterion 2: transmission plant only | C41: 328 | D41: Ameren Transmission Company of Illinois | E41: 2025 | G41: 2175.5266
A42: Electric Energy, Inc. | B42: Criterion 2: no distribution plant; last year in PUDL is 2012 | C42: 321 | D42: Electric Energy, Inc. | E42: 2012 | F42: 482.32887 | G42: 20.878105 | H42: 0.427787
A43: Illinois Power Generating Company | B43: Criterion 2: no distribution plant; last year in PUDL is 2013 | C43: 223 | D43: Illinois Power Generating Company | E43: 2013 | F43: 2134.2551
A44: South Beloit Water, Gas and Electric Company | B44: Criterion 1: no electric plant reported in PUDL; last year in PUDL is 2007 | C44: 36 | D44: South Beloit Water, Gas and Electric Company | E44: 2007
A46: Plant figures: PUDL v2026.10.0 core_ferc1__yearly_plant_in_service_sched204, ending balance of reported line items, by account range. For Michigan Electric Transmission Company, Indiana-Kentucky Electric Corporation and other multi-ID respondents, the latest year across their IDs is shown. Blank = no amount reported.

Sheet Category Map
A1: Category | B1: O&M accounts (FERC Form 1 pp. 320–323) | C1: Depreciation: p. 336 plant function
A2: Transmission | B2: 560–573 incl. 561.1–561.8, 565 transmission of electricity by others, 569.1–569.4; load dispatching 1994–2011 (unnumbered in PUDL); energy storage lines labeled transmission | C2: transmission
A3: Distribution | B3: 580–598; energy storage lines labeled distribution | C3: distribution
A4: RTO/market operation | B4: 575.1–575.8, 576.1–576.5 | C4: regional transmission and market operation
A5: Customer accounts, service & sales | B5: 901–905, 907–910, 911–916 | C5: (none)
A6: A&G and general | B6: 920–935 (922 and 929 as credits) | C6: general, intangible, common plant – electric
A7: Excluded: generation | B7: 500–557 (steam, nuclear, hydraulic, other generation, other power supply incl. fuel 501, 518, 547 and purchased power 555, 555.1, 556, 557); 577–578 energy storage; 2024–25 solar, wind, other renewable and storage generation lines | C7: steam, nuclear, hydraulic conventional, hydraulic pumped storage, other production, solar, wind, other renewable, energy storage

Sheet Data
A1: Year | B1: Utility | C1: State | D1: Category | E1: O&M ($mm) | F1: of which acct 565 ($mm) | G1: Depreciation & amortization ($mm)
A2: 1995 | B2: ALLETE (Minnesota Power) | C2: MN | D2: A&G and general | E2: 30.61807 | F2: 0 | G2: 7.324776
A3: 1995 | B3: ALLETE (Minnesota Power) | C3: MN | D3: Customer accounts, service & sales | E3: 20.637863 | F3: 0 | G3: 0
A4: 1995 | B4: ALLETE (Minnesota Power) | C4: MN | D4: Distribution | E4: 14.165218 | F4: 0 | G4: 7.442834
A5: 1995 | B5: ALLETE (Minnesota Power) | C5: MN | D5: Transmission | E5: 5.534161 | F5: 0.243549 | G5: 3.995863
A6: 1995 | B6: Ameren Illinois | C6: IL | D6: A&G and general | E6: 222.13539 | F6: 0 | G6: 20.03741
A7: 1995 | B7: Ameren Illinois | C7: IL | D7: Customer accounts, service & sales | E7: 48.200476 | F7: 0 | G7: 0
A8: 1995 | B8: Ameren Illinois | C8: IL | D8: Distribution | E8: 79.048644 | F8: 0 | G8: 62.607227
A9: 1995 | B9: Ameren Illinois | C9: IL | D9: Transmission | E9: 18.639925 | F9: 0.007368 | G9: 16.302175
A10: 1995 | B10: Commonwealth Edison (ComEd) | C10: IL | D10: A&G and general | E10: 565.68825 | F10: 0 | G10: 24.2878
A11: 1995 | B11: Commonwealth Edison (ComEd) | C11: IL | D11: Customer accounts, service & sales | E11: 167.98233 | F11: 0 | G11: 0
A12: 1995 | B12: Commonwealth Edison (ComEd) | C12: IL | D12: Distribution | E12: 192.08628 | F12: 0 | G12: 183.7477
A13: 1995 | B13: Commonwealth Edison (ComEd) | C13: IL | D13: Transmission | E13: 45.5486 | F13: 0.222104 | G13: 53.903639
... A2657: 2025 | B2657: Wisconsin Public Service | C2657: WI | D2657: Transmission | E2657: 181.41132 | F2657: 174.78458 | G2657: 0
